Workbook
Name IQ_CH: 110000
Name IQ_CQ: 5000
Name IQ_CY: 10000
Name IQ_DAILY: 500000
Name IQ_FH: 100000
Name IQ_FQ: 500
Name IQ_FY: 1000
Name IQ_LTM: 2000
Name IQ_MONTH: 15000
Name IQ_NTM: 6000
Name IQ_WEEK: 50000
Name IQ_YTD: 3000

Sheet FSM Data Input_Empty
C2: ="Financial Statement Model for "&D5 -> Financial Statement Model for Apple
C3: $ in thousands except per share
C5: Company name | D5: Apple
C6: Ticker | D6: AAPL
C7: Circ break 1=off, 0=on | D7: 1
C8: Latest closing share price | D8: 299.24
C9: Latest closing share price date | D9: 43500
C10: Latest fiscal year end date | D10: 45947
C11: Shares outstanding (millions) | D11: 14776.353
C13: INCOME STATEMENT
C14: Fiscal year | D14: =E14-1 -> 2023 | E14: =F14-1 -> 2024 | F14: =YEAR(D10) -> 2025
C15: Fiscal year end date | D15: =EOMONTH(E15,-12) -> 45230 | E15: =EOMONTH(F15,-12) -> 45596 | F15: =D10 -> 45947
C17: Revenue | D17: 383285 | E17: 391035 | F17: 416161
C18: Cost of sales (enter as -) | D18: -214137 | E18: -210352 | F18: -220960
C19: Gross Profit | D19: =SUM(D17:D18) -> 169148 | E19: =SUM(E17:E18) -> 180683 | F19: =SUM(F17:F18) -> 195201
C20: Research & development (enter as -) | D20: -29915 | E20: -31370 | F20: -34550
C21: Selling, general & administrative (enter as -) | D21: -24932 | E21: -26097 | F21: -27601
C22: Operating profit (EBIT) | D22: =SUM(D19:D21) -> 114301 | E22: =SUM(E19:E21) -> 123216 | F22: =SUM(F19:F21) -> 133050
C23: Interest income | D23: 0 | E23: 0 | F23: 0
C24: Interest expense (enter as -) | D24: 0 | E24: 0 | F24: 0
C25: Other expense, net (enter as -) | D25: -565 | E25: 269 | F25: -321
C26: Pretax profit | D26: =SUM(D22:D25) -> 113736 | E26: =SUM(E22:E25) -> 123485 | F26: =SUM(F22:F25) -> 132729
C27: Taxes (enter expense as -) | D27: -16741 | E27: -29749 | F27: -20719
C28: Net income | D28: =SUM(D26:D27) -> 96995 | E28: =SUM(E26:E27) -> 93736 | F28: =SUM(F26:F27) -> 112010
C30: Depreciation & amortization | D30: 11519 | E30: 11445 | F30: 11698
C31: EBITDA | D31: =D30+D22 -> 125820 | E31: =E30+E22 -> 134661 | F31: =F30+F22 -> 144748
C32: Stock based compensation | D32: 10833 | E32: 11688 | F32: 12863
C33: Adjusted EBITDA | D33: =D31+D32 -> 136653 | E33: =E31+E32 -> 146349 | F33: =F31+F32 -> 157611
C35: Growth rates & margins
C36: Revenue growth | E36: =E17/D17-1 -> 0.020219941 | F36: =F17/E17-1 -> 0.064255118
C37: Gross profit margin | D37: =D19/D17 -> 0.4413113 | E37: =E19/E17 -> 0.4620635 | F37: =F19/F17 -> 0.46905164
C38: R&D % of sales | D38: =-(D20/D17) -> 0.078048971 | E38: =-(E20/E17) -> 0.080222998 | F38: =-(F20/F17) -> 0.083020754
C39: SG&A % of sales | D39: =-(D21/D17) -> 0.065048202 | E39: =-(E21/E17) -> 0.066738272 | F39: =-(F21/F17) -> 0.066322889
C40: Tax rate | D40: =-(D27/D26) -> 0.14719174 | E40: =-(E27/E26) -> 0.24091185 | F40: =-(F27/F26) -> 0.15610002
C42: BALANCE SHEET
C43: =C14 -> Fiscal year | E43: 2024A | F43: 2025A
C44: =C15 -> Fiscal year end date | E44: =E15 -> 45596 | F44: =F15 -> 45947
C45: Cash & equivalents, ST and LT marketable securities | E45: =29943+35228+91479 -> 156650 | F45: =35934+18763+77723 -> 132420
C46: Accounts receivable | E46: 33410 | F46: 39777
C47: Inventories | E47: 7286 | F47: 5718
C48: Other current assets | E48: =32833+14287 -> 47120 | F48: =33180+14585 -> 47765
C49: Property, plant & equipment | E49: 45680 | F49: 49834
C50: Other non current assets | E50: 74834 | F50: 83727
C51: Total assets | E51: =SUM(E45:E50) -> 364980 | F51: =SUM(F45:F50) -> 359241
C53: Accounts payable | E53: 68960 | F53: 69860
C54: Other current liabilities | E54: 78304 | F54: 66387
C55: Deferred revenue (current and non current) | E55: 8249 | F55: 9055
C56: Commercial paper / revolver | E56: 9967 | F56: 7979
C57: Long term debt | E57: =10912+85750 -> 96662 | F57: =12350+78328 -> 90678
C58: Other non current liabilities | E58: 45888 | F58: 41549
C59: Total liabilities | E59: =SUM(E53:E58) -> 308030 | F59: =SUM(F53:F58) -> 285508
C61: Common stock | E61: 83276 | F61: 93568
C62: Retained earnings | E62: -19154 | F62: -14264
C63: Other comprehensive income | E63: -7172 | F63: -5571
C64: Total equity | E64: =SUM(E61:E63) -> 56950 | F64: =SUM(F61:F63) -> 73733
C66: Balance check | E66: =ROUND(E51-E59-E64,3) -> 0 | F66: =ROUND(F51-F59-F64,3) -> 0
C68: Additional data
C69: Capital expenditures (enter as +) | D69: 10959 | E69: 9447 | F69: 12715
C70: D&A related only to PP&E (enter as -) | D70: -8500 | E70: -8200 | F70: -8000 | H70: Depreciation on PP&E - Note 5, Apple FY2025 10-K p.39 (rounded to $0.1B)
C71: Dividends | D71: -14996 | E71: -15218 | F71: -15413 | H71: Statement of Shareholders' Equity - Apple FY2025 10-K p.32 (dividends declared)
C72: Repurchases | D72: -77046 | E72: -95846 | F72: -90052 | H72: Statement of Shareholders' Equity - Apple FY2025 10-K p.32 (repurchases)
C73: Weighted average interest rate on commercial paper | E73: 0.05 | F73: 0.0419

Sheet FSM Forecasting_Empty
C2: ="Financial Statement Model for "&D5 -> Financial Statement Model for Apple
C3: $ in thousands except per share
C5: Company name | D5: Apple
C6: Ticker | D6: AAPL
C7: Circ break 1=off, 0=on | D7: 1
C8: Latest closing share price | D8: 296.42
C9: Latest closing share price date | D9: 46189
C10: Latest fiscal year end date | D10: 45927
C11: Shares outstanding (millions) | D11: 14776.353
C13: INCOME STATEMENT
C14: Fiscal year | D14: =E14-1 -> 2023 | E14: =F14-1 -> 2024 | F14: =YEAR(D10) -> 2025 | G14: =F14+1 -> 2026 | H14: =G14+1 -> 2027 | I14: =H14+1 -> 2028 | J14: =I14+1 -> 2029 | K14: =J14+1 -> 2030
C15: Fiscal year end date | D15: =EOMONTH(E15,-12) -> 45199 | E15: =EOMONTH(F15,-12) -> 45565 | F15: =D10 -> 45927 | G15: =EOMONTH(F15,12) -> 46295 | H15: =EOMONTH(G15,12) -> 46660 | I15: =EOMONTH(H15,12) -> 47026 | J15: =EOMONTH(I15,12) -> 47391 | K15: =EOMONTH(J15,12) -> 47756 | M15: WSP Comments
C17: Revenue | D17: 383285 | E17: 391035 | F17: 416161 | G17: =F17*(1+G36) -> 436969.05 | H17: =G17*(1+H36) -> 458817.5 | I17: =H17*(1+I36) -> 481758.38 | J17: =I17*(1+J36) -> 505846.3 | K17: =J17*(1+K36) -> 531138.61 | M17: Previous year's revenues x (1+revenue growth rate)
C18: Cost of sales (enter as -) | D18: -214137 | E18: -210352 | F18: -220960 | G18: =G19-G17 -> -232008 | H18: =H19-H17 -> -243608.4 | I18: =I19-I17 -> -255788.82 | J18: =J19-J17 -> -268578.26 | K18: =K19-K17 -> -282007.17 | M18: Plug = Revenue - Gross Profit
C19: Gross Profit | D19: =SUM(D17:D18) -> 169148 | E19: =SUM(E17:E18) -> 180683 | F19: =SUM(F17:F18) -> 195201 | G19: =G17*G37 -> 204961.05 | H19: =H17*H37 -> 215209.1 | I19: =I17*I37 -> 225969.56 | J19: =J17*J37 -> 237268.04 | K19: =K17*K37 -> 249131.44 | M19: Revenue x Gross Profit Margin forecast
C20: Research & development (enter as -) | D20: -29915 | E20: -31370 | F20: -34550 | G20: =-G38*G17 -> -36277.5 | H20: =-H38*H17 -> -38091.375 | I20: =-I38*I17 -> -39995.944 | J20: =-J38*J17 -> -41995.741 | K20: =-K38*K17 -> -44095.528 | M20: Revenue x R&D % of sales forecast
C21: Selling, general & administrative (enter as -) | D21: -24932 | E21: -26097 | F21: -27601 | G21: =-G17*G39 -> -28981.05 | H21: =-H17*H39 -> -30430.103 | I21: =-I17*I39 -> -31951.608 | J21: =-J17*J39 -> -33549.188 | K21: =-K17*K39 -> -35226.647 | M21: Revenue x SG&A % of sales forecast
C22: Operating profit (EBIT) | D22: =D19+D20+D21 -> 114301 | E22: =E19+E20+E21 -> 123216 | F22: =F19+F20+F21 -> 133050 | G22: =G19+G20+G21 -> 139702.5 | H22: =H19+H20+H21 -> 146687.63 | I22: =I19+I20+I21 -> 154022.01 | J22: =J19+J20+J21 -> 161723.11 | K22: =K19+K20+K21 -> 169809.26 | M22: Gross Profit - R&D - SG&A
C23: Interest income | D23: 0 | E23: 0 | F23: 0 | G23: =G156 -> 5112.0223 | H23: =H156 -> 6126.2494 | I23: =I156 -> 7340.2595 | J23: =J156 -> 8845.3404 | K23: =K156 -> 10663.488 | M23: Reference from interest on cash schedule
C24: Interest expense (enter as -) | D24: 0 | E24: 0 | F24: 0 | G24: =-G142 -> -3002.8831 | H24: =-H142 -> -3087.123 | I24: =-I142 -> -3087.123 | J24: =-J142 -> -3087.123 | K24: =-K142 -> -3087.123 | M24: Reference from interest expense schedule
C25: Other expense, net (enter as -) | D25: -565 | E25: 269 | F25: -321 | G25: =F25 -> -321 | H25: =G25 -> -321 | I25: =H25 -> -321 | J25: =I25 -> -321 | K25: =J25 -> -321 | M25: Straight-line
C26: Pretax profit | D26: =SUM(D22:D25) -> 113736 | E26: =SUM(E22:E25) -> 123485 | F26: =SUM(F22:F25) -> 132729 | G26: =SUM(G22:G25) -> 141490.64 | H26: =SUM(H22:H25) -> 149405.75 | I26: =SUM(I22:I25) -> 157954.14 | J26: =SUM(J22:J25) -> 167160.32 | K26: =SUM(K22:K25) -> 177064.63 | M26: EBIT + interest income less interest expense less other expense
C27: Taxes (enter expense as -) | D27: -16741 | E27: -29749 | F27: -20719 | G27: =-G40*G26 -> -22086.692 | H27: =-H40*H26 -> -23322.241 | I27: =-I40*I26 -> -24656.645 | J27: =-J40*J26 -> -26093.73 | K27: =-K40*K26 -> -27639.792 | M27: Pre-tax Profit x Tax Rate forecast
C28: Net income | D28: =SUM(D26:D27) -> 96995 | E28: =SUM(E26:E27) -> 93736 | F28: =SUM(F26:F27) -> 112010 | G28: =SUM(G26:G27) -> 119403.95 | H28: =SUM(H26:H27) -> 126083.51 | I28: =SUM(I26:I27) -> 133297.5 | J28: =SUM(J26:J27) -> 141066.59 | K28: =SUM(K26:K27) -> 149424.83 | M28: Pre-tax Profit less taxes
C30: Depreciation & amortization | D30: 11519 | E30: 11445 | F30: 11698 | G30: =G106 -> 12549.915 | H30: =H106 -> 13457.776 | I30: =I106 -> 14425.049 | J30: =J106 -> 15455.405 | K30: =K106 -> 16552.734 | M30: Reference from D&A schedule
C31: EBITDA | D31: =D22+D30 -> 125820 | E31: =E22+E30 -> 134661 | F31: =F22+F30 -> 144748 | G31: =G22+G30 -> 152252.42 | H31: =H22+H30 -> 160145.4 | I31: =I22+I30 -> 168447.06 | J31: =J22+J30 -> 177178.51 | K31: =K22+K30 -> 186362 | M31: EBIT + D&A
C32: Stock based compensation | D32: 10833 | E32: 11688 | F32: 12863 | G32: =F32*(1+G36) -> 13506.15 | H32: =G32*(1+H36) -> 14181.458 | I32: =H32*(1+I36) -> 14890.53 | J32: =I32*(1+J36) -> 15635.057 | K32: =J32*(1+K36) -> 16416.81 | M32: WSP assumption: grow SBC in-line with revenue growth
C33: Adjusted EBITDA | D33: =SUM(D31:D32) -> 136653 | E33: =SUM(E31:E32) -> 146349 | F33: =SUM(F31:F32) -> 157611 | G33: =SUM(G31:G32) -> 165758.57 | H33: =SUM(H31:H32) -> 174326.86 | I33: =SUM(I31:I32) -> 183337.59 | J33: =SUM(J31:J32) -> 192813.57 | K33: =SUM(K31:K32) -> 202778.81 | M33: EBITDA + Stock-based compensation
C35: Growth rates & margins
C36: Revenue growth | E36: =E17/D17-1 -> 0.020219941 | F36: =F17/E17-1 -> 0.064255118 | G36: 0.05 | H36: 0.05 | I36: 0.05 | J36: =I36 -> 0.05 | K36: =J36 -> 0.05 | M36: JP Morgan estimates through 2021; straight-line growth rate thereafter
C37: Gross profit margin | D37: =D19/D17 -> 0.4413113 | E37: =E19/E17 -> 0.4620635 | F37: =F19/F17 -> 0.46905164 | G37: =F37 -> 0.46905164 | H37: =G37 -> 0.46905164 | I37: =H37 -> 0.46905164 | J37: =I37 -> 0.46905164 | K37: =J37 -> 0.46905164 | M37: JP Morgan estimates through 2021; straight-line margin thereafter
C38: R&D % of sales | D38: =-D20/D17 -> 0.078048971 | E38: =-E20/E17 -> 0.080222998 | F38: =-F20/F17 -> 0.083020754 | G38: =F38 -> 0.083020754 | H38: =G38 -> 0.083020754 | I38: =H38 -> 0.083020754 | J38: =I38 -> 0.083020754 | K38: =J38 -> 0.083020754 | M38: JP Morgan estimates through 2021: straight-line margin thereafter
C39: SG&A % of sales | D39: =-D21/D17 -> 0.065048202 | E39: =-E21/E17 -> 0.066738272 | F39: =-F21/F17 -> 0.066322889 | G39: =F39 -> 0.066322889 | H39: =G39 -> 0.066322889 | I39: =H39 -> 0.066322889 | J39: =I39 -> 0.066322889 | K39: =J39 -> 0.066322889 | M39: JP Morgan estimates through 2021: straight-line margin thereafter
C40: Tax rate | D40: =-(D27/D26) -> 0.14719174 | E40: =-(E27/E26) -> 0.24091185 | F40: =-(F27/F26) -> 0.15610002 | G40: =F40 -> 0.15610002 | H40: =G40 -> 0.15610002 | I40: =H40 -> 0.15610002 | J40: =I40 -> 0.15610002 | K40: =J40 -> 0.15610002 | M40: JP Morgan estimates through 2021: straight-line margin thereafter
C42: BALANCE SHEET
C43: =C14 -> Fiscal year | E43: =E14 -> 2024 | F43: =F14 -> 2025 | G43: =G14 -> 2026 | H43: =H14 -> 2027 | I43: =I14 -> 2028 | J43: =J14 -> 2029 | K43: =K14 -> 2030
C44: =C15 -> Fiscal year end date | E44: =E15 -> 45565 | F44: =F15 -> 45927 | G44: =G15 -> 46295 | H44: =H15 -> 46660 | I44: =I15 -> 47026 | J44: =J15 -> 47391 | K44: =K15 -> 47756
C45: Cash & equivalents, ST and LT marketable securities | E45: =29943+35228+91479 -> 156650 | F45: =35934+18763+77723 -> 132420 | G45: =G90+F45 -> 159695.56 | H45: =H90+G45 -> 190375.83 | I45: =I90+H45 -> 229067.56 | J45: =J90+I45 -> 276380.46 | K45: =K90+J45 -> 332961.71 | M45: Reference from 'net change in cash' line on the cash flow statement
C46: Accounts receivable | E46: 33410 | F46: 39777 | G46: =F46*(1+G36) -> 41765.85 | H46: =G46*(1+H36) -> 43854.143 | I46: =H46*(1+I36) -> 46046.85 | J46: =I46*(1+J36) -> 48349.192 | K46: =J46*(1+K36) -> 50766.652 | M46: Grow in-line with revenue growth
C47: Inventories | E47: 7286 | F47: 5718 | G47: =F47*G18/F18 -> 6003.9 | H47: =G47*H18/G18 -> 6304.095 | I47: =H47*I18/H18 -> 6619.2998 | J47: =I47*J18/I18 -> 6950.2647 | K47: =J47*K18/J18 -> 7297.778 | M47: Grow in-line with cost of sales growth
C48: Other current assets | E48: =14287+32833 -> 47120 | F48: =14585+33180 -> 47765 | G48: =F48*(1+G36) -> 50153.25 | H48: =G48*(1+H36) -> 52660.913 | I48: =H48*(1+I36) -> 55293.958 | J48: =I48*(1+J36) -> 58058.656 | K48: =J48*(1+K36) -> 60961.589 | M48: Grow in-line with revenue growth
C49: Property, plant & equipment | E49: 45680 | F49: 49834 | G49: =G99 -> 54517.735 | H49: =H99 -> 59155.291 | I49: =I99 -> 63730.341 | J49: =J99 -> 68225.04 | K49: =K99 -> 72619.915 | M49: Reference from PP&E schedule
C50: Other non current assets | E50: 74834 | F50: 83727 | G50: =F50*(1+G36) -> 87913.35 | H50: =G50*(1+H36) -> 92309.018 | I50: =H50*(1+I36) -> 96924.468 | J50: =I50*(1+J36) -> 101770.69 | K50: =J50*(1+K36) -> 106859.23 | M50: Grow in-line with revenue growth
C51: Total assets | E51: =SUM(E45:E50) -> 364980 | F51: =SUM(F45:F50) -> 359241 | G51: =SUM(G45:G50) -> 400049.65 | H51: =SUM(H45:H50) -> 444659.29 | I51: =SUM(I45:I50) -> 497682.48 | J51: =SUM(J45:J50) -> 559734.3 | K51: =SUM(K45:K50) -> 631466.87
C53: Accounts payable | E53: 68960 | F53: 69860 | G53: =F53*G18/F18 -> 73353 | H53: =G53*H18/G18 -> 77020.65 | I53: =H53*I18/H18 -> 80871.683 | J53: =I53*J18/I18 -> 84915.267 | K53: =J53*K18/J18 -> 89161.03 | M53: Grow in-line with cost of sales growth
C54: Other current liabilities | E54: 78304 | F54: 66387 | G54: =F54*(1+G36) -> 69706.35 | H54: =G54*(1+H36) -> 73191.668 | I54: =H54*(1+I36) -> 76851.251 | J54: =I54*(1+J36) -> 80693.813 | K54: =J54*(1+K36) -> 84728.504 | M54: Grow in-line with revenue growth
C55: Deferred revenue (current and non current) | E55: 8249 | F55: 9055 | G55: =F55*(1+G36) -> 9507.75 | H55: =G55*(1+H36) -> 9983.1375 | I55: =H55*(1+I36) -> 10482.294 | J55: =I55*(1+J36) -> 11006.409 | K55: =J55*(1+K36) -> 11556.73 | M55: Grow in-line with revenue growth
C56: Commercial paper / revolver | E56: 9967 | F56: 7979 | G56: =G135 -> 12000 | H56: =H135 -> 12000 | I56: =I135 -> 12000 | J56: =J135 -> 12000 | K56: =K135 -> 12000 | M56: Reference EOP balance from CP/revolver schedule
C57: Long term debt (includes current portion) | E57: =10912+85750 -> 96662 | F57: =12350+78328 -> 90678 | G57: =F57 -> 90678 | H57: =G57 -> 90678 | I57: =H57 -> 90678 | J57: =I57 -> 90678 | K57: =J57 -> 90678 | M57: WSP assumption: straight-line
C58: Other non current liabilities | E58: 45888 | F58: 41549 | G58: =F58*(1+G36) -> 43626.45 | H58: =G58*(1+H36) -> 45807.773 | I58: =H58*(1+I36) -> 48098.161 | J58: =I58*(1+J36) -> 50503.069 | K58: =J58*(1+K36) -> 53028.223 | M58: Grow in-line with revenue growth
C59: Total liabilities | E59: =SUM(E53:E58) -> 308030 | F59: =SUM(F53:F58) -> 285508 | G59: =SUM(G53:G58) -> 298871.55 | H59: =SUM(H53:H58) -> 308681.23 | I59: =SUM(I53:I58) -> 318981.39 | J59: =SUM(J53:J58) -> 329796.56 | K59: =SUM(K53:K58) -> 341152.49
C61: Common stock | E61: 83276 | F61: 93568 | G61: =F61+G32 -> 107074.15 | H61: =G61+H32 -> 121255.61 | I61: =H61+I32 -> 136146.14 | J61: =I61+J32 -> 151781.19 | K61: =J61+K32 -> 168198 | M61: Increase by stock-based compensation forecasted in the I/S section
C62: Retained earnings | E62: -19154 | F62: -14264 | G62: =G119 -> -325.05281 | H62: =H119 -> 20293.457 | I62: =I119 -> 48125.955 | J62: =J119 -> 83727.548 | K62: =K119 -> 127687.38 | M62: Reference from Retained Earnings schedule
C63: Other comprehensive income | E63: -7172 | F63: -5571 | G63: =F63 -> -5571 | H63: =G63 -> -5571 | I63: =H63 -> -5571 | J63: =I63 -> -5571 | K63: =J63 -> -5571 | M63: WSP assumption: straight-line
C64: Total equity | E64: =SUM(E61:E63) -> 56950 | F64: =SUM(F61:F63) -> 73733 | G64: =SUM(G61:G63) -> 101178.1 | H64: =SUM(H61:H63) -> 135978.06 | I64: =SUM(I61:I63) -> 178701.09 | J64: =SUM(J61:J63) -> 229937.74 | K64: =SUM(K61:K63) -> 290314.39
C66: Balance check | E66: =ROUND(E51-E59-E64,3) -> 0 | F66: =ROUND(F51-F59-F64,3) -> 0 | G66: =ROUND(G51-G59-G64,3) -> 0 | H66: =ROUND(H51-H59-H64,3) -> 0 | I66: =ROUND(I51-I59-I64,3) -> 0 | J66: =ROUND(J51-J59-J64,3) -> 0 | K66: =ROUND(K51-K59-K64,3) -> 0
C68: CASH FLOW STATEMENT
C69: =C14 -> Fiscal year | G69: =G14 -> 2026 | H69: =H14 -> 2027 | I69: =I14 -> 2028 | J69: =J14 -> 2029 | K69: =K14 -> 2030
C70: =C15 -> Fiscal year end date | G70: =G15 -> 46295 | H70: =H15 -> 46660 | I70: =I15 -> 47026 | J70: =J15 -> 47391 | K70: =K15 -> 47756
C72: Net income | G72: =G28 -> 119403.95 | H72: =H28 -> 126083.51 | I72: =I28 -> 133297.5 | J72: =J28 -> 141066.59 | K72: =K28 -> 149424.83
C73: Depreciation and amortization | G73: =G30 -> 12549.915 | H73: =H30 -> 13457.776 | I73: =I30 -> 14425.049 | J73: =J30 -> 15455.405 | K73: =K30 -> 16552.734 | M73: Reference from the I/S
C74: Stock based compensation | G74: =G32 -> 13506.15 | H74: =H32 -> 14181.458 | I74: =I32 -> 14890.53 | J74: =J32 -> 15635.057 | K74: =K32 -> 16416.81
C75: Decreases / (Increases) in working capital assets | G75: =-1*(SUM(G46:G48)-SUM(F46:F48)) -> -4663 | H75: =-1*(SUM(H46:H48)-SUM(G46:G48)) -> -4896.15 | I75: =-1*(SUM(I46:I48)-SUM(H46:H48)) -> -5140.9575 | J75: =-1*(SUM(J46:J48)-SUM(I46:I48)) -> -5398.0054 | K75: =-1*(SUM(K46:K48)-SUM(J46:J48)) -> -5667.9056
C76: Increases / (Decreases) in working capital liabilities | G76: =SUM(G53:G55)-SUM(F53:F55) -> 7265.1 | H76: =SUM(H53:H55)-SUM(G53:G55) -> 7628.355 | I76: =SUM(I53:I55)-SUM(H53:H55) -> 8009.7728 | J76: =SUM(J53:J55)-SUM(I53:I55) -> 8410.2614 | K76: =SUM(K53:K55)-SUM(J53:J55) -> 8830.7745
C77: Other non current assets | G77: =-(G111) -> -8069.25 | H77: =-(H111) -> -8472.7125 | I77: =-(I111) -> -8896.3481 | J77: =-(J111) -> -9341.1655 | K77: =-(K111) -> -9808.2238 | M77: Reference from schedule NOT the B/S: Only include 'Additions' (as outflow)
C78: Other non current liabilities | G78: =G58-F58 -> 2077.45 | H78: =H58-G58 -> 2181.3225 | I78: =I58-H58 -> 2290.3886 | J78: =J58-I58 -> 2404.9081 | K78: =K58-J58 -> 2525.1535
C79: Cash from operating activities | G79: =SUM(G72:G78) -> 142070.31 | H79: =SUM(H72:H78) -> 150163.56 | I79: =SUM(I72:I78) -> 158875.93 | J79: =SUM(J72:J78) -> 168233.05 | K79: =SUM(K72:K78) -> 178274.18
C81: Capital expenditures | G81: =-(G97) -> -13350.75 | H81: =-(H97) -> -14018.288 | I81: =-(I97) -> -14719.202 | J81: =-(J97) -> -15455.162 | K81: =-(K97) -> -16227.92 | M81: Reference from PP&E schedule
C82: Cash from investing activities | G82: =IFERROR(G81,"NA") -> -13350.75 | H82: =IFERROR(H81,"NA") -> -14018.288 | I82: =IFERROR(I81,"NA") -> -14719.202 | J82: =IFERROR(J81,"NA") -> -15455.162 | K82: =IFERROR(K81,"NA") -> -16227.92
C84: Long term debt | G84: =G57-F57 -> 0 | H84: =H57-G57 -> 0 | I84: =I57-H57 -> 0 | J84: =J57-I57 -> 0 | K84: =K57-J57 -> 0
C85: Revolver | G85: =G56-F56 -> 4021 | H85: =H56-G56 -> 0 | I85: =I56-H56 -> 0 | J85: =J56-I56 -> 0 | K85: =K56-J56 -> 0 | M85: Reference from B/S
C86: Share repurchases | G86: =G118 -> -90052 | H86: =H118 -> -90052 | I86: =I118 -> -90052 | J86: =J118 -> -90052 | K86: =K118 -> -90052 | M86: Reference from Retained Earnings schedule
C87: Common dividends | G87: =G117 -> -15413 | H87: =H117 -> -15413 | I87: =I117 -> -15413 | J87: =J117 -> -15413 | K87: =K117 -> -15413 | M87: Reference from Retained Earnings schedule
C88: Cash from financing activities | G88: =SUM(G84:G87) -> -101444 | H88: =SUM(H84:H87) -> -105465 | I88: =SUM(I84:I87) -> -105465 | J88: =SUM(J84:J87) -> -105465 | K88: =SUM(K84:K87) -> -105465
C90: Net change in cash during period | G90: =G79+G82+G88 -> 27275.562 | H90: =H79+H82+H88 -> 30680.272 | I90: =I79+I82+I88 -> 38691.731 | J90: =J79+J82+J88 -> 47312.892 | K90: =K79+K82+K88 -> 56581.256
C92: PROPERTY, PLANT & EQUIPMENT
C93: =C14 -> Fiscal year | D93: =D14 -> 2023 | E93: =E14 -> 2024 | F93: =F14 -> 2025 | G93: =G14 -> 2026 | H93: =H14 -> 2027 | I93: =I14 -> 2028 | J93: =J14 -> 2029 | K93: =K14 -> 2030
C94: =C15 -> Fiscal year end date | D94: =D15 -> 45199 | E94: =E15 -> 45565 | F94: =F15 -> 45927 | G94: =G15 -> 46295 | H94: =H15 -> 46660 | I94: =I15 -> 47026 | J94: =J15 -> 47391 | K94: =K15 -> 47756
G95: Forecast
C96: Beginning of period | G96: =F99 -> 49834 | H96: =G99 -> 54517.735 | I96: =H99 -> 59155.291 | J96: =I99 -> 63730.341 | K96: =J99 -> 68225.04 | M96: BOP = Previous year EOP
C97: Plus: Capital expenditures | D97: 10959 | E97: 9447 | F97: 12715 | G97: =F97*(1+G36) -> 13350.75 | H97: =G97*(1+H36) -> 14018.288 | I97: =H97*(1+I36) -> 14719.202 | J97: =I97*(1+J36) -> 15455.162 | K97: =J97*(1+K36) -> 16227.92 | M97: JP Morgan through 2021; WSP assumption thereafter
C98: Less: Depreciation | D98: -8500 | E98: -8200 | F98: -8000 | G98: =-(G101*G97) -> -8667.015 | H98: =-(H101*H97) -> -9380.7315 | I98: =-(I101*I97) -> -10144.152 | J98: =-(J101*J97) -> -10960.463 | K98: =-(K101*K97) -> -11833.045 | M98: Capex x 'D&A related to PP&E as a % of capex' ratio (below)
C99: End of period | E99: =E49 -> 45680 | F99: =F49 -> 49834 | G99: =SUM(G96:G98) -> 54517.735 | H99: =SUM(H96:H98) -> 59155.291 | I99: =SUM(I96:I98) -> 63730.341 | J99: =SUM(J96:J98) -> 68225.04 | K99: =SUM(K96:K98) -> 72619.915 | M99: BOP + Capex - Depreciation
M100: Step
C101: D&A related to PP&E as a % of capex | D101: =-(D98/D97) -> 0.77561821 | E101: =-(E98/E97) -> 0.86800042 | F101: =-(F98/F97) -> 0.62917814 | G101: =F101+$M$101 -> 0.64917814 | H101: =G101+$M$101 -> 0.66917814 | I101: =H101+$M$101 -> 0.68917814 | J101: =I101+$M$101 -> 0.70917814 | K101: =J101+$M$101 -> 0.72917814 | M101: 0.02
C103: IMPUTING TOTAL DEPRECIATION & AMORTIZATION
C104: D&A not related to PP&E | D104: =D106+D98 -> 3019 | E104: =E106+E98 -> 3245 | F104: =F106+F98 -> 3698 | G104: =G105*G17 -> 3882.9 | H104: =H105*H17 -> 4077.045 | I104: =I105*I17 -> 4280.8973 | J104: =J105*J17 -> 4494.9421 | K104: =K105*K17 -> 4719.6892 | M104: Revenue x 'as % of revenue' assumption
C105: as % of revenue | D105: =D104/D17 -> 0.0078766453 | E105: =E104/E17 -> 0.0082984899 | F105: =F104/F17 -> 0.008885984 | G105: =F105 -> 0.008885984 | H105: =G105 -> 0.008885984 | I105: =H105 -> 0.008885984 | J105: =I105 -> 0.008885984 | K105: =J105 -> 0.008885984 | M105: Straight line last historical % of revenue - WSP assumption
C106: Depreciation & Amortization - Total | D106: =D30 -> 11519 | E106: =E30 -> 11445 | F106: =F30 -> 11698 | G106: =-G98+G104 -> 12549.915 | H106: =-H98+H104 -> 13457.776 | I106: =-I98+I104 -> 14425.049 | J106: =-J98+J104 -> 15455.405 | K106: =-K98+K104 -> 16552.734 | M106: D&A from PP&E + D&A not from PP&E
C108: OTHER NON-CURRENT ASSETS
C109: Beginning of period | G109: =F112 -> 83727 | H109: =G112 -> 87913.35 | I109: =H112 -> 92309.018 | J109: =I112 -> 96924.468 | K109: =J112 -> 101770.69 | M109: BOP = Previous year EOP
C110: Less: Amortization of intangible assets | G110: =-(G104) -> -3882.9 | H110: =-(H104) -> -4077.045 | I110: =-(I104) -> -4280.8973 | J110: =-(J104) -> -4494.9421 | K110: =-(K104) -> -4719.6892 | M110: Assume all D&A not from PP&E is in non-current assets
C111: Plus: Additions | G111: =G112-G110-G109 -> 8069.25 | H111: =H112-H110-H109 -> 8472.7125 | I111: =I112-I110-I109 -> 8896.3481 | J111: =J112-J110-J109 -> 9341.1655 | K111: =K112-K110-K109 -> 9808.2238 | M111: Because we already know the EOP balance, this is a plug: EOP - D&A not from PP&E - BOP
C112: End of period | E112: =E50 -> 74834 | F112: =F50 -> 83727 | G112: =G50 -> 87913.35 | H112: =H50 -> 92309.018 | I112: =I50 -> 96924.468 | J112: =J50 -> 101770.69 | K112: =K50 -> 106859.23 | M112: Referenced from balance sheet
C114: RETAINED EARNINGS
C115: Beginning of period | G115: =F119 -> -14264 | H115: =G119 -> -325.05281 | I115: =H119 -> 20293.457 | J115: =I119 -> 48125.955 | K115: =J119 -> 83727.548 | M115: BOP = Previous year EOP
C116: Plus: Net income | D116: =D28 -> 96995 | E116: =E28 -> 93736 | F116: =F28 -> 112010 | G116: =G28 -> 119403.95 | H116: =H28 -> 126083.51 | I116: =I28 -> 133297.5 | J116: =J28 -> 141066.59 | K116: =K28 -> 149424.83 | M116: Reference from income statement
C117: Less: Dividends | D117: -14996 | E117: -15218 | F117: -15413 | G117: =F117 -> -15413 | H117: =G117 -> -15413 | I117: =H117 -> -15413 | J117: =I117 -> -15413 | K117: =J117 -> -15413 | M117: WSP assumption: Straight-line last historical year dividends
C118: Less: Repurchases | D118: -77046 | E118: -95846 | F118: -90052 | G118: =F118 -> -90052 | H118: =G118 -> -90052 | I118: =H118 -> -90052 | J118: =I118 -> -90052 | K118: =J118 -> -90052 | M118: WSP assumption: Straight-line last historical year repurchases
C119: End of period | D119: =D62 -> 0 | E119: =E62 -> -19154 | F119: =F62 -> -14264 | G119: =SUM(G115:G118) -> -325.05281 | H119: =SUM(H115:H118) -> 20293.457 | I119: =SUM(I115:I118) -> 48125.955 | J119: =SUM(J115:J118) -> 83727.548 | K119: =SUM(K115:K118) -> 127687.38 | M119: BOP + net income - dividends - repurchases
...

Sheet FSM Forecasting_ProgressCheck1
C2: ="Financial Statement Model for "&D5 -> Financial Statement Model for Apple
C3: $ in thousands except per share
C5: Company name | D5: Apple
C6: Ticker | D6: AAPL
C7: Circ break 1=off, 0=on | D7: 1
C8: Latest closing share price | D8: 171.25
C9: Latest closing share price date | D9: 43500
C10: Latest fiscal year end date | D10: 43372
C11: Shares outstanding (millions) | D11: 4745.398
C13: INCOME STATEMENT
C14: Fiscal year | D14: =E14-1 -> 2016 | E14: =F14-1 -> 2017 | F14: =YEAR(D10) -> 2018 | G14: =F14+1 -> 2019 | H14: =G14+1 -> 2020 | I14: =H14+1 -> 2021 | J14: =I14+1 -> 2022 | K14: =J14+1 -> 2023
C15: Fiscal year end date | D15: =EOMONTH(E15,-12) -> 42643 | E15: =EOMONTH(F15,-12) -> 43008 | F15: =D10 -> 43372 | G15: =EOMONTH(F15,12) -> 43738 | H15: =EOMONTH(G15,12) -> 44104 | I15: =EOMONTH(H15,12) -> 44469 | J15: =EOMONTH(I15,12) -> 44834 | K15: =EOMONTH(J15,12) -> 45199 | M15: WSP Comments
C17: Revenue | D17: 215639 | E17: 229234 | F17: 265595 | G17: =F17*(1+G36) -> 254971.2 | H17: =G17*(1+H36) -> 270269.47 | I17: =H17*(1+I36) -> 288918.07 | J17: =I17*(1+J36) -> 308853.41 | K17: =J17*(1+K36) -> 330164.3 | M17: Previous year's revenues x (1+revenue growth rate)
C18: Cost of sales (enter as -) | D18: -131376 | E18: -141048 | F18: -163756 | G18: =G19-G17 -> -158592.09 | H18: =H19-H17 -> -167296.8 | I18: =I19-I17 -> -178551.36 | J18: =J19-J17 -> -190871.41 | K18: =K19-K17 -> -204041.54 | M18: Plug = Revenue - Gross Profit
C19: Gross Profit | D19: =SUM(D17:D18) -> 84263 | E19: =SUM(E17:E18) -> 88186 | F19: =SUM(F17:F18) -> 101839 | G19: =G17*G37 -> 96379.114 | H19: =H17*H37 -> 102972.67 | I19: =I17*I37 -> 110366.7 | J19: =J17*J37 -> 117982 | K19: =K17*K37 -> 126122.76 | M19: Revenue x Gross Profit Margin forecast
C20: Research & development (enter as -) | D20: -10045 | E20: -11581 | F20: -14236 | G20: =-G38*G17 -> -15808.214 | H20: =-H38*H17 -> -17026.977 | I20: =-I38*I17 -> -18201.838 | J20: =-J38*J17 -> -19457.765 | K20: =-K38*K17 -> -20800.351 | M20: Revenue x R&D % of sales forecast
C21: Selling, general & administrative (enter as -) | D21: -14194 | E21: -15261 | F21: -16705 | G21: =-G17*G39 -> -18867.869 | H21: =-H17*H39 -> -18648.594 | I21: =-I17*I39 -> -19935.347 | J21: =-J17*J39 -> -21310.885 | K21: =-K17*K39 -> -22781.337 | M21: Revenue x SG&A % of sales forecast
C22: Operating profit (EBIT) | D22: =D19+D20+D21 -> 60024 | E22: =E19+E20+E21 -> 61344 | F22: =F19+F20+F21 -> 70898 | G22: =G19+G20+G21 -> 61703.03 | H22: =H19+H20+H21 -> 67297.099 | I22: =I19+I20+I21 -> 72229.516 | J22: =J19+J20+J21 -> 77213.353 | K22: =K19+K20+K21 -> 82541.074 | M22: Gross Profit - R&D - SG&A
C23: Interest income | D23: 3999 | E23: 5201 | F23: 5686 | M23: Reference from interest on cash schedule
C24: Interest expense (enter as -) | D24: -1456 | E24: -2323 | F24: -3240 | M24: Reference from interest expense schedule
C25: Other expense, net (enter as -) | D25: -1195 | E25: -133 | F25: -441 | G25: =F25 -> -441 | H25: =G25 -> -441 | I25: =H25 -> -441 | J25: =I25 -> -441 | K25: =J25 -> -441 | M25: Straight-line
C26: Pretax profit | D26: =SUM(D22:D25) -> 61372 | E26: =SUM(E22:E25) -> 64089 | F26: =SUM(F22:F25) -> 72903 | G26: =SUM(G22:G25) -> 61262.03 | H26: =SUM(H22:H25) -> 66856.099 | I26: =SUM(I22:I25) -> 71788.516 | J26: =SUM(J22:J25) -> 76772.353 | K26: =SUM(K22:K25) -> 82100.074 | M26: EBIT + interest income less interest expense less other expense
C27: Taxes (enter expense as -) | D27: -15685 | E27: -15738 | F27: -13372 | G27: =-G40*G26 -> -10230.759 | H27: =-H40*H26 -> -11365.537 | I27: =-I40*I26 -> -12132.259 | J27: =-J40*J26 -> -12974.528 | K27: =-K40*K26 -> -13874.913 | M27: Pre-tax Profit x Tax Rate forecast
C28: Net income | D28: =SUM(D26:D27) -> 45687 | E28: =SUM(E26:E27) -> 48351 | F28: =SUM(F26:F27) -> 59531 | G28: =SUM(G26:G27) -> 51031.271 | H28: =SUM(H26:H27) -> 55490.562 | I28: =SUM(I26:I27) -> 59656.257 | J28: =SUM(J26:J27) -> 63797.825 | K28: =SUM(K26:K27) -> 68225.162 | M28: Pre-tax Profit less taxes
C30: Depreciation & amortization | D30: 10505 | E30: 10157 | F30: 10903 | M30: Reference from D&A schedule
C31: EBITDA | D31: =D22+D30 -> 70529 | E31: =E22+E30 -> 71501 | F31: =F22+F30 -> 81801 | G31: =G22+G30 -> 61703.03 | H31: =H22+H30 -> 67297.099 | I31: =I22+I30 -> 72229.516 | J31: =J22+J30 -> 77213.353 | K31: =K22+K30 -> 82541.074 | M31: EBIT + D&A
C32: Stock based compensation | D32: 4210 | E32: 4840 | F32: 5340 | G32: =F32*(1+G36) -> 5126.4 | H32: =G32*(1+H36) -> 5433.984 | I32: =H32*(1+I36) -> 5808.9289 | J32: =I32*(1+J36) -> 6209.745 | K32: =J32*(1+K36) -> 6638.2174 | M32: WSP assumption: grow SBC in-line with revenue growth
C33: Adjusted EBITDA | D33: =SUM(D31:D32) -> 74739 | E33: =SUM(E31:E32) -> 76341 | F33: =SUM(F31:F32) -> 87141 | G33: =SUM(G31:G32) -> 66829.43 | H33: =SUM(H31:H32) -> 72731.083 | I33: =SUM(I31:I32) -> 78038.445 | J33: =SUM(J31:J32) -> 83423.098 | K33: =SUM(K31:K32) -> 89179.292 | M33: EBITDA + Stock-based compensation
C35: Growth rates & margins
C36: Revenue growth | E36: =E17/D17-1 -> 0.063045182 | F36: =F17/E17-1 -> 0.15861958 | G36: -0.04 | H36: 0.06 | I36: 0.069 | J36: =I36 -> 0.069 | K36: =J36 -> 0.069 | M36: JP Morgan estimates through 2021; straight-line growth rate thereafter
C37: Gross profit margin | D37: =D19/D17 -> 0.39075956 | E37: =E19/E17 -> 0.3846986 | F37: =F19/F17 -> 0.38343719 | G37: 0.378 | H37: 0.381 | I37: 0.382 | J37: =I37 -> 0.382 | K37: =J37 -> 0.382 | M37: JP Morgan estimates through 2021; straight-line margin thereafter
C38: R&D % of sales | D38: =-D20/D17 -> 0.046582483 | E38: =-E20/E17 -> 0.050520429 | F38: =-F20/F17 -> 0.053600407 | G38: 0.062 | H38: 0.063 | I38: 0.063 | J38: =I38 -> 0.063 | K38: =J38 -> 0.063 | M38: JP Morgan estimates through 2021: straight-line margin thereafter
C39: SG&A % of sales | D39: =-D21/D17 -> 0.065822973 | E39: =-E21/E17 -> 0.066573894 | F39: =-F21/F17 -> 0.062896515 | G39: 0.074 | H39: 0.069 | I39: 0.069 | J39: =I39 -> 0.069 | K39: =J39 -> 0.069 | M39: JP Morgan estimates through 2021: straight-line margin thereafter
C40: Tax rate | D40: =-(D27/D26) -> 0.25557257 | E40: =-(E27/E26) -> 0.24556476 | F40: =-(F27/F26) -> 0.18342181 | G40: 0.167 | H40: 0.17 | I40: 0.169 | J40: =I40 -> 0.169 | K40: =J40 -> 0.169 | M40: JP Morgan estimates through 2021: straight-line margin thereafter
C42: BALANCE SHEET
C43: =C14 -> Fiscal year | E43: =E14 -> 2017 | F43: =F14 -> 2018 | G43: =G14 -> 2019 | H43: =H14 -> 2020 | I43: =I14 -> 2021 | J43: =J14 -> 2022 | K43: =K14 -> 2023
C44: =C15 -> Fiscal year end date | E44: =E15 -> 43008 | F44: =F15 -> 43372 | G44: =G15 -> 43738 | H44: =H15 -> 44104 | I44: =I15 -> 44469 | J44: =J15 -> 44834 | K44: =K15 -> 45199
C45: Cash & equivalents, ST and LT marketable securities | E45: =20289+53892+194714 -> 268895 | F45: =25913+40388+170799 -> 237100 | G45: =G90+F45 -> 290535.04 | H45: =H90+G45 -> 355782.51 | I45: =I90+H45 -> 426721.43 | J45: =J90+I45 -> 502672.04 | K45: =K90+J45 -> 583888.53 | M45: Reference from 'net change in cash' line on the cash flow statement
C46: Accounts receivable | E46: 17874 | F46: 23186 | G46: =F46*(1+G36) -> 22258.56 | H46: =G46*(1+H36) -> 23594.074 | I46: =H46*(1+I36) -> 25222.065 | J46: =I46*(1+J36) -> 26962.387 | K46: =J46*(1+K36) -> 28822.792 | M46: Grow in-line with revenue growth
C47: Inventories | E47: 4855 | F47: 3956 | G47: =F47*G18/F18 -> 3831.2507 | H47: =G47*H18/G18 -> 4041.5383 | I47: =H47*I18/H18 -> 4313.4248 | J47: =I47*J18/I18 -> 4611.0512 | K47: =J47*K18/J18 -> 4929.2137 | M47: Grow in-line with cost of sales growth
C48: Other current assets | E48: =17799+13936 -> 31735 | F48: =25809+12087 -> 37896 | G48: =F48*(1+G36) -> 36380.16 | H48: =G48*(1+H36) -> 38562.97 | I48: =H48*(1+I36) -> 41223.815 | J48: =I48*(1+J36) -> 44068.258 | K48: =J48*(1+K36) -> 47108.967 | M48: Grow in-line with revenue growth
C49: Property, plant & equipment | E49: 33783 | F49: 41304 | M49: Reference from PP&E schedule
C50: Other non current assets | E50: 18177 | F50: 22283 | G50: =F50*(1+G36) -> 21391.68 | H50: =G50*(1+H36) -> 22675.181 | I50: =H50*(1+I36) -> 24239.768 | J50: =I50*(1+J36) -> 25912.312 | K50: =J50*(1+K36) -> 27700.262 | M50: Grow in-line with revenue growth
C51: Total assets | E51: =SUM(E45:E50) -> 375319 | F51: =SUM(F45:F50) -> 365725 | G51: =SUM(G45:G50) -> 374396.69 | H51: =SUM(H45:H50) -> 444656.28 | I51: =SUM(I45:I50) -> 521720.5 | J51: =SUM(J45:J50) -> 604226.05 | K51: =SUM(K45:K50) -> 692449.76
C53: Accounts payable | E53: 44242 | F53: 55888 | G53: =F53*G18/F18 -> 54125.617 | H53: =G53*H18/G18 -> 57096.435 | I53: =H53*I18/H18 -> 60937.484 | J53: =I53*J18/I18 -> 65142.171 | K53: =J53*K18/J18 -> 69636.98 | M53: Grow in-line with cost of sales growth
C54: Other current liabilities | E54: 30551 | F54: 32687 | G54: =F54*(1+G36) -> 31379.52 | H54: =G54*(1+H36) -> 33262.291 | I54: =H54*(1+I36) -> 35557.389 | J54: =I54*(1+J36) -> 38010.849 | K54: =J54*(1+K36) -> 40633.598 | M54: Grow in-line with revenue growth
C55: Deferred revenue (current and non current) | E55: =7548+2836 -> 10384 | F55: =7543+2797 -> 10340 | G55: =F55*(1+G36) -> 9926.4 | H55: =G55*(1+H36) -> 10521.984 | I55: =H55*(1+I36) -> 11248.001 | J55: =I55*(1+J36) -> 12024.113 | K55: =J55*(1+K36) -> 12853.777 | M55: Grow in-line with revenue growth
C56: Commercial paper / revolver | E56: 11977 | F56: 11964 | M56: Reference from revolver schedule
C57: Long term debt (includes current portion) | E57: =6496+97207 -> 103703 | F57: =8784+93735 -> 102519 | G57: =F57 -> 102519 | H57: =G57 -> 102519 | I57: =H57 -> 102519 | J57: =I57 -> 102519 | K57: =J57 -> 102519 | M57: WSP assumption: straight-line
C58: Other non current liabilities | E58: 40415 | F58: 45180 | G58: =F58*(1+G36) -> 43372.8 | H58: =G58*(1+H36) -> 45975.168 | I58: =H58*(1+I36) -> 49147.455 | J58: =I58*(1+J36) -> 52538.629 | K58: =J58*(1+K36) -> 56163.794 | M58: Grow in-line with revenue growth
C59: Total liabilities | E59: =SUM(E53:E58) -> 241272 | F59: =SUM(F53:F58) -> 258578 | G59: =SUM(G53:G58) -> 241323.34 | H59: =SUM(H53:H58) -> 249374.88 | I59: =SUM(I53:I58) -> 259409.33 | J59: =SUM(J53:J58) -> 270234.76 | K59: =SUM(K53:K58) -> 281807.15
C61: Common stock | E61: 35867 | F61: 40201 | G61: =F61+G32 -> 45327.4 | H61: =G61+H32 -> 50761.384 | I61: =H61+I32 -> 56570.313 | J61: =I61+J32 -> 62780.058 | K61: =J61+K32 -> 69418.275 | M61: Increase by stock-based compensation forecasted in the I/S section
C62: Retained earnings | E62: 98330 | F62: 70400 | M62: Reference from Retained Earnings schedule
C63: Other comprehensive income | E63: -150 | F63: -3454 | G63: =F63 -> -3454 | H63: =G63 -> -3454 | I63: =H63 -> -3454 | J63: =I63 -> -3454 | K63: =J63 -> -3454 | M63: WSP assumption: straight-line
C64: Total equity | E64: =SUM(E61:E63) -> 134047 | F64: =SUM(F61:F63) -> 107147 | G64: =SUM(G61:G63) -> 41873.4 | H64: =SUM(H61:H63) -> 47307.384 | I64: =SUM(I61:I63) -> 53116.313 | J64: =SUM(J61:J63) -> 59326.058 | K64: =SUM(K61:K63) -> 65964.275
C66: Balance check | E66: =ROUND(E51-E59-E64,3) -> 0 | F66: =ROUND(F51-F59-F64,3) -> 0 | G66: =ROUND(G51-G59-G64,3) -> 91199.951 | H66: =ROUND(H51-H59-H64,3) -> 147974.01 | I66: =ROUND(I51-I59-I64,3) -> 209194.86 | J66: =ROUND(J51-J59-J64,3) -> 274665.23 | K66: =ROUND(K51-K59-K64,3) -> 344678.34
C68: CASH FLOW STATEMENT
C69: =C14 -> Fiscal year | G69: =G14 -> 2019 | H69: =H14 -> 2020 | I69: =I14 -> 2021 | J69: =J14 -> 2022 | K69: =K14 -> 2023
C70: =C15 -> Fiscal year end date | G70: =G15 -> 43738 | H70: =H15 -> 44104 | I70: =I15 -> 44469 | J70: =J15 -> 44834 | K70: =K15 -> 45199
C72: Net income | G72: =G28 -> 51031.271 | H72: =H28 -> 55490.562 | I72: =I28 -> 59656.257 | J72: =J28 -> 63797.825 | K72: =K28 -> 68225.162
C73: Depreciation and amortization
C74: Stock based compensation | G74: =G32 -> 5126.4 | H74: =H32 -> 5433.984 | I74: =I32 -> 5808.9289 | J74: =J32 -> 6209.745 | K74: =K32 -> 6638.2174
C75: Decreases / (Increases) in working capital assets | G75: =-1*(SUM(G46:G48)-SUM(F46:F48)) -> 2568.0293 | H75: =-1*(SUM(H46:H48)-SUM(G46:G48)) -> -3728.6108 | I75: =-1*(SUM(I46:I48)-SUM(H46:H48)) -> -4560.7225 | J75: =-1*(SUM(J46:J48)-SUM(I46:I48)) -> -4882.392 | K75: =-1*(SUM(K46:K48)-SUM(J46:J48)) -> -5219.277
C76: Increases / (Decreases) in working capital liabilities | G76: =SUM(G53:G55)-SUM(F53:F55) -> -3483.4631 | H76: =SUM(H53:H55)-SUM(G53:G55) -> 5449.1728 | I76: =SUM(I53:I55)-SUM(H53:H55) -> 6862.1646 | J76: =SUM(J53:J55)-SUM(I53:I55) -> 7434.2583 | K76: =SUM(K53:K55)-SUM(J53:J55) -> 7947.2222
C77: Other non current assets | M77: Reference additions to 'other non-current assets' from schedule
C78: Other non current liabilities | G78: =G58-F58 -> -1807.2 | H78: =H58-G58 -> 2602.368 | I78: =I58-H58 -> 3172.2866 | J78: =J58-I58 -> 3391.1744 | K78: =K58-J58 -> 3625.1654
C79: Cash from operating activities | G79: =SUM(G72:G78) -> 53435.038 | H79: =SUM(H72:H78) -> 65247.476 | I79: =SUM(I72:I78) -> 70938.915 | J79: =SUM(J72:J78) -> 75950.611 | K79: =SUM(K72:K78) -> 81216.49
C81: Capital expenditures
C82: Cash from investing activities | G82: =IFERROR(G81,"NA") -> 0 | H82: =IFERROR(H81,"NA") -> 0 | I82: =IFERROR(I81,"NA") -> 0 | J82: =IFERROR(J81,"NA") -> 0 | K82: =IFERROR(K81,"NA") -> 0
C84: Long term debt | G84: =G57-F57 -> 0 | H84: =H57-G57 -> 0 | I84: =I57-H57 -> 0 | J84: =J57-I57 -> 0 | K84: =K57-J57 -> 0
C85: Revolver
C86: Share repurchases
C87: Common dividends
C88: Cash from financing activities | G88: =SUM(G84:G87) -> 0 | H88: =SUM(H84:H87) -> 0 | I88: =SUM(I84:I87) -> 0 | J88: =SUM(J84:J87) -> 0 | K88: =SUM(K84:K87) -> 0
C90: Net change in cash during period | G90: =G79+G82+G88 -> 53435.038 | H90: =H79+H82+H88 -> 65247.476 | I90: =I79+I82+I88 -> 70938.915 | J90: =J79+J82+J88 -> 75950.611 | K90: =K79+K82+K88 -> 81216.49

Sheet FSM Forecasting_ProgressCheck2
C2: ="Financial Statement Model for "&D5 -> Financial Statement Model for Apple
C3: $ in thousands except per share
C5: Company name | D5: Apple
C6: Ticker | D6: AAPL
C7: Circ break 1=off, 0=on | D7: 1
C8: Latest closing share price | D8: 171.25
C9: Latest closing share price date | D9: 43500
C10: Latest fiscal year end date | D10: 43372
C11: Shares outstanding (millions) | D11: 4745.398
C13: INCOME STATEMENT
C14: Fiscal year | D14: =E14-1 -> 2016 | E14: =F14-1 -> 2017 | F14: =YEAR(D10) -> 2018 | G14: =F14+1 -> 2019 | H14: =G14+1 -> 2020 | I14: =H14+1 -> 2021 | J14: =I14+1 -> 2022 | K14: =J14+1 -> 2023
C15: Fiscal year end date | D15: =EOMONTH(E15,-12) -> 42643 | E15: =EOMONTH(F15,-12) -> 43008 | F15: =D10 -> 43372 | G15: =EOMONTH(F15,12) -> 43738 | H15: =EOMONTH(G15,12) -> 44104 | I15: =EOMONTH(H15,12) -> 44469 | J15: =EOMONTH(I15,12) -> 44834 | K15: =EOMONTH(J15,12) -> 45199 | M15: WSP Comments
C17: Revenue | D17: 215639 | E17: 229234 | F17: 265595 | G17: =F17*(1+G36) -> 254971.2 | H17: =G17*(1+H36) -> 270269.47 | I17: =H17*(1+I36) -> 288918.07 | J17: =I17*(1+J36) -> 308853.41 | K17: =J17*(1+K36) -> 330164.3 | M17: Previous year's revenues x (1+revenue growth rate)
C18: Cost of sales (enter as -) | D18: -131376 | E18: -141048 | F18: -163756 | G18: =G19-G17 -> -158592.09 | H18: =H19-H17 -> -167296.8 | I18: =I19-I17 -> -178551.36 | J18: =J19-J17 -> -190871.41 | K18: =K19-K17 -> -204041.54 | M18: Plug = Revenue - Gross Profit
C19: Gross Profit | D19: =SUM(D17:D18) -> 84263 | E19: =SUM(E17:E18) -> 88186 | F19: =SUM(F17:F18) -> 101839 | G19: =G37*G17 -> 96379.114 | H19: =H37*H17 -> 102972.67 | I19: =I37*I17 -> 110366.7 | J19: =J37*J17 -> 117982 | K19: =K37*K17 -> 126122.76 | M19: Revenue x Gross Profit Margin forecast
C20: Research & development (enter as -) | D20: -10045 | E20: -11581 | F20: -14236 | G20: =-(G38*G17) -> -15808.214 | H20: =-(H38*H17) -> -17026.977 | I20: =-(I38*I17) -> -18201.838 | J20: =-(J38*J17) -> -19457.765 | K20: =-(K38*K17) -> -20800.351 | M20: Revenue x R&D % of sales forecast
C21: Selling, general & administrative (enter as -) | D21: -14194 | E21: -15261 | F21: -16705 | G21: =-(G39*G17) -> -18867.869 | H21: =-(H39*H17) -> -18648.594 | I21: =-(I39*I17) -> -19935.347 | J21: =-(J39*J17) -> -21310.885 | K21: =-(K39*K17) -> -22781.337 | M21: Revenue x SG&A % of sales forecast
C22: Operating profit (EBIT) | D22: =D19+D20+D21 -> 60024 | E22: =E19+E20+E21 -> 61344 | F22: =F19+F20+F21 -> 70898 | G22: =G19+G20+G21 -> 61703.03 | H22: =H19+H20+H21 -> 67297.099 | I22: =I19+I20+I21 -> 72229.516 | J22: =J19+J20+J21 -> 77213.353 | K22: =K19+K20+K21 -> 82541.074 | M22: Gross Profit - R&D - SG&A
C23: Interest income | D23: 3999 | E23: 5201 | F23: 5686 | M23: Reference from interest on cash schedule
C24: Interest expense (enter as -) | D24: -1456 | E24: -2323 | F24: -3240 | M24: Reference from interest expense schedule
C25: Other expense, net (enter as -) | D25: -1195 | E25: -133 | F25: -441 | G25: =F25 -> -441 | H25: =G25 -> -441 | I25: =H25 -> -441 | J25: =I25 -> -441 | K25: =J25 -> -441 | M25: Straight-line
C26: Pretax profit | D26: =SUM(D22:D25) -> 61372 | E26: =SUM(E22:E25) -> 64089 | F26: =SUM(F22:F25) -> 72903 | G26: =SUM(G22:G25) -> 61262.03 | H26: =SUM(H22:H25) -> 66856.099 | I26: =SUM(I22:I25) -> 71788.516 | J26: =SUM(J22:J25) -> 76772.353 | K26: =SUM(K22:K25) -> 82100.074 | M26: EBIT + interest income less interest expense less other expense
C27: Taxes (enter expense as -) | D27: -15685 | E27: -15738 | F27: -13372 | G27: =-G40*G26 -> -10230.759 | H27: =-H40*H26 -> -11365.537 | I27: =-I40*I26 -> -12132.259 | J27: =-J40*J26 -> -12974.528 | K27: =-K40*K26 -> -13874.913 | M27: Pre-tax Profit x Tax Rate forecast
C28: Net income | D28: =SUM(D26:D27) -> 45687 | E28: =SUM(E26:E27) -> 48351 | F28: =SUM(F26:F27) -> 59531 | G28: =SUM(G26:G27) -> 51031.271 | H28: =SUM(H26:H27) -> 55490.562 | I28: =SUM(I26:I27) -> 59656.257 | J28: =SUM(J26:J27) -> 63797.825 | K28: =SUM(K26:K27) -> 68225.162 | M28: Pre-tax Profit less taxes
C30: Depreciation & amortization | D30: 10505 | E30: 10157 | F30: 10903 | G30: =G106 -> 11085.02 | H30: =H106 -> 11711.891 | I30: =I106 -> 12226.381 | J30: =J106 -> 13365.451 | K30: =K106 -> 14603.503 | M30: Reference from D&A schedule
C31: EBITDA | D31: =D22+D30 -> 70529 | E31: =E22+E30 -> 71501 | F31: =F22+F30 -> 81801 | G31: =G22+G30 -> 72788.051 | H31: =H22+H30 -> 79008.989 | I31: =I22+I30 -> 84455.897 | J31: =J22+J30 -> 90578.804 | K31: =K22+K30 -> 97144.578 | M31: EBIT + D&A
C32: Stock based compensation | D32: 4210 | E32: 4840 | F32: 5340 | G32: =F32*(1+G36) -> 5126.4 | H32: =G32*(1+H36) -> 5433.984 | I32: =H32*(1+I36) -> 5808.9289 | J32: =I32*(1+J36) -> 6209.745 | K32: =J32*(1+K36) -> 6638.2174 | M32: WSP assumption: grow SBC in-line with revenue growth
C33: Adjusted EBITDA | D33: =SUM(D31:D32) -> 74739 | E33: =SUM(E31:E32) -> 76341 | F33: =SUM(F31:F32) -> 87141 | G33: =SUM(G31:G32) -> 77914.451 | H33: =SUM(H31:H32) -> 84442.973 | I33: =SUM(I31:I32) -> 90264.826 | J33: =SUM(J31:J32) -> 96788.549 | K33: =SUM(K31:K32) -> 103782.8 | M33: EBITDA + Stock-based compensation
C35: Growth rates & margins
C36: Revenue growth | E36: =E17/D17-1 -> 0.063045182 | F36: =F17/E17-1 -> 0.15861958 | G36: -0.04 | H36: 0.06 | I36: 0.069 | J36: =I36 -> 0.069 | K36: =J36 -> 0.069 | M36: JP Morgan estimates through 2021; straight-line growth rate thereafter
C37: Gross profit margin | D37: =D19/D17 -> 0.39075956 | E37: =E19/E17 -> 0.3846986 | F37: =F19/F17 -> 0.38343719 | G37: 0.378 | H37: 0.381 | I37: 0.382 | J37: =I37 -> 0.382 | K37: =J37 -> 0.382 | M37: JP Morgan estimates through 2021; straight-line margin thereafter
C38: R&D % of sales | D38: =-D20/D17 -> 0.046582483 | E38: =-E20/E17 -> 0.050520429 | F38: =-F20/F17 -> 0.053600407 | G38: 0.062 | H38: 0.063 | I38: 0.063 | J38: =I38 -> 0.063 | K38: =J38 -> 0.063 | M38: JP Morgan estimates through 2021: straight-line margin thereafter
C39: SG&A % of sales | D39: =-D21/D17 -> 0.065822973 | E39: =-E21/E17 -> 0.066573894 | F39: =-F21/F17 -> 0.062896515 | G39: 0.074 | H39: 0.069 | I39: 0.069 | J39: =I39 -> 0.069 | K39: =J39 -> 0.069 | M39: JP Morgan estimates through 2021: straight-line margin thereafter
C40: Tax rate | D40: =-(D27/D26) -> 0.25557257 | E40: =-(E27/E26) -> 0.24556476 | F40: =-(F27/F26) -> 0.18342181 | G40: 0.167 | H40: 0.17 | I40: 0.169 | J40: =I40 -> 0.169 | K40: =J40 -> 0.169 | M40: JP Morgan estimates through 2021: straight-line margin thereafter
C42: BALANCE SHEET
C43: =C14 -> Fiscal year | E43: =E14 -> 2017 | F43: =F14 -> 2018 | G43: =G14 -> 2019 | H43: =H14 -> 2020 | I43: =I14 -> 2021 | J43: =J14 -> 2022 | K43: =K14 -> 2023
C44: =C15 -> Fiscal year end date | E44: =E15 -> 43008 | F44: =F15 -> 43372 | G44: =G15 -> 43738 | H44: =H15 -> 44104 | I44: =I15 -> 44469 | J44: =J15 -> 44834 | K44: =K15 -> 45199
C45: Cash & equivalents, ST and LT marketable securities | E45: =20289+53892+194714 -> 268895 | F45: =25913+40388+170799 -> 237100 | G45: =F45+G90 -> 200896.5 | H45: =G45+H90 -> 174501.15 | I45: =H45+I90 -> 153748.09 | J45: =I45+J90 -> 137964.01 | K45: =J45+K90 -> 127420.53 | M45: Reference from 'net change in cash' line on the cash flow statement
C46: Accounts receivable | E46: 17874 | F46: 23186 | G46: =F46*(1+G36) -> 22258.56 | H46: =G46*(1+H36) -> 23594.074 | I46: =H46*(1+I36) -> 25222.065 | J46: =I46*(1+J36) -> 26962.387 | K46: =J46*(1+K36) -> 28822.792 | M46: Grow in-line with revenue growth
C47: Inventories | E47: 4855 | F47: 3956 | G47: =F47*(G18/F18) -> 3831.2507 | H47: =G47*(H18/G18) -> 4041.5383 | I47: =H47*(I18/H18) -> 4313.4248 | J47: =I47*(J18/I18) -> 4611.0512 | K47: =J47*(K18/J18) -> 4929.2137 | M47: Grow in-line with cost of sales growth
C48: Other current assets | E48: =17799+13936 -> 31735 | F48: =25809+12087 -> 37896 | G48: =F48*(1+G36) -> 36380.16 | H48: =G48*(1+H36) -> 38562.97 | I48: =H48*(1+I36) -> 41223.815 | J48: =I48*(1+J36) -> 44068.258 | K48: =J48*(1+K36) -> 47108.967 | M48: Grow in-line with revenue growth
C49: Property, plant & equipment | E49: 33783 | F49: 41304 | G49: =G99 -> 45042.86 | H49: =H99 -> 48611.182 | I49: =I99 -> 51947.568 | J49: =J99 -> 55218.714 | K49: =K99 -> 58399.733 | M49: Reference from PP&E schedule
C50: Other non current assets | E50: 18177 | F50: 22283 | G50: =F50*(1+G36) -> 21391.68 | H50: =G50*(1+H36) -> 22675.181 | I50: =H50*(1+I36) -> 24239.768 | J50: =I50*(1+J36) -> 25912.312 | K50: =J50*(1+K36) -> 27700.262 | M50: Grow in-line with revenue growth
C51: Total assets | E51: =SUM(E45:E50) -> 375319 | F51: =SUM(F45:F50) -> 365725 | G51: =SUM(G45:G50) -> 329801.01 | H51: =SUM(H45:H50) -> 311986.09 | I51: =SUM(I45:I50) -> 300694.73 | J51: =SUM(J45:J50) -> 294736.74 | K51: =SUM(K45:K50) -> 294381.5
C53: Accounts payable | E53: 44242 | F53: 55888 | G53: =F53*G18/F18 -> 54125.617 | H53: =G53*H18/G18 -> 57096.435 | I53: =H53*I18/H18 -> 60937.484 | J53: =I53*J18/I18 -> 65142.171 | K53: =J53*K18/J18 -> 69636.98 | M53: Grow in-line with cost of sales growth
C54: Other current liabilities | E54: 30551 | F54: 32687 | G54: =F54*(1+G36) -> 31379.52 | H54: =G54*(1+H36) -> 33262.291 | I54: =H54*(1+I36) -> 35557.389 | J54: =I54*(1+J36) -> 38010.849 | K54: =J54*(1+K36) -> 40633.598 | M54: Grow in-line with revenue growth
C55: Deferred revenue (current and non current) | E55: =7548+2836 -> 10384 | F55: =7543+2797 -> 10340 | G55: =F55*(1+G36) -> 9926.4 | H55: =G55*(1+H36) -> 10521.984 | I55: =H55*(1+I36) -> 11248.001 | J55: =I55*(1+J36) -> 12024.113 | K55: =J55*(1+K36) -> 12853.777 | M55: Grow in-line with revenue growth
C56: Commercial paper / revolver | E56: 11977 | F56: 11964 | M56: Reference from revolver schedule
C57: Long term debt (includes current portion) | E57: =6496+97207 -> 103703 | F57: =8784+93735 -> 102519 | G57: =F57 -> 102519 | H57: =G57 -> 102519 | I57: =H57 -> 102519 | J57: =I57 -> 102519 | K57: =J57 -> 102519 | M57: WSP assumption: straight-line
C58: Other non current liabilities | E58: 40415 | F58: 45180 | G58: =F58*(1+G36) -> 43372.8 | H58: =G58*(1+H36) -> 45975.168 | I58: =H58*(1+I36) -> 49147.455 | J58: =I58*(1+J36) -> 52538.629 | K58: =J58*(1+K36) -> 56163.794 | M58: Grow in-line with revenue growth
C59: Total liabilities | E59: =SUM(E53:E58) -> 241272 | F59: =SUM(F53:F58) -> 258578 | G59: =SUM(G53:G58) -> 241323.34 | H59: =SUM(H53:H58) -> 249374.88 | I59: =SUM(I53:I58) -> 259409.33 | J59: =SUM(J53:J58) -> 270234.76 | K59: =SUM(K53:K58) -> 281807.15
C61: Common stock | E61: 35867 | F61: 40201 | G61: =F61+G32 -> 45327.4 | H61: =G61+H32 -> 50761.384 | I61: =H61+I32 -> 56570.313 | J61: =I61+J32 -> 62780.058 | K61: =J61+K32 -> 69418.275 | M61: Increase by stock-based compensation forecasted in the I/S section
C62: Retained earnings | E62: 98330 | F62: 70400 | G62: =G119 -> 34640.271 | H62: =H119 -> 3339.8331 | I62: =I119 -> -23794.91 | J62: =J119 -> -46788.084 | K62: =K119 -> -65353.923 | M62: Reference from Retained Earnings schedule
C63: Other comprehensive income | E63: -150 | F63: -3454 | G63: =F63 -> -3454 | H63: =G63 -> -3454 | I63: =H63 -> -3454 | J63: =I63 -> -3454 | K63: =J63 -> -3454 | M63: WSP assumption: straight-line
C64: Total equity | E64: =SUM(E61:E63) -> 134047 | F64: =SUM(F61:F63) -> 107147 | G64: =SUM(G61:G63) -> 76513.671 | H64: =SUM(H61:H63) -> 50647.217 | I64: =SUM(I61:I63) -> 29321.403 | J64: =SUM(J61:J63) -> 12537.973 | K64: =SUM(K61:K63) -> 610.35268
C66: Balance check | E66: =ROUND(E51-E59-E64,3) -> 0 | F66: =ROUND(F51-F59-F64,3) -> 0 | G66: =ROUND(G51-G59-G64,3) -> 11964 | H66: =ROUND(H51-H59-H64,3) -> 11964 | I66: =ROUND(I51-I59-I64,3) -> 11964 | J66: =ROUND(J51-J59-J64,3) -> 11964 | K66: =ROUND(K51-K59-K64,3) -> 11964
C68: CASH FLOW STATEMENT
C69: =C14 -> Fiscal year | G69: =G14 -> 2019 | H69: =H14 -> 2020 | I69: =I14 -> 2021 | J69: =J14 -> 2022 | K69: =K14 -> 2023
C70: =C15 -> Fiscal year end date | G70: =G15 -> 43738 | H70: =H15 -> 44104 | I70: =I15 -> 44469 | J70: =J15 -> 44834 | K70: =K15 -> 45199
C72: Net income | G72: =G28 -> 51031.271 | H72: =H28 -> 55490.562 | I72: =I28 -> 59656.257 | J72: =J28 -> 63797.825 | K72: =K28 -> 68225.162
C73: Depreciation and amortization | G73: =G30 -> 11085.02 | H73: =H30 -> 11711.891 | I73: =I30 -> 12226.381 | J73: =J30 -> 13365.451 | K73: =K30 -> 14603.503
C74: Stock based compensation | G74: =G32 -> 5126.4 | H74: =H32 -> 5433.984 | I74: =I32 -> 5808.9289 | J74: =J32 -> 6209.745 | K74: =K32 -> 6638.2174
C75: Decreases / (Increases) in working capital assets | G75: =SUM(F46:F48)-SUM(G46:G48) -> 2568.0293 | H75: =SUM(G46:G48)-SUM(H46:H48) -> -3728.6108 | I75: =SUM(H46:H48)-SUM(I46:I48) -> -4560.7225 | J75: =SUM(I46:I48)-SUM(J46:J48) -> -4882.392 | K75: =SUM(J46:J48)-SUM(K46:K48) -> -5219.277
C76: Increases / (Decreases) in working capital liabilities | G76: =SUM(G53:G55)-SUM(F53:F55) -> -3483.4631 | H76: =SUM(H53:H55)-SUM(G53:G55) -> 5449.1728 | I76: =SUM(I53:I55)-SUM(H53:H55) -> 6862.1646 | J76: =SUM(J53:J55)-SUM(I53:I55) -> 7434.2583 | K76: =SUM(K53:K55)-SUM(J53:J55) -> 7947.2222
C77: Other non current assets | G77: =-G111 -> -647.56 | H77: =-H111 -> -2914.7136 | I77: =-I111 -> -3308.354 | J77: =-J111 -> -3536.6304 | K77: =-K111 -> -3780.6579 | M77: Reference additions to 'other non-current assets' from schedule
C78: Other non current liabilities | G78: =G58-F58 -> -1807.2 | H78: =H58-G58 -> 2602.368 | I78: =I58-H58 -> 3172.2866 | J78: =J58-I58 -> 3391.1744 | K78: =K58-J58 -> 3625.1654
C79: Cash from operating activities | G79: =SUM(G72:G78) -> 63872.498 | H79: =SUM(H72:H78) -> 74044.653 | I79: =SUM(I72:I78) -> 79856.941 | J79: =SUM(J72:J78) -> 85779.432 | K79: =SUM(K72:K78) -> 92039.335
C81: Capital expenditures | G81: =-G97 -> -13285 | H81: =-H97 -> -13649 | I81: =-I97 -> -13819 | J81: =-J97 -> -14772.511 | K81: =-K97 -> -15791.814
C82: Cash from investing activities | G82: =SUM(G81) -> -13285 | H82: =SUM(H81) -> -13649 | I82: =SUM(I81) -> -13819 | J82: =SUM(J81) -> -14772.511 | K82: =SUM(K81) -> -15791.814
C84: Long term debt | G84: =G57-F57 -> 0 | H84: =H57-G57 -> 0 | I84: =I57-H57 -> 0 | J84: =J57-I57 -> 0 | K84: =K57-J57 -> 0
C85: Revolver
C86: Share repurchases | G86: =G118 -> -73056 | H86: =H118 -> -73056 | I86: =I118 -> -73056 | J86: =J118 -> -73056 | K86: =K118 -> -73056
C87: Common dividends | G87: =G117 -> -13735 | H87: =H117 -> -13735 | I87: =I117 -> -13735 | J87: =J117 -> -13735 | K87: =K117 -> -13735
C88: Cash from financing activities | G88: =SUM(G84:G87) -> -86791 | H88: =SUM(H84:H87) -> -86791 | I88: =SUM(I84:I87) -> -86791 | J88: =SUM(J84:J87) -> -86791 | K88: =SUM(K84:K87) -> -86791
C90: Net change in cash during period | G90: =G79+G82+G88 -> -36203.502 | H90: =H79+H82+H88 -> -26395.347 | I90: =I79+I82+I88 -> -20753.059 | J90: =J79+J82+J88 -> -15784.079 | K90: =K79+K82+K88 -> -10543.479
C92: PROPERTY, PLANT & EQUIPMENT
C93: =C14 -> Fiscal year | D93: =D14 -> 2016 | E93: =E14 -> 2017 | F93: =F14 -> 2018 | G93: =G14 -> 2019 | H93: =H14 -> 2020 | I93: =I14 -> 2021 | J93: =J14 -> 2022 | K93: =K14 -> 2023
C94: =C15 -> Fiscal year end date | D94: =D15 -> 42643 | E94: =E15 -> 43008 | F94: =F15 -> 43372 | G94: =G15 -> 43738 | H94: =H15 -> 44104 | I94: =I15 -> 44469 | J94: =J15 -> 44834 | K94: =K15 -> 45199
G95: Forecast
C96: Beginning of period | G96: =F99 -> 41304 | H96: =G99 -> 45042.86 | I96: =H99 -> 48611.182 | J96: =I99 -> 51947.568 | K96: =J99 -> 55218.714 | M96: BOP = Previous year EOP
C97: Plus: Capital expenditures | D97: 12734 | E97: 12451 | F97: 13313 | G97: 13285 | H97: 13649 | I97: 13819 | J97: =I97*(1+J36) -> 14772.511 | K97: =J97*(1+K36) -> 15791.814 | M97: JP Morgan through 2021; WSP assumption thereafter
C98: Less: Depreciation | D98: -8300 | E98: -8200 | F98: -9300 | G98: =-(G101*G97) -> -9546.1402 | H98: =-(H101*H97) -> -10080.678 | I98: =-(I101*I97) -> -10482.614 | J98: =-(J101*J97) -> -11501.365 | K98: =-(K101*K97) -> -12610.795 | M98: Capex x 'D&A related to PP&E as a % of capex' ratio (below)
C99: End of period | E99: =E49 -> 33783 | F99: =F49 -> 41304 | G99: =SUM(G96:G98) -> 45042.86 | H99: =SUM(H96:H98) -> 48611.182 | I99: =SUM(I96:I98) -> 51947.568 | J99: =SUM(J96:J98) -> 55218.714 | K99: =SUM(K96:K98) -> 58399.733 | M99: BOP + Capex - Depreciation
M100: Step
C101: D&A related to PP&E as a % of capex | D101: =-(D98/D97) -> 0.65179834 | E101: =-(E98/E97) -> 0.65858164 | F101: =-(F98/F97) -> 0.69856531 | G101: =F101+$M$101 -> 0.71856531 | H101: =G101+$M$101 -> 0.73856531 | I101: =H101+$M$101 -> 0.75856531 | J101: =I101+$M$101 -> 0.77856531 | K101: =J101+$M$101 -> 0.79856531 | M101: 0.02
C103: IMPUTING TOTAL DEPRECIATION & AMORTIZATION
C104: D&A not related to PP&E | D104: =D106+D98 -> 2205 | E104: =E106+E98 -> 1957 | F104: =F106+F98 -> 1603 | G104: =G105*G17 -> 1538.88 | H104: =H105*H17 -> 1631.2128 | I104: =I105*I17 -> 1743.7665 | J104: =J105*J17 -> 1864.0864 | K104: =K105*K17 -> 1992.7083 | M104: Revenue x 'as % of revenue' assumption
C105: as % of revenue | D105: =D104/D17 -> 0.010225423 | E105: =E104/E17 -> 0.008537128 | F105: =F104/F17 -> 0.0060355052 | G105: =F105 -> 0.0060355052 | H105: =G105 -> 0.0060355052 | I105: =H105 -> 0.0060355052 | J105: =I105 -> 0.0060355052 | K105: =J105 -> 0.0060355052 | M105: Straight line last historical % of revenue - WSP assumption
C106: Depreciation & Amortization - Total | D106: =D30 -> 10505 | E106: =E30 -> 10157 | F106: =F30 -> 10903 | G106: =G104-G98 -> 11085.02 | H106: =H104-H98 -> 11711.891 | I106: =I104-I98 -> 12226.381 | J106: =J104-J98 -> 13365.451 | K106: =K104-K98 -> 14603.503 | M106: D&A from PP&E + D&A not from PP&E
C108: OTHER NON-CURRENT ASSETS
C109: Beginning of period | G109: =F112 -> 22283 | H109: =G112 -> 21391.68 | I109: =H112 -> 22675.181 | J109: =I112 -> 24239.768 | K109: =J112 -> 25912.312 | M109: BOP = Previous year EOP
C110: Less: D&A not related to PP&E | G110: =-G104 -> -1538.88 | H110: =-H104 -> -1631.2128 | I110: =-I104 -> -1743.7665 | J110: =-J104 -> -1864.0864 | K110: =-K104 -> -1992.7083 | M110: Assume all D&A not from PP&E is in non-current assets
C111: Plus: Additions | G111: =G112-G110-G109 -> 647.56 | H111: =H112-H110-H109 -> 2914.7136 | I111: =I112-I110-I109 -> 3308.354 | J111: =J112-J110-J109 -> 3536.6304 | K111: =K112-K110-K109 -> 3780.6579 | M111: Because we already know the EOP balance, this is a plug: EOP - D&A not from PP&E - BOP
C112: End of period | E112: =E50 -> 18177 | F112: =F50 -> 22283 | G112: =G50 -> 21391.68 | H112: =H50 -> 22675.181 | I112: =I50 -> 24239.768 | J112: =J50 -> 25912.312 | K112: =K50 -> 27700.262 | M112: Referenced from balance sheet
C114: RETAINED EARNINGS
C115: Beginning of period | G115: =F119 -> 70400 | H115: =G119 -> 34640.271 | I115: =H119 -> 3339.8331 | J115: =I119 -> -23794.91 | K115: =J119 -> -46788.084 | M115: BOP = Previous year EOP
C116: Plus: Net income | D116: =D28 -> 45687 | E116: =E28 -> 48351 | F116: =F28 -> 59531 | G116: =G28 -> 51031.271 | H116: =H28 -> 55490.562 | I116: =I28 -> 59656.257 | J116: =J28 -> 63797.825 | K116: =K28 -> 68225.162 | M116: Reference from income statement
C117: Less: Dividends | D117: -12188 | E117: -12803 | F117: -13735 | G117: =F117 -> -13735 | H117: =G117 -> -13735 | I117: =H117 -> -13735 | J117: =I117 -> -13735 | K117: =J117 -> -13735 | M117: WSP assumption: Straight-line last historical year dividends
C118: Less: Repurchases | D118: -29000 | E118: -33001 | F118: -73056 | G118: =F118 -> -73056 | H118: =G118 -> -73056 | I118: =H118 -> -73056 | J118: =I118 -> -73056 | K118: =J118 -> -73056 | M118: WSP assumption: Straight-line last historical year repurchases
C119: End of period | D119: =D62 -> 0 | E119: =E62 -> 98330 | F119: =F62 -> 70400 | G119: =SUM(G115:G118) -> 34640.271 | H119: =SUM(H115:H118) -> 3339.8331 | I119: =SUM(I115:I118) -> -23794.91 | J119: =SUM(J115:J118) -> -46788.084 | K119: =SUM(K115:K118) -> -65353.923 | M119: BOP + net income - dividends - repurchases
...

Sheet FSM Forecasting_Empty II
C2: ="Financial Statement Model for "&D5 -> Financial Statement Model for Apple
C3: $ in thousands except per share
C5: Company name | D5: Apple
C6: Ticker | D6: AAPL
D7: 1
C8: Latest closing share price | D8: 171.25
C9: Latest closing share price date | D9: 43500
C10: Latest fiscal year end date | D10: 43372
C11: Shares outstanding (millions) | D11: 4745.398
C13: INCOME STATEMENT
C14: Fiscal year | D14: =E14-1 -> 2016 | E14: =F14-1 -> 2017 | F14: =YEAR(D10) -> 2018 | G14: =F14+1 -> 2019 | H14: =G14+1 -> 2020 | I14: =H14+1 -> 2021 | J14: =I14+1 -> 2022 | K14: =J14+1 -> 2023
C15: Fiscal year end date | D15: =EOMONTH(E15,-12) -> 42643 | E15: =EOMONTH(F15,-12) -> 43008 | F15: =D10 -> 43372 | G15: =EOMONTH(F15,12) -> 43738 | H15: =EOMONTH(G15,12) -> 44104 | I15: =EOMONTH(H15,12) -> 44469 | J15: =EOMONTH(I15,12) -> 44834 | K15: =EOMONTH(J15,12) -> 45199 | M15: WSP Comments
C17: Revenue | D17: 215639 | E17: 229234 | F17: 265595 | G17: =F17*(1+G36) -> 254971.2 | H17: =G17*(1+H36) -> 270269.47 | I17: =H17*(1+I36) -> 288918.07 | J17: =I17*(1+J36) -> 308853.41 | K17: =J17*(1+K36) -> 330164.3 | M17: Previous year's revenues x (1+revenue growth rate)
C18: Cost of sales (enter as -) | D18: -131376 | E18: -141048 | F18: -163756 | G18: =G19-G17 -> -158592.09 | H18: =H19-H17 -> -167296.8 | I18: =I19-I17 -> -178551.36 | J18: =J19-J17 -> -190871.41 | K18: =K19-K17 -> -204041.54 | M18: Plug = Revenue - Gross Profit
C19: Gross Profit | D19: =SUM(D17:D18) -> 84263 | E19: =SUM(E17:E18) -> 88186 | F19: =SUM(F17:F18) -> 101839 | G19: =G17*G37 -> 96379.114 | H19: =H17*H37 -> 102972.67 | I19: =I17*I37 -> 110366.7 | J19: =J17*J37 -> 117982 | K19: =K17*K37 -> 126122.76 | M19: Revenue x Gross Profit Margin forecast
C20: Research & development (enter as -) | D20: -10045 | E20: -11581 | F20: -14236 | G20: =-G38*G17 -> -15808.214 | H20: =-H38*H17 -> -17026.977 | I20: =-I38*I17 -> -18201.838 | J20: =-J38*J17 -> -19457.765 | K20: =-K38*K17 -> -20800.351 | M20: Revenue x R&D % of sales forecast
C21: Selling, general & administrative (enter as -) | D21: -14194 | E21: -15261 | F21: -16705 | G21: =-G17*G39 -> -18867.869 | H21: =-H17*H39 -> -18648.594 | I21: =-I17*I39 -> -19935.347 | J21: =-J17*J39 -> -21310.885 | K21: =-K17*K39 -> -22781.337 | M21: Revenue x SG&A % of sales forecast
C22: Operating profit (EBIT) | D22: =D19+D20+D21 -> 60024 | E22: =E19+E20+E21 -> 61344 | F22: =F19+F20+F21 -> 70898 | G22: =G19+G20+G21 -> 61703.03 | H22: =H19+H20+H21 -> 67297.099 | I22: =I19+I20+I21 -> 72229.516 | J22: =J19+J20+J21 -> 77213.353 | K22: =K19+K20+K21 -> 82541.074 | M22: Gross Profit - R&D - SG&A
C23: Interest income | D23: 3999 | E23: 5201 | F23: 5686 | G23: =G156 -> 4744.4371 | H23: =H156 -> 4090.2133 | I23: =I156 -> 3592.0871 | J23: =J156 -> 3200.5876 | K23: =K156 -> 2913.2593 | M23: Reference from interest on cash schedule
C24: Interest expense (enter as -) | D24: -1456 | E24: -2323 | F24: -3240 | G24: =-G142 -> -3223.1469 | H24: =-H142 -> -3223.5393 | I24: =-I142 -> -3223.5393 | J24: =-J142 -> -3223.5393 | K24: =-K142 -> -3223.5393 | M24: Reference from interest expense schedule
C25: Other expense, net (enter as -) | D25: -1195 | E25: -133 | F25: -441 | G25: =F25 -> -441 | H25: =G25 -> -441 | I25: =H25 -> -441 | J25: =I25 -> -441 | K25: =J25 -> -441 | M25: Straight-line
C26: Pretax profit | D26: =SUM(D22:D25) -> 61372 | E26: =SUM(E22:E25) -> 64089 | F26: =SUM(F22:F25) -> 72903 | G26: =SUM(G22:G25) -> 62783.321 | H26: =SUM(H22:H25) -> 67722.773 | I26: =SUM(I22:I25) -> 72157.064 | J26: =SUM(J22:J25) -> 76749.401 | K26: =SUM(K22:K25) -> 81789.794 | M26: EBIT + interest income less interest expense less other expense
C27: Taxes (enter expense as -) | D27: -15685 | E27: -15738 | F27: -13372 | G27: =-G40*G26 -> -10484.815 | H27: =-H40*H26 -> -11512.871 | I27: =-I40*I26 -> -12194.544 | J27: =-J40*J26 -> -12970.649 | K27: =-K40*K26 -> -13822.475 | M27: Pre-tax Profit x Tax Rate forecast
C28: Net income | D28: =SUM(D26:D27) -> 45687 | E28: =SUM(E26:E27) -> 48351 | F28: =SUM(F26:F27) -> 59531 | G28: =SUM(G26:G27) -> 52298.506 | H28: =SUM(H26:H27) -> 56209.901 | I28: =SUM(I26:I27) -> 59962.52 | J28: =SUM(J26:J27) -> 63778.753 | K28: =SUM(K26:K27) -> 67967.319 | M28: Pre-tax Profit less taxes
C30: Depreciation & amortization | D30: 10505 | E30: 10157 | F30: 10903 | G30: =G106 -> 11085.02 | H30: =H106 -> 11711.891 | I30: =I106 -> 12226.381 | J30: =J106 -> 13365.451 | K30: =K106 -> 14603.503 | M30: Reference from D&A schedule
C31: EBITDA | D31: =D22+D30 -> 70529 | E31: =E22+E30 -> 71501 | F31: =F22+F30 -> 81801 | G31: =G22+G30 -> 72788.051 | H31: =H22+H30 -> 79008.989 | I31: =I22+I30 -> 84455.897 | J31: =J22+J30 -> 90578.804 | K31: =K22+K30 -> 97144.578 | M31: EBIT + D&A
C32: Stock based compensation | D32: 4210 | E32: 4840 | F32: 5340 | G32: =F32*(1+G36) -> 5126.4 | H32: =G32*(1+H36) -> 5433.984 | I32: =H32*(1+I36) -> 5808.9289 | J32: =I32*(1+J36) -> 6209.745 | K32: =J32*(1+K36) -> 6638.2174 | M32: WSP assumption: grow SBC in-line with revenue growth
C33: Adjusted EBITDA | D33: =SUM(D31:D32) -> 74739 | E33: =SUM(E31:E32) -> 76341 | F33: =SUM(F31:F32) -> 87141 | G33: =SUM(G31:G32) -> 77914.451 | H33: =SUM(H31:H32) -> 84442.973 | I33: =SUM(I31:I32) -> 90264.826 | J33: =SUM(J31:J32) -> 96788.549 | K33: =SUM(K31:K32) -> 103782.8 | M33: EBITDA + Stock-based compensation
C35: Growth rates & margins
C36: Revenue growth | E36: =E17/D17-1 -> 0.063045182 | F36: =F17/E17-1 -> 0.15861958 | G36: -0.04 | H36: 0.06 | I36: 0.069 | J36: =I36 -> 0.069 | K36: =J36 -> 0.069 | M36: JP Morgan estimates through 2021; straight-line growth rate thereafter
C37: Gross profit margin | D37: =D19/D17 -> 0.39075956 | E37: =E19/E17 -> 0.3846986 | F37: =F19/F17 -> 0.38343719 | G37: 0.378 | H37: 0.381 | I37: 0.382 | J37: =I37 -> 0.382 | K37: =J37 -> 0.382 | M37: JP Morgan estimates through 2021; straight-line margin thereafter
C38: R&D % of sales | D38: =-D20/D17 -> 0.046582483 | E38: =-E20/E17 -> 0.050520429 | F38: =-F20/F17 -> 0.053600407 | G38: 0.062 | H38: 0.063 | I38: 0.063 | J38: =I38 -> 0.063 | K38: =J38 -> 0.063 | M38: JP Morgan estimates through 2021: straight-line margin thereafter
C39: SG&A % of sales | D39: =-D21/D17 -> 0.065822973 | E39: =-E21/E17 -> 0.066573894 | F39: =-F21/F17 -> 0.062896515 | G39: 0.074 | H39: 0.069 | I39: 0.069 | J39: =I39 -> 0.069 | K39: =J39 -> 0.069 | M39: JP Morgan estimates through 2021: straight-line margin thereafter
C40: Tax rate | D40: =-(D27/D26) -> 0.25557257 | E40: =-(E27/E26) -> 0.24556476 | F40: =-(F27/F26) -> 0.18342181 | G40: 0.167 | H40: 0.17 | I40: 0.169 | J40: =I40 -> 0.169 | K40: =J40 -> 0.169 | M40: JP Morgan estimates through 2021: straight-line margin thereafter
C42: BALANCE SHEET
C43: =C14 -> Fiscal year | E43: =E14 -> 2017 | F43: =F14 -> 2018 | G43: =G14 -> 2019 | H43: =H14 -> 2020 | I43: =I14 -> 2021 | J43: =J14 -> 2022 | K43: =K14 -> 2023
C44: =C15 -> Fiscal year end date | E44: =E15 -> 43008 | F44: =F15 -> 43372 | G44: =G15 -> 43738 | H44: =H15 -> 44104 | I44: =I15 -> 44469 | J44: =J15 -> 44834 | K44: =K15 -> 45199
C45: Cash & equivalents, ST and LT marketable securities | E45: =20289+53892+194714 -> 268895 | F45: =25913+40388+170799 -> 237100 | G45: =G90+F45 -> 202199.73 | H45: =H90+G45 -> 176523.72 | I45: =I90+H45 -> 156076.93 | J45: =J90+I45 -> 140273.78 | K45: =K90+J45 -> 129472.46 | M45: Reference from 'net change in cash' line on the cash flow statement
C46: Accounts receivable | E46: 17874 | F46: 23186 | G46: =F46*(1+G36) -> 22258.56 | H46: =G46*(1+H36) -> 23594.074 | I46: =H46*(1+I36) -> 25222.065 | J46: =I46*(1+J36) -> 26962.387 | K46: =J46*(1+K36) -> 28822.792 | M46: Grow in-line with revenue growth
C47: Inventories | E47: 4855 | F47: 3956 | G47: =F47*G18/F18 -> 3831.2507 | H47: =G47*H18/G18 -> 4041.5383 | I47: =H47*I18/H18 -> 4313.4248 | J47: =I47*J18/I18 -> 4611.0512 | K47: =J47*K18/J18 -> 4929.2137 | M47: Grow in-line with cost of sales growth
C48: Other current assets | E48: =17799+13936 -> 31735 | F48: =25809+12087 -> 37896 | G48: =F48*(1+G36) -> 36380.16 | H48: =G48*(1+H36) -> 38562.97 | I48: =H48*(1+I36) -> 41223.815 | J48: =I48*(1+J36) -> 44068.258 | K48: =J48*(1+K36) -> 47108.967 | M48: Grow in-line with revenue growth
C49: Property, plant & equipment | E49: 33783 | F49: 41304 | G49: =G99 -> 45042.86 | H49: =H99 -> 48611.182 | I49: =I99 -> 51947.568 | J49: =J99 -> 55218.714 | K49: =K99 -> 58399.733 | M49: Reference from PP&E schedule
C50: Other non current assets | E50: 18177 | F50: 22283 | G50: =F50*(1+G36) -> 21391.68 | H50: =G50*(1+H36) -> 22675.181 | I50: =H50*(1+I36) -> 24239.768 | J50: =I50*(1+J36) -> 25912.312 | K50: =J50*(1+K36) -> 27700.262 | M50: Grow in-line with revenue growth
C51: Total assets | E51: =SUM(E45:E50) -> 375319 | F51: =SUM(F45:F50) -> 365725 | G51: =SUM(G45:G50) -> 331104.24 | H51: =SUM(H45:H50) -> 314008.67 | I51: =SUM(I45:I50) -> 303023.57 | J51: =SUM(J45:J50) -> 297046.5 | K51: =SUM(K45:K50) -> 296433.42
C53: Accounts payable | E53: 44242 | F53: 55888 | G53: =F53*G18/F18 -> 54125.617 | H53: =G53*H18/G18 -> 57096.435 | I53: =H53*I18/H18 -> 60937.484 | J53: =I53*J18/I18 -> 65142.171 | K53: =J53*K18/J18 -> 69636.98 | M53: Grow in-line with cost of sales growth
C54: Other current liabilities | E54: 30551 | F54: 32687 | G54: =F54*(1+G36) -> 31379.52 | H54: =G54*(1+H36) -> 33262.291 | I54: =H54*(1+I36) -> 35557.389 | J54: =I54*(1+J36) -> 38010.849 | K54: =J54*(1+K36) -> 40633.598 | M54: Grow in-line with revenue growth
C55: Deferred revenue (current and non current) | E55: =7548+2836 -> 10384 | F55: =7543+2797 -> 10340 | G55: =F55*(1+G36) -> 9926.4 | H55: =G55*(1+H36) -> 10521.984 | I55: =H55*(1+I36) -> 11248.001 | J55: =I55*(1+J36) -> 12024.113 | K55: =J55*(1+K36) -> 12853.777 | M55: Grow in-line with revenue growth
C56: Commercial paper / revolver | E56: 11977 | F56: 11964 | G56: =G135 -> 12000 | H56: =H135 -> 12000 | I56: =I135 -> 12000 | J56: =J135 -> 12000 | K56: =K135 -> 12000 | M56: Reference EOP balance from CP/revolver schedule
C57: Long term debt (includes current portion) | E57: =6496+97207 -> 103703 | F57: =8784+93735 -> 102519 | G57: =F57 -> 102519 | H57: =G57 -> 102519 | I57: =H57 -> 102519 | J57: =I57 -> 102519 | K57: =J57 -> 102519 | M57: WSP assumption: straight-line
C58: Other non current liabilities | E58: 40415 | F58: 45180 | G58: =F58*(1+G36) -> 43372.8 | H58: =G58*(1+H36) -> 45975.168 | I58: =H58*(1+I36) -> 49147.455 | J58: =I58*(1+J36) -> 52538.629 | K58: =J58*(1+K36) -> 56163.794 | M58: Grow in-line with revenue growth
C59: Total liabilities | E59: =SUM(E53:E58) -> 241272 | F59: =SUM(F53:F58) -> 258578 | G59: =SUM(G53:G58) -> 253323.34 | H59: =SUM(H53:H58) -> 261374.88 | I59: =SUM(I53:I58) -> 271409.33 | J59: =SUM(J53:J58) -> 282234.76 | K59: =SUM(K53:K58) -> 293807.15
C61: Common stock | E61: 35867 | F61: 40201 | G61: =F61+G32 -> 45327.4 | H61: =G61+H32 -> 50761.384 | I61: =H61+I32 -> 56570.313 | J61: =I61+J32 -> 62780.058 | K61: =J61+K32 -> 69418.275 | M61: Increase by stock-based compensation forecasted in the I/S section
C62: Retained earnings | E62: 98330 | F62: 70400 | G62: =G119 -> 35907.506 | H62: =H119 -> 5326.4074 | I62: =I119 -> -21502.072 | J62: =J119 -> -44514.32 | K62: =K119 -> -63338.001 | M62: Reference from Retained Earnings schedule
C63: Other comprehensive income | E63: -150 | F63: -3454 | G63: =F63 -> -3454 | H63: =G63 -> -3454 | I63: =H63 -> -3454 | J63: =I63 -> -3454 | K63: =J63 -> -3454 | M63: WSP assumption: straight-line
C64: Total equity | E64: =SUM(E61:E63) -> 134047 | F64: =SUM(F61:F63) -> 107147 | G64: =SUM(G61:G63) -> 77780.906 | H64: =SUM(H61:H63) -> 52633.791 | I64: =SUM(I61:I63) -> 31614.241 | J64: =SUM(J61:J63) -> 14811.738 | K64: =SUM(K61:K63) -> 2626.2747
C66: Balance check | E66: =ROUND(E51-E59-E64,3) -> 0 | F66: =ROUND(F51-F59-F64,3) -> 0 | G66: =ROUND(G51-G59-G64,3) -> 0 | H66: =ROUND(H51-H59-H64,3) -> 0 | I66: =ROUND(I51-I59-I64,3) -> 0 | J66: =ROUND(J51-J59-J64,3) -> 0 | K66: =ROUND(K51-K59-K64,3) -> 0
C68: CASH FLOW STATEMENT
C69: =C14 -> Fiscal year | G69: =G14 -> 2019 | H69: =H14 -> 2020 | I69: =I14 -> 2021 | J69: =J14 -> 2022 | K69: =K14 -> 2023
C70: =C15 -> Fiscal year end date | G70: =G15 -> 43738 | H70: =H15 -> 44104 | I70: =I15 -> 44469 | J70: =J15 -> 44834 | K70: =K15 -> 45199
C72: Net income | G72: =G28 -> 52298.506 | H72: =H28 -> 56209.901 | I72: =I28 -> 59962.52 | J72: =J28 -> 63778.753 | K72: =K28 -> 67967.319
C73: Depreciation and amortization | G73: =G30 -> 11085.02 | H73: =H30 -> 11711.891 | I73: =I30 -> 12226.381 | J73: =J30 -> 13365.451 | K73: =K30 -> 14603.503 | M73: Reference from the I/S
C74: Stock based compensation | G74: =G32 -> 5126.4 | H74: =H32 -> 5433.984 | I74: =I32 -> 5808.9289 | J74: =J32 -> 6209.745 | K74: =K32 -> 6638.2174
C75: Decreases / (Increases) in working capital assets | G75: =-1*(SUM(G46:G48)-SUM(F46:F48)) -> 2568.0293 | H75: =-1*(SUM(H46:H48)-SUM(G46:G48)) -> -3728.6108 | I75: =-1*(SUM(I46:I48)-SUM(H46:H48)) -> -4560.7225 | J75: =-1*(SUM(J46:J48)-SUM(I46:I48)) -> -4882.392 | K75: =-1*(SUM(K46:K48)-SUM(J46:J48)) -> -5219.277
C76: Increases / (Decreases) in working capital liabilities | G76: =SUM(G53:G55)-SUM(F53:F55) -> -3483.4631 | H76: =SUM(H53:H55)-SUM(G53:G55) -> 5449.1728 | I76: =SUM(I53:I55)-SUM(H53:H55) -> 6862.1646 | J76: =SUM(J53:J55)-SUM(I53:I55) -> 7434.2583 | K76: =SUM(K53:K55)-SUM(J53:J55) -> 7947.2222
C77: Other non current assets | G77: =-(G111) -> -647.56 | H77: =-(H111) -> -2914.7136 | I77: =-(I111) -> -3308.354 | J77: =-(J111) -> -3536.6304 | K77: =-(K111) -> -3780.6579 | M77: Reference from schedule NOT the B/S: Only include 'Additions' (as outflow)
C78: Other non current liabilities | G78: =G58-F58 -> -1807.2 | H78: =H58-G58 -> 2602.368 | I78: =I58-H58 -> 3172.2866 | J78: =J58-I58 -> 3391.1744 | K78: =K58-J58 -> 3625.1654
C79: Cash from operating activities | G79: =SUM(G72:G78) -> 65139.732 | H79: =SUM(H72:H78) -> 74763.992 | I79: =SUM(I72:I78) -> 80163.205 | J79: =SUM(J72:J78) -> 85760.359 | K79: =SUM(K72:K78) -> 91781.493
C81: Capital expenditures | G81: =-(G97) -> -13285 | H81: =-(H97) -> -13649 | I81: =-(I97) -> -13819 | J81: =-(J97) -> -14772.511 | K81: =-(K97) -> -15791.814 | M81: Reference from PP&E schedule
C82: Cash from investing activities | G82: =IFERROR(G81,"NA") -> -13285 | H82: =IFERROR(H81,"NA") -> -13649 | I82: =IFERROR(I81,"NA") -> -13819 | J82: =IFERROR(J81,"NA") -> -14772.511 | K82: =IFERROR(K81,"NA") -> -15791.814
C84: Long term debt | G84: =G57-F57 -> 0 | H84: =H57-G57 -> 0 | I84: =I57-H57 -> 0 | J84: =J57-I57 -> 0 | K84: =K57-J57 -> 0
C85: Revolver | G85: =G56-F56 -> 36 | H85: =H56-G56 -> 0 | I85: =I56-H56 -> 0 | J85: =J56-I56 -> 0 | K85: =K56-J56 -> 0 | M85: Reference from B/S
C86: Share repurchases | G86: =G118 -> -73056 | H86: =H118 -> -73056 | I86: =I118 -> -73056 | J86: =J118 -> -73056 | K86: =K118 -> -73056 | M86: Reference from Retained Earnings schedule
C87: Common dividends | G87: =G117 -> -13735 | H87: =H117 -> -13735 | I87: =I117 -> -13735 | J87: =J117 -> -13735 | K87: =K117 -> -13735 | M87: Reference from Retained Earnings schedule
C88: Cash from financing activities | G88: =SUM(G84:G87) -> -86755 | H88: =SUM(H84:H87) -> -86791 | I88: =SUM(I84:I87) -> -86791 | J88: =SUM(J84:J87) -> -86791 | K88: =SUM(K84:K87) -> -86791
C90: Net change in cash during period | G90: =G79+G82+G88 -> -34900.268 | H90: =H79+H82+H88 -> -25676.008 | I90: =I79+I82+I88 -> -20446.795 | J90: =J79+J82+J88 -> -15803.152 | K90: =K79+K82+K88 -> -10801.322
C92: PROPERTY, PLANT & EQUIPMENT
C93: =C14 -> Fiscal year | D93: =D14 -> 2016 | E93: =E14 -> 2017 | F93: =F14 -> 2018 | G93: =G14 -> 2019 | H93: =H14 -> 2020 | I93: =I14 -> 2021 | J93: =J14 -> 2022 | K93: =K14 -> 2023
C94: =C15 -> Fiscal year end date | D94: =D15 -> 42643 | E94: =E15 -> 43008 | F94: =F15 -> 43372 | G94: =G15 -> 43738 | H94: =H15 -> 44104 | I94: =I15 -> 44469 | J94: =J15 -> 44834 | K94: =K15 -> 45199
G95: Forecast
C96: Beginning of period | G96: =F99 -> 41304 | H96: =G99 -> 45042.86 | I96: =H99 -> 48611.182 | J96: =I99 -> 51947.568 | K96: =J99 -> 55218.714 | M96: BOP = Previous year EOP
C97: Plus: Capital expenditures | D97: 12734 | E97: 12451 | F97: 13313 | G97: 13285 | H97: 13649 | I97: 13819 | J97: =I97*(1+J36) -> 14772.511 | K97: =J97*(1+K36) -> 15791.814 | M97: JP Morgan through 2021; WSP assumption thereafter
C98: Less: Depreciation | D98: -8300 | E98: -8200 | F98: -9300 | G98: =-(G101*G97) -> -9546.1402 | H98: =-(H101*H97) -> -10080.678 | I98: =-(I101*I97) -> -10482.614 | J98: =-(J101*J97) -> -11501.365 | K98: =-(K101*K97) -> -12610.795 | M98: Capex x 'D&A related to PP&E as a % of capex' ratio (below)
C99: End of period | E99: =E49 -> 33783 | F99: =F49 -> 41304 | G99: =SUM(G96:G98) -> 45042.86 | H99: =SUM(H96:H98) -> 48611.182 | I99: =SUM(I96:I98) -> 51947.568 | J99: =SUM(J96:J98) -> 55218.714 | K99: =SUM(K96:K98) -> 58399.733 | M99: BOP + Capex - Depreciation
M100: Step
C101: D&A related to PP&E as a % of capex | D101: =-(D98/D97) -> 0.65179834 | E101: =-(E98/E97) -> 0.65858164 | F101: =-(F98/F97) -> 0.69856531 | G101: =F101+$M$101 -> 0.71856531 | H101: =G101+$M$101 -> 0.73856531 | I101: =H101+$M$101 -> 0.75856531 | J101: =I101+$M$101 -> 0.77856531 | K101: =J101+$M$101 -> 0.79856531 | M101: 0.02
C103: IMPUTING TOTAL DEPRECIATION & AMORTIZATION
C104: D&A not related to PP&E | D104: =D106+D98 -> 2205 | E104: =E106+E98 -> 1957 | F104: =F106+F98 -> 1603 | G104: =G105*G17 -> 1538.88 | H104: =H105*H17 -> 1631.2128 | I104: =I105*I17 -> 1743.7665 | J104: =J105*J17 -> 1864.0864 | K104: =K105*K17 -> 1992.7083 | M104: Revenue x 'as % of revenue' assumption
C105: as % of revenue | D105: =D104/D17 -> 0.010225423 | E105: =E104/E17 -> 0.008537128 | F105: =F104/F17 -> 0.0060355052 | G105: =F105 -> 0.0060355052 | H105: =G105 -> 0.0060355052 | I105: =H105 -> 0.0060355052 | J105: =I105 -> 0.0060355052 | K105: =J105 -> 0.0060355052 | M105: Straight line last historical % of revenue - WSP assumption
C106: Depreciation & Amortization - Total | D106: =D30 -> 10505 | E106: =E30 -> 10157 | F106: =F30 -> 10903 | G106: =-G98+G104 -> 11085.02 | H106: =-H98+H104 -> 11711.891 | I106: =-I98+I104 -> 12226.381 | J106: =-J98+J104 -> 13365.451 | K106: =-K98+K104 -> 14603.503 | M106: D&A from PP&E + D&A not from PP&E
C108: OTHER NON-CURRENT ASSETS
C109: Beginning of period | G109: =F112 -> 22283 | H109: =G112 -> 21391.68 | I109: =H112 -> 22675.181 | J109: =I112 -> 24239.768 | K109: =J112 -> 25912.312 | M109: BOP = Previous year EOP
C110: Less: D&A not related to PP&E | G110: =-(G104) -> -1538.88 | H110: =-(H104) -> -1631.2128 | I110: =-(I104) -> -1743.7665 | J110: =-(J104) -> -1864.0864 | K110: =-(K104) -> -1992.7083 | M110: Assume all D&A not from PP&E is in non-current assets
C111: Plus: Additions | G111: =G112-G110-G109 -> 647.56 | H111: =H112-H110-H109 -> 2914.7136 | I111: =I112-I110-I109 -> 3308.354 | J111: =J112-J110-J109 -> 3536.6304 | K111: =K112-K110-K109 -> 3780.6579 | M111: Because we already know the EOP balance, this is a plug: EOP - D&A not from PP&E - BOP
C112: End of period | E112: =E50 -> 18177 | F112: =F50 -> 22283 | G112: =G50 -> 21391.68 | H112: =H50 -> 22675.181 | I112: =I50 -> 24239.768 | J112: =J50 -> 25912.312 | K112: =K50 -> 27700.262 | M112: Referenced from balance sheet
C114: RETAINED EARNINGS
C115: Beginning of period | G115: =F119 -> 70400 | H115: =G119 -> 35907.506 | I115: =H119 -> 5326.4074 | J115: =I119 -> -21502.072 | K115: =J119 -> -44514.32 | M115: BOP = Previous year EOP
C116: Plus: Net income | D116: =D28 -> 45687 | E116: =E28 -> 48351 | F116: =F28 -> 59531 | G116: =G28 -> 52298.506 | H116: =H28 -> 56209.901 | I116: =I28 -> 59962.52 | J116: =J28 -> 63778.753 | K116: =K28 -> 67967.319 | M116: Reference from income statement
C117: Less: Dividends | D117: -12188 | E117: -12803 | F117: -13735 | G117: =F117 -> -13735 | H117: =G117 -> -13735 | I117: =H117 -> -13735 | J117: =I117 -> -13735 | K117: =J117 -> -13735 | M117: WSP assumption: Straight-line last historical year dividends
C118: Less: Repurchases | D118: -29000 | E118: -33001 | F118: -73056 | G118: =F118 -> -73056 | H118: =G118 -> -73056 | I118: =H118 -> -73056 | J118: =I118 -> -73056 | K118: =J118 -> -73056 | M118: WSP assumption: Straight-line last historical year repurchases
C119: End of period | D119: =D62 -> 0 | E119: =E62 -> 98330 | F119: =F62 -> 70400 | G119: =SUM(G115:G118) -> 35907.506 | H119: =SUM(H115:H118) -> 5326.4074 | I119: =SUM(I115:I118) -> -21502.072 | J119: =SUM(J115:J118) -> -44514.32 | K119: =SUM(K115:K118) -> -63338.001 | M119: BOP + net income - dividends - repurchases
...

Sheet FSM Complete
C2: ="Financial Statement Model for "&D5 -> Financial Statement Model for Apple
C3: $ in thousands except per share
C5: Company name | D5: Apple
C6: Ticker | D6: AAPL
C7: Circ break 1=off, 0=on | D7: 1
C8: Latest closing share price | D8: 171.25
C9: Latest closing share price date | D9: 43500
C10: Latest fiscal year end date | D10: 43372
C11: Shares outstanding (millions) | D11: 4745.398
C13: INCOME STATEMENT
C14: Fiscal year | D14: =E14-1 -> 2016 | E14: =F14-1 -> 2017 | F14: =YEAR(D10) -> 2018 | G14: =F14+1 -> 2019 | H14: =G14+1 -> 2020 | I14: =H14+1 -> 2021 | J14: =I14+1 -> 2022 | K14: =J14+1 -> 2023
C15: Fiscal year end date | D15: =EOMONTH(E15,-12) -> 42643 | E15: =EOMONTH(F15,-12) -> 43008 | F15: =D10 -> 43372 | G15: =EOMONTH(F15,12) -> 43738 | H15: =EOMONTH(G15,12) -> 44104 | I15: =EOMONTH(H15,12) -> 44469 | J15: =EOMONTH(I15,12) -> 44834 | K15: =EOMONTH(J15,12) -> 45199 | M15: WSP Comments
C17: Revenue | D17: 215639 | E17: 229234 | F17: 265595 | G17: =F17*(1+G36) -> 254971.2 | H17: =G17*(1+H36) -> 270269.47 | I17: =H17*(1+I36) -> 288918.07 | J17: =I17*(1+J36) -> 308853.41 | K17: =J17*(1+K36) -> 330164.3 | M17: Previous year's revenues x (1+revenue growth rate)
C18: Cost of sales (enter as -) | D18: -131376 | E18: -141048 | F18: -163756 | G18: =G19-G17 -> -158592.09 | H18: =H19-H17 -> -167296.8 | I18: =I19-I17 -> -178551.36 | J18: =J19-J17 -> -190871.41 | K18: =K19-K17 -> -204041.54 | M18: Plug = Revenue - Gross Profit
C19: Gross Profit | D19: =SUM(D17:D18) -> 84263 | E19: =SUM(E17:E18) -> 88186 | F19: =SUM(F17:F18) -> 101839 | G19: =G17*G37 -> 96379.114 | H19: =H17*H37 -> 102972.67 | I19: =I17*I37 -> 110366.7 | J19: =J17*J37 -> 117982 | K19: =K17*K37 -> 126122.76 | M19: Revenue x Gross Profit Margin forecast
C20: Research & development (enter as -) | D20: -10045 | E20: -11581 | F20: -14236 | G20: =-G38*G17 -> -15808.214 | H20: =-H38*H17 -> -17026.977 | I20: =-I38*I17 -> -18201.838 | J20: =-J38*J17 -> -19457.765 | K20: =-K38*K17 -> -20800.351 | M20: Revenue x R&D % of sales forecast
C21: Selling, general & administrative (enter as -) | D21: -14194 | E21: -15261 | F21: -16705 | G21: =-G17*G39 -> -18867.869 | H21: =-H17*H39 -> -18648.594 | I21: =-I17*I39 -> -19935.347 | J21: =-J17*J39 -> -21310.885 | K21: =-K17*K39 -> -22781.337 | M21: Revenue x SG&A % of sales forecast
C22: Operating profit (EBIT) | D22: =D19+D20+D21 -> 60024 | E22: =E19+E20+E21 -> 61344 | F22: =F19+F20+F21 -> 70898 | G22: =G19+G20+G21 -> 61703.03 | H22: =H19+H20+H21 -> 67297.099 | I22: =I19+I20+I21 -> 72229.516 | J22: =J19+J20+J21 -> 77213.353 | K22: =K19+K20+K21 -> 82541.074 | M22: Gross Profit - R&D - SG&A
C23: Interest income | D23: 3999 | E23: 5201 | F23: 5686 | G23: =G156 -> 4744.4371 | H23: =H156 -> 4090.2133 | I23: =I156 -> 3592.0871 | J23: =J156 -> 3200.5876 | K23: =K156 -> 2913.2593 | M23: Reference from interest on cash schedule
C24: Interest expense (enter as -) | D24: -1456 | E24: -2323 | F24: -3240 | G24: =-G142 -> -3223.1469 | H24: =-H142 -> -3223.5393 | I24: =-I142 -> -3223.5393 | J24: =-J142 -> -3223.5393 | K24: =-K142 -> -3223.5393 | M24: Reference from interest expense schedule
C25: Other expense, net (enter as -) | D25: -1195 | E25: -133 | F25: -441 | G25: =F25 -> -441 | H25: =G25 -> -441 | I25: =H25 -> -441 | J25: =I25 -> -441 | K25: =J25 -> -441 | M25: Straight-line
C26: Pretax profit | D26: =SUM(D22:D25) -> 61372 | E26: =SUM(E22:E25) -> 64089 | F26: =SUM(F22:F25) -> 72903 | G26: =SUM(G22:G25) -> 62783.321 | H26: =SUM(H22:H25) -> 67722.773 | I26: =SUM(I22:I25) -> 72157.064 | J26: =SUM(J22:J25) -> 76749.401 | K26: =SUM(K22:K25) -> 81789.794 | M26: EBIT + interest income less interest expense less other expense
C27: Taxes (enter expense as -) | D27: -15685 | E27: -15738 | F27: -13372 | G27: =-G40*G26 -> -10484.815 | H27: =-H40*H26 -> -11512.871 | I27: =-I40*I26 -> -12194.544 | J27: =-J40*J26 -> -12970.649 | K27: =-K40*K26 -> -13822.475 | M27: Pre-tax Profit x Tax Rate forecast
C28: Net income | D28: =SUM(D26:D27) -> 45687 | E28: =SUM(E26:E27) -> 48351 | F28: =SUM(F26:F27) -> 59531 | G28: =SUM(G26:G27) -> 52298.506 | H28: =SUM(H26:H27) -> 56209.901 | I28: =SUM(I26:I27) -> 59962.52 | J28: =SUM(J26:J27) -> 63778.753 | K28: =SUM(K26:K27) -> 67967.319 | M28: Pre-tax Profit less taxes
C30: Depreciation & amortization | D30: 10505 | E30: 10157 | F30: 10903 | G30: =G106 -> 11085.02 | H30: =H106 -> 11711.891 | I30: =I106 -> 12226.381 | J30: =J106 -> 13365.451 | K30: =K106 -> 14603.503 | M30: Reference from D&A schedule
C31: EBITDA | D31: =D22+D30 -> 70529 | E31: =E22+E30 -> 71501 | F31: =F22+F30 -> 81801 | G31: =G22+G30 -> 72788.051 | H31: =H22+H30 -> 79008.989 | I31: =I22+I30 -> 84455.897 | J31: =J22+J30 -> 90578.804 | K31: =K22+K30 -> 97144.578 | M31: EBIT + D&A
C32: Stock based compensation | D32: 4210 | E32: 4840 | F32: 5340 | G32: =F32*(1+G36) -> 5126.4 | H32: =G32*(1+H36) -> 5433.984 | I32: =H32*(1+I36) -> 5808.9289 | J32: =I32*(1+J36) -> 6209.745 | K32: =J32*(1+K36) -> 6638.2174 | M32: WSP assumption: grow SBC in-line with revenue growth
C33: Adjusted EBITDA | D33: =SUM(D31:D32) -> 74739 | E33: =SUM(E31:E32) -> 76341 | F33: =SUM(F31:F32) -> 87141 | G33: =SUM(G31:G32) -> 77914.451 | H33: =SUM(H31:H32) -> 84442.973 | I33: =SUM(I31:I32) -> 90264.826 | J33: =SUM(J31:J32) -> 96788.549 | K33: =SUM(K31:K32) -> 103782.8 | M33: EBITDA + Stock-based compensation
C35: Growth rates & margins
C36: Revenue growth | E36: =E17/D17-1 -> 0.063045182 | F36: =F17/E17-1 -> 0.15861958 | G36: -0.04 | H36: 0.06 | I36: 0.069 | J36: =I36 -> 0.069 | K36: =J36 -> 0.069 | M36: JP Morgan estimates through 2021; straight-line growth rate thereafter
C37: Gross profit margin | D37: =D19/D17 -> 0.39075956 | E37: =E19/E17 -> 0.3846986 | F37: =F19/F17 -> 0.38343719 | G37: 0.378 | H37: 0.381 | I37: 0.382 | J37: =I37 -> 0.382 | K37: =J37 -> 0.382 | M37: JP Morgan estimates through 2021; straight-line margin thereafter
C38: R&D % of sales | D38: =-D20/D17 -> 0.046582483 | E38: =-E20/E17 -> 0.050520429 | F38: =-F20/F17 -> 0.053600407 | G38: 0.062 | H38: 0.063 | I38: 0.063 | J38: =I38 -> 0.063 | K38: =J38 -> 0.063 | M38: JP Morgan estimates through 2021: straight-line margin thereafter
C39: SG&A % of sales | D39: =-D21/D17 -> 0.065822973 | E39: =-E21/E17 -> 0.066573894 | F39: =-F21/F17 -> 0.062896515 | G39: 0.074 | H39: 0.069 | I39: 0.069 | J39: =I39 -> 0.069 | K39: =J39 -> 0.069 | M39: JP Morgan estimates through 2021: straight-line margin thereafter
C40: Tax rate | D40: =-(D27/D26) -> 0.25557257 | E40: =-(E27/E26) -> 0.24556476 | F40: =-(F27/F26) -> 0.18342181 | G40: 0.167 | H40: 0.17 | I40: 0.169 | J40: =I40 -> 0.169 | K40: =J40 -> 0.169 | M40: JP Morgan estimates through 2021: straight-line margin thereafter
C42: BALANCE SHEET
C43: =C14 -> Fiscal year | E43: =E14 -> 2017 | F43: =F14 -> 2018 | G43: =G14 -> 2019 | H43: =H14 -> 2020 | I43: =I14 -> 2021 | J43: =J14 -> 2022 | K43: =K14 -> 2023
C44: =C15 -> Fiscal year end date | E44: =E15 -> 43008 | F44: =F15 -> 43372 | G44: =G15 -> 43738 | H44: =H15 -> 44104 | I44: =I15 -> 44469 | J44: =J15 -> 44834 | K44: =K15 -> 45199
C45: Cash & equivalents, ST and LT marketable securities | E45: =20289+53892+194714 -> 268895 | F45: =25913+40388+170799 -> 237100 | G45: =G90+F45 -> 202199.73 | H45: =H90+G45 -> 176523.72 | I45: =I90+H45 -> 156076.93 | J45: =J90+I45 -> 140273.78 | K45: =K90+J45 -> 129472.46 | M45: Reference from 'net change in cash' line on the cash flow statement
C46: Accounts receivable | E46: 17874 | F46: 23186 | G46: =F46*(1+G36) -> 22258.56 | H46: =G46*(1+H36) -> 23594.074 | I46: =H46*(1+I36) -> 25222.065 | J46: =I46*(1+J36) -> 26962.387 | K46: =J46*(1+K36) -> 28822.792 | M46: Grow in-line with revenue growth
C47: Inventories | E47: 4855 | F47: 3956 | G47: =F47*G18/F18 -> 3831.2507 | H47: =G47*H18/G18 -> 4041.5383 | I47: =H47*I18/H18 -> 4313.4248 | J47: =I47*J18/I18 -> 4611.0512 | K47: =J47*K18/J18 -> 4929.2137 | M47: Grow in-line with cost of sales growth
C48: Other current assets | E48: =17799+13936 -> 31735 | F48: =25809+12087 -> 37896 | G48: =F48*(1+G36) -> 36380.16 | H48: =G48*(1+H36) -> 38562.97 | I48: =H48*(1+I36) -> 41223.815 | J48: =I48*(1+J36) -> 44068.258 | K48: =J48*(1+K36) -> 47108.967 | M48: Grow in-line with revenue growth
C49: Property, plant & equipment | E49: 33783 | F49: 41304 | G49: =G99 -> 45042.86 | H49: =H99 -> 48611.182 | I49: =I99 -> 51947.568 | J49: =J99 -> 55218.714 | K49: =K99 -> 58399.733 | M49: Reference from PP&E schedule
C50: Other non current assets | E50: 18177 | F50: 22283 | G50: =F50*(1+G36) -> 21391.68 | H50: =G50*(1+H36) -> 22675.181 | I50: =H50*(1+I36) -> 24239.768 | J50: =I50*(1+J36) -> 25912.312 | K50: =J50*(1+K36) -> 27700.262 | M50: Grow in-line with revenue growth
C51: Total assets | E51: =SUM(E45:E50) -> 375319 | F51: =SUM(F45:F50) -> 365725 | G51: =SUM(G45:G50) -> 331104.24 | H51: =SUM(H45:H50) -> 314008.67 | I51: =SUM(I45:I50) -> 303023.57 | J51: =SUM(J45:J50) -> 297046.5 | K51: =SUM(K45:K50) -> 296433.42
C53: Accounts payable | E53: 44242 | F53: 55888 | G53: =F53*G18/F18 -> 54125.617 | H53: =G53*H18/G18 -> 57096.435 | I53: =H53*I18/H18 -> 60937.484 | J53: =I53*J18/I18 -> 65142.171 | K53: =J53*K18/J18 -> 69636.98 | M53: Grow in-line with cost of sales growth
C54: Other current liabilities | E54: 30551 | F54: 32687 | G54: =F54*(1+G36) -> 31379.52 | H54: =G54*(1+H36) -> 33262.291 | I54: =H54*(1+I36) -> 35557.389 | J54: =I54*(1+J36) -> 38010.849 | K54: =J54*(1+K36) -> 40633.598 | M54: Grow in-line with revenue growth
C55: Deferred revenue (current and non current) | E55: =7548+2836 -> 10384 | F55: =7543+2797 -> 10340 | G55: =F55*(1+G36) -> 9926.4 | H55: =G55*(1+H36) -> 10521.984 | I55: =H55*(1+I36) -> 11248.001 | J55: =I55*(1+J36) -> 12024.113 | K55: =J55*(1+K36) -> 12853.777 | M55: Grow in-line with revenue growth
C56: Commercial paper / revolver | E56: 11977 | F56: 11964 | G56: =G135 -> 12000 | H56: =H135 -> 12000 | I56: =I135 -> 12000 | J56: =J135 -> 12000 | K56: =K135 -> 12000 | M56: Reference EOP balance from CP/revolver schedule
C57: Long term debt (includes current portion) | E57: =6496+97207 -> 103703 | F57: =8784+93735 -> 102519 | G57: =F57 -> 102519 | H57: =G57 -> 102519 | I57: =H57 -> 102519 | J57: =I57 -> 102519 | K57: =J57 -> 102519 | M57: WSP assumption: straight-line
C58: Other non current liabilities | E58: 40415 | F58: 45180 | G58: =F58*(1+G36) -> 43372.8 | H58: =G58*(1+H36) -> 45975.168 | I58: =H58*(1+I36) -> 49147.455 | J58: =I58*(1+J36) -> 52538.629 | K58: =J58*(1+K36) -> 56163.794 | M58: Grow in-line with revenue growth
C59: Total liabilities | E59: =SUM(E53:E58) -> 241272 | F59: =SUM(F53:F58) -> 258578 | G59: =SUM(G53:G58) -> 253323.34 | H59: =SUM(H53:H58) -> 261374.88 | I59: =SUM(I53:I58) -> 271409.33 | J59: =SUM(J53:J58) -> 282234.76 | K59: =SUM(K53:K58) -> 293807.15
C61: Common stock | E61: 35867 | F61: 40201 | G61: =F61+G32 -> 45327.4 | H61: =G61+H32 -> 50761.384 | I61: =H61+I32 -> 56570.313 | J61: =I61+J32 -> 62780.058 | K61: =J61+K32 -> 69418.275 | M61: Increase by stock-based compensation forecasted in the I/S section
C62: Retained earnings | E62: =98330 -> 98330 | F62: 70400 | G62: =G119 -> 35907.506 | H62: =H119 -> 5326.4074 | I62: =I119 -> -21502.072 | J62: =J119 -> -44514.32 | K62: =K119 -> -63338.001 | M62: Reference from Retained Earnings schedule
C63: Other comprehensive income | E63: -150 | F63: -3454 | G63: =F63 -> -3454 | H63: =G63 -> -3454 | I63: =H63 -> -3454 | J63: =I63 -> -3454 | K63: =J63 -> -3454 | M63: WSP assumption: straight-line
C64: Total equity | E64: =SUM(E61:E63) -> 134047 | F64: =SUM(F61:F63) -> 107147 | G64: =SUM(G61:G63) -> 77780.906 | H64: =SUM(H61:H63) -> 52633.791 | I64: =SUM(I61:I63) -> 31614.241 | J64: =SUM(J61:J63) -> 14811.738 | K64: =SUM(K61:K63) -> 2626.2747
C66: Balance check | E66: =ROUND(E51-E59-E64,3) -> 0 | F66: =ROUND(F51-F59-F64,3) -> 0 | G66: =ROUND(G51-G59-G64,3) -> 0 | H66: =ROUND(H51-H59-H64,3) -> 0 | I66: =ROUND(I51-I59-I64,3) -> 0 | J66: =ROUND(J51-J59-J64,3) -> 0 | K66: =ROUND(K51-K59-K64,3) -> 0
C68: CASH FLOW STATEMENT
C69: =C14 -> Fiscal year | G69: =G14 -> 2019 | H69: =H14 -> 2020 | I69: =I14 -> 2021 | J69: =J14 -> 2022 | K69: =K14 -> 2023
C70: =C15 -> Fiscal year end date | G70: =G15 -> 43738 | H70: =H15 -> 44104 | I70: =I15 -> 44469 | J70: =J15 -> 44834 | K70: =K15 -> 45199
C72: Net income | G72: =G28 -> 52298.506 | H72: =H28 -> 56209.901 | I72: =I28 -> 59962.52 | J72: =J28 -> 63778.753 | K72: =K28 -> 67967.319
C73: Depreciation and amortization | G73: =G30 -> 11085.02 | H73: =H30 -> 11711.891 | I73: =I30 -> 12226.381 | J73: =J30 -> 13365.451 | K73: =K30 -> 14603.503 | M73: Reference from the I/S
C74: Stock based compensation | G74: =G32 -> 5126.4 | H74: =H32 -> 5433.984 | I74: =I32 -> 5808.9289 | J74: =J32 -> 6209.745 | K74: =K32 -> 6638.2174
C75: Decreases / (Increases) in working capital assets | G75: =-1*(SUM(G46:G48)-SUM(F46:F48)) -> 2568.0293 | H75: =-1*(SUM(H46:H48)-SUM(G46:G48)) -> -3728.6108 | I75: =-1*(SUM(I46:I48)-SUM(H46:H48)) -> -4560.7225 | J75: =-1*(SUM(J46:J48)-SUM(I46:I48)) -> -4882.392 | K75: =-1*(SUM(K46:K48)-SUM(J46:J48)) -> -5219.277
C76: Increases / (Decreases) in working capital liabilities | G76: =SUM(G53:G55)-SUM(F53:F55) -> -3483.4631 | H76: =SUM(H53:H55)-SUM(G53:G55) -> 5449.1728 | I76: =SUM(I53:I55)-SUM(H53:H55) -> 6862.1646 | J76: =SUM(J53:J55)-SUM(I53:I55) -> 7434.2583 | K76: =SUM(K53:K55)-SUM(J53:J55) -> 7947.2222
C77: Other non current assets | G77: =-(G111) -> -647.56 | H77: =-(H111) -> -2914.7136 | I77: =-(I111) -> -3308.354 | J77: =-(J111) -> -3536.6304 | K77: =-(K111) -> -3780.6579 | M77: Reference from schedule NOT the B/S: Only include 'Additions' (as outflow)
C78: Other non current liabilities | G78: =G58-F58 -> -1807.2 | H78: =H58-G58 -> 2602.368 | I78: =I58-H58 -> 3172.2866 | J78: =J58-I58 -> 3391.1744 | K78: =K58-J58 -> 3625.1654
C79: Cash from operating activities | G79: =SUM(G72:G78) -> 65139.732 | H79: =SUM(H72:H78) -> 74763.992 | I79: =SUM(I72:I78) -> 80163.205 | J79: =SUM(J72:J78) -> 85760.359 | K79: =SUM(K72:K78) -> 91781.493
C81: Capital expenditures | G81: =-(G97) -> -13285 | H81: =-(H97) -> -13649 | I81: =-(I97) -> -13819 | J81: =-(J97) -> -14772.511 | K81: =-(K97) -> -15791.814 | M81: Reference from PP&E schedule
C82: Cash from investing activities | G82: =IFERROR(G81,"NA") -> -13285 | H82: =IFERROR(H81,"NA") -> -13649 | I82: =IFERROR(I81,"NA") -> -13819 | J82: =IFERROR(J81,"NA") -> -14772.511 | K82: =IFERROR(K81,"NA") -> -15791.814
C84: Long term debt | G84: =G57-F57 -> 0 | H84: =H57-G57 -> 0 | I84: =I57-H57 -> 0 | J84: =J57-I57 -> 0 | K84: =K57-J57 -> 0
C85: Revolver | G85: =G56-F56 -> 36 | H85: =H56-G56 -> 0 | I85: =I56-H56 -> 0 | J85: =J56-I56 -> 0 | K85: =K56-J56 -> 0 | M85: Reference from B/S
C86: Share repurchases | G86: =G118 -> -73056 | H86: =H118 -> -73056 | I86: =I118 -> -73056 | J86: =J118 -> -73056 | K86: =K118 -> -73056 | M86: Reference from Retained Earnings schedule
C87: Common dividends | G87: =G117 -> -13735 | H87: =H117 -> -13735 | I87: =I117 -> -13735 | J87: =J117 -> -13735 | K87: =K117 -> -13735 | M87: Reference from Retained Earnings schedule
C88: Cash from financing activities | G88: =SUM(G84:G87) -> -86755 | H88: =SUM(H84:H87) -> -86791 | I88: =SUM(I84:I87) -> -86791 | J88: =SUM(J84:J87) -> -86791 | K88: =SUM(K84:K87) -> -86791
C90: Net change in cash during period | G90: =G79+G82+G88 -> -34900.268 | H90: =H79+H82+H88 -> -25676.008 | I90: =I79+I82+I88 -> -20446.795 | J90: =J79+J82+J88 -> -15803.152 | K90: =K79+K82+K88 -> -10801.322
C92: PROPERTY, PLANT & EQUIPMENT
C93: =C14 -> Fiscal year | D93: =D14 -> 2016 | E93: =E14 -> 2017 | F93: =F14 -> 2018 | G93: =G14 -> 2019 | H93: =H14 -> 2020 | I93: =I14 -> 2021 | J93: =J14 -> 2022 | K93: =K14 -> 2023
C94: =C15 -> Fiscal year end date | D94: =D15 -> 42643 | E94: =E15 -> 43008 | F94: =F15 -> 43372 | G94: =G15 -> 43738 | H94: =H15 -> 44104 | I94: =I15 -> 44469 | J94: =J15 -> 44834 | K94: =K15 -> 45199
G95: Forecast
C96: Beginning of period | G96: =F99 -> 41304 | H96: =G99 -> 45042.86 | I96: =H99 -> 48611.182 | J96: =I99 -> 51947.568 | K96: =J99 -> 55218.714 | M96: BOP = Previous year EOP
C97: Plus: Capital expenditures | D97: 12734 | E97: 12451 | F97: 13313 | G97: 13285 | H97: 13649 | I97: 13819 | J97: =I97*(1+J36) -> 14772.511 | K97: =J97*(1+K36) -> 15791.814 | M97: JP Morgan through 2021; WSP assumption thereafter
C98: Less: Depreciation | D98: -8300 | E98: -8200 | F98: -9300 | G98: =-(G101*G97) -> -9546.1402 | H98: =-(H101*H97) -> -10080.678 | I98: =-(I101*I97) -> -10482.614 | J98: =-(J101*J97) -> -11501.365 | K98: =-(K101*K97) -> -12610.795 | M98: Capex x 'D&A related to PP&E as a % of capex' ratio (below)
C99: End of period | E99: =E49 -> 33783 | F99: =F49 -> 41304 | G99: =SUM(G96:G98) -> 45042.86 | H99: =SUM(H96:H98) -> 48611.182 | I99: =SUM(I96:I98) -> 51947.568 | J99: =SUM(J96:J98) -> 55218.714 | K99: =SUM(K96:K98) -> 58399.733 | M99: BOP + Capex - Depreciation
M100: Step
C101: D&A related to PP&E as a % of capex | D101: =-(D98/D97) -> 0.65179834 | E101: =-(E98/E97) -> 0.65858164 | F101: =-(F98/F97) -> 0.69856531 | G101: =F101+$M$101 -> 0.71856531 | H101: =G101+$M$101 -> 0.73856531 | I101: =H101+$M$101 -> 0.75856531 | J101: =I101+$M$101 -> 0.77856531 | K101: =J101+$M$101 -> 0.79856531 | M101: 0.02
C103: IMPUTING TOTAL DEPRECIATION & AMORTIZATION
C104: D&A not related to PP&E | D104: =D106+D98 -> 2205 | E104: =E106+E98 -> 1957 | F104: =F106+F98 -> 1603 | G104: =G105*G17 -> 1538.88 | H104: =H105*H17 -> 1631.2128 | I104: =I105*I17 -> 1743.7665 | J104: =J105*J17 -> 1864.0864 | K104: =K105*K17 -> 1992.7083 | M104: Revenue x 'as % of revenue' assumption
C105: as % of revenue | D105: =D104/D17 -> 0.010225423 | E105: =E104/E17 -> 0.008537128 | F105: =F104/F17 -> 0.0060355052 | G105: =F105 -> 0.0060355052 | H105: =G105 -> 0.0060355052 | I105: =H105 -> 0.0060355052 | J105: =I105 -> 0.0060355052 | K105: =J105 -> 0.0060355052 | M105: Straight line last historical % of revenue - WSP assumption
C106: Depreciation & Amortization - Total | D106: =D30 -> 10505 | E106: =E30 -> 10157 | F106: =F30 -> 10903 | G106: =-G98+G104 -> 11085.02 | H106: =-H98+H104 -> 11711.891 | I106: =-I98+I104 -> 12226.381 | J106: =-J98+J104 -> 13365.451 | K106: =-K98+K104 -> 14603.503 | M106: D&A from PP&E + D&A not from PP&E
C108: OTHER NON-CURRENT ASSETS
C109: Beginning of period | G109: =F112 -> 22283 | H109: =G112 -> 21391.68 | I109: =H112 -> 22675.181 | J109: =I112 -> 24239.768 | K109: =J112 -> 25912.312 | M109: BOP = Previous year EOP
C110: Less: Amortization of intangible assets | G110: =-(G104) -> -1538.88 | H110: =-(H104) -> -1631.2128 | I110: =-(I104) -> -1743.7665 | J110: =-(J104) -> -1864.0864 | K110: =-(K104) -> -1992.7083 | M110: Assume all D&A not from PP&E is in non-current assets
C111: Plus: Additions | G111: =G112-G110-G109 -> 647.56 | H111: =H112-H110-H109 -> 2914.7136 | I111: =I112-I110-I109 -> 3308.354 | J111: =J112-J110-J109 -> 3536.6304 | K111: =K112-K110-K109 -> 3780.6579 | M111: Because we already know the EOP balance, this is a plug: EOP - D&A not from PP&E - BOP
C112: End of period | E112: =E50 -> 18177 | F112: =F50 -> 22283 | G112: =G50 -> 21391.68 | H112: =H50 -> 22675.181 | I112: =I50 -> 24239.768 | J112: =J50 -> 25912.312 | K112: =K50 -> 27700.262 | M112: Referenced from balance sheet
C114: RETAINED EARNINGS
C115: Beginning of period | G115: =F119 -> 70400 | H115: =G119 -> 35907.506 | I115: =H119 -> 5326.4074 | J115: =I119 -> -21502.072 | K115: =J119 -> -44514.32 | M115: BOP = Previous year EOP
C116: Plus: Net income | D116: =D28 -> 45687 | E116: =E28 -> 48351 | F116: =F28 -> 59531 | G116: =G28 -> 52298.506 | H116: =H28 -> 56209.901 | I116: =I28 -> 59962.52 | J116: =J28 -> 63778.753 | K116: =K28 -> 67967.319 | M116: Reference from income statement
C117: Less: Dividends | D117: -12188 | E117: -12803 | F117: -13735 | G117: =F117 -> -13735 | H117: =G117 -> -13735 | I117: =H117 -> -13735 | J117: =I117 -> -13735 | K117: =J117 -> -13735 | M117: WSP assumption: Straight-line last historical year dividends
C118: Less: Repurchases | D118: -29000 | E118: -33001 | F118: -73056 | G118: =F118 -> -73056 | H118: =G118 -> -73056 | I118: =H118 -> -73056 | J118: =I118 -> -73056 | K118: =J118 -> -73056 | M118: WSP assumption: Straight-line last historical year repurchases
C119: End of period | D119: =D62 -> 0 | E119: =E62 -> 98330 | F119: =F62 -> 70400 | G119: =SUM(G115:G118) -> 35907.506 | H119: =SUM(H115:H118) -> 5326.4074 | I119: =SUM(I115:I118) -> -21502.072 | J119: =SUM(J115:J118) -> -44514.32 | K119: =SUM(K115:K118) -> -63338.001 | M119: BOP + net income - dividends - repurchases
...

Sheet FSM 2025
C2: ="Financial Statement Model for "&D5 -> Financial Statement Model for Apple
C3: $ in thousands except per share
C5: Company name | D5: Apple
C6: Ticker | D6: AAPL
C7: Circ break 1=off, 0=on | D7: 1
C8: Latest closing share price | D8: 296.42
C9: Latest closing share price date | D9: 46189
C10: Latest fiscal year end date | D10: 45927
C11: Shares outstanding (millions) | D11: 14776.353
C13: INCOME STATEMENT
C14: Fiscal year | D14: =E14-1 -> 2023 | E14: =F14-1 -> 2024 | F14: =YEAR(D10) -> 2025 | G14: =F14+1 -> 2026 | H14: =G14+1 -> 2027 | I14: =H14+1 -> 2028 | J14: =I14+1 -> 2029 | K14: =J14+1 -> 2030
C15: Fiscal year end date | D15: =EOMONTH(E15,-12) -> 45199 | E15: =EOMONTH(F15,-12) -> 45565 | F15: =D10 -> 45927 | G15: =EOMONTH(F15,12) -> 46295 | H15: =EOMONTH(G15,12) -> 46660 | I15: =EOMONTH(H15,12) -> 47026 | J15: =EOMONTH(I15,12) -> 47391 | K15: =EOMONTH(J15,12) -> 47756 | M15: WSP Comments
C17: Revenue | D17: 383285 | E17: 391035 | F17: 416161 | G17: =F17*(1+G36) -> 436969.05 | H17: =G17*(1+H36) -> 458817.5 | I17: =H17*(1+I36) -> 481758.38 | J17: =I17*(1+J36) -> 505846.3 | K17: =J17*(1+K36) -> 531138.61 | M17: Previous year's revenues x (1+revenue growth rate)
C18: Cost of sales (enter as -) | D18: -214137 | E18: -210352 | F18: -220960 | G18: =G19-G17 -> -232008 | H18: =H19-H17 -> -243608.4 | I18: =I19-I17 -> -255788.82 | J18: =J19-J17 -> -268578.26 | K18: =K19-K17 -> -282007.17 | M18: Plug = Revenue - Gross Profit
C19: Gross Profit | D19: =SUM(D17:D18) -> 169148 | E19: =SUM(E17:E18) -> 180683 | F19: =SUM(F17:F18) -> 195201 | G19: =G17*G37 -> 204961.05 | H19: =H17*H37 -> 215209.1 | I19: =I17*I37 -> 225969.56 | J19: =J17*J37 -> 237268.04 | K19: =K17*K37 -> 249131.44 | M19: Revenue x Gross Profit Margin forecast
C20: Research & development (enter as -) | D20: -29915 | E20: -31370 | F20: -34550 | G20: =-G38*G17 -> -36277.5 | H20: =-H38*H17 -> -38091.375 | I20: =-I38*I17 -> -39995.944 | J20: =-J38*J17 -> -41995.741 | K20: =-K38*K17 -> -44095.528 | M20: Revenue x R&D % of sales forecast
C21: Selling, general & administrative (enter as -) | D21: -24932 | E21: -26097 | F21: -27601 | G21: =-G17*G39 -> -28981.05 | H21: =-H17*H39 -> -30430.103 | I21: =-I17*I39 -> -31951.608 | J21: =-J17*J39 -> -33549.188 | K21: =-K17*K39 -> -35226.647 | M21: Revenue x SG&A % of sales forecast
C22: Operating profit (EBIT) | D22: =D19+D20+D21 -> 114301 | E22: =E19+E20+E21 -> 123216 | F22: =F19+F20+F21 -> 133050 | G22: =G19+G20+G21 -> 139702.5 | H22: =H19+H20+H21 -> 146687.63 | I22: =I19+I20+I21 -> 154022.01 | J22: =J19+J20+J21 -> 161723.11 | K22: =K19+K20+K21 -> 169809.26 | M22: Gross Profit - R&D - SG&A
C23: Interest income | D23: 0 | E23: 0 | F23: 0 | G23: =G156 -> 5112.0223 | H23: =H156 -> 6126.2494 | I23: =I156 -> 7340.2595 | J23: =J156 -> 8845.3404 | K23: =K156 -> 10663.488 | M23: Reference from interest on cash schedule
C24: Interest expense (enter as -) | D24: 0 | E24: 0 | F24: 0 | G24: =-G142 -> -3002.8831 | H24: =-H142 -> -3087.123 | I24: =-I142 -> -3087.123 | J24: =-J142 -> -3087.123 | K24: =-K142 -> -3087.123 | M24: Reference from interest expense schedule
C25: Other expense, net (enter as -) | D25: -565 | E25: 269 | F25: -321 | G25: =F25 -> -321 | H25: =G25 -> -321 | I25: =H25 -> -321 | J25: =I25 -> -321 | K25: =J25 -> -321 | M25: Straight-line
C26: Pretax profit | D26: =SUM(D22:D25) -> 113736 | E26: =SUM(E22:E25) -> 123485 | F26: =SUM(F22:F25) -> 132729 | G26: =SUM(G22:G25) -> 141490.64 | H26: =SUM(H22:H25) -> 149405.75 | I26: =SUM(I22:I25) -> 157954.14 | J26: =SUM(J22:J25) -> 167160.32 | K26: =SUM(K22:K25) -> 177064.63 | M26: EBIT + interest income less interest expense less other expense
C27: Taxes (enter expense as -) | D27: -16741 | E27: -29749 | F27: -20719 | G27: =-G40*G26 -> -22086.692 | H27: =-H40*H26 -> -23322.241 | I27: =-I40*I26 -> -24656.645 | J27: =-J40*J26 -> -26093.73 | K27: =-K40*K26 -> -27639.792 | M27: Pre-tax Profit x Tax Rate forecast
C28: Net income | D28: =SUM(D26:D27) -> 96995 | E28: =SUM(E26:E27) -> 93736 | F28: =SUM(F26:F27) -> 112010 | G28: =SUM(G26:G27) -> 119403.95 | H28: =SUM(H26:H27) -> 126083.51 | I28: =SUM(I26:I27) -> 133297.5 | J28: =SUM(J26:J27) -> 141066.59 | K28: =SUM(K26:K27) -> 149424.83 | M28: Pre-tax Profit less taxes
C30: Depreciation & amortization | D30: 11519 | E30: 11445 | F30: 11698 | G30: =G106 -> 12549.915 | H30: =H106 -> 13457.776 | I30: =I106 -> 14425.049 | J30: =J106 -> 15455.405 | K30: =K106 -> 16552.734 | M30: Reference from D&A schedule
C31: EBITDA | D31: =D22+D30 -> 125820 | E31: =E22+E30 -> 134661 | F31: =F22+F30 -> 144748 | G31: =G22+G30 -> 152252.42 | H31: =H22+H30 -> 160145.4 | I31: =I22+I30 -> 168447.06 | J31: =J22+J30 -> 177178.51 | K31: =K22+K30 -> 186362 | M31: EBIT + D&A
C32: Stock based compensation | D32: 10833 | E32: 11688 | F32: 12863 | G32: =F32*(1+G36) -> 13506.15 | H32: =G32*(1+H36) -> 14181.458 | I32: =H32*(1+I36) -> 14890.53 | J32: =I32*(1+J36) -> 15635.057 | K32: =J32*(1+K36) -> 16416.81 | M32: WSP assumption: grow SBC in-line with revenue growth
C33: Adjusted EBITDA | D33: =SUM(D31:D32) -> 136653 | E33: =SUM(E31:E32) -> 146349 | F33: =SUM(F31:F32) -> 157611 | G33: =SUM(G31:G32) -> 165758.57 | H33: =SUM(H31:H32) -> 174326.86 | I33: =SUM(I31:I32) -> 183337.59 | J33: =SUM(J31:J32) -> 192813.57 | K33: =SUM(K31:K32) -> 202778.81 | M33: EBITDA + Stock-based compensation
C35: Growth rates & margins
C36: Revenue growth | E36: =E17/D17-1 -> 0.020219941 | F36: =F17/E17-1 -> 0.064255118 | G36: 0.05 | H36: 0.05 | I36: 0.05 | J36: =I36 -> 0.05 | K36: =J36 -> 0.05 | M36: JP Morgan estimates through 2021; straight-line growth rate thereafter
C37: Gross profit margin | D37: =D19/D17 -> 0.4413113 | E37: =E19/E17 -> 0.4620635 | F37: =F19/F17 -> 0.46905164 | G37: =F37 -> 0.46905164 | H37: =G37 -> 0.46905164 | I37: =H37 -> 0.46905164 | J37: =I37 -> 0.46905164 | K37: =J37 -> 0.46905164 | M37: JP Morgan estimates through 2021; straight-line margin thereafter
C38: R&D % of sales | D38: =-D20/D17 -> 0.078048971 | E38: =-E20/E17 -> 0.080222998 | F38: =-F20/F17 -> 0.083020754 | G38: =F38 -> 0.083020754 | H38: =G38 -> 0.083020754 | I38: =H38 -> 0.083020754 | J38: =I38 -> 0.083020754 | K38: =J38 -> 0.083020754 | M38: JP Morgan estimates through 2021: straight-line margin thereafter
C39: SG&A % of sales | D39: =-D21/D17 -> 0.065048202 | E39: =-E21/E17 -> 0.066738272 | F39: =-F21/F17 -> 0.066322889 | G39: =F39 -> 0.066322889 | H39: =G39 -> 0.066322889 | I39: =H39 -> 0.066322889 | J39: =I39 -> 0.066322889 | K39: =J39 -> 0.066322889 | M39: JP Morgan estimates through 2021: straight-line margin thereafter
C40: Tax rate | D40: =-(D27/D26) -> 0.14719174 | E40: =-(E27/E26) -> 0.24091185 | F40: =-(F27/F26) -> 0.15610002 | G40: =F40 -> 0.15610002 | H40: =G40 -> 0.15610002 | I40: =H40 -> 0.15610002 | J40: =I40 -> 0.15610002 | K40: =J40 -> 0.15610002 | M40: JP Morgan estimates through 2021: straight-line margin thereafter
C42: BALANCE SHEET
C43: =C14 -> Fiscal year | E43: =E14 -> 2024 | F43: =F14 -> 2025 | G43: =G14 -> 2026 | H43: =H14 -> 2027 | I43: =I14 -> 2028 | J43: =J14 -> 2029 | K43: =K14 -> 2030
C44: =C15 -> Fiscal year end date | E44: =E15 -> 45565 | F44: =F15 -> 45927 | G44: =G15 -> 46295 | H44: =H15 -> 46660 | I44: =I15 -> 47026 | J44: =J15 -> 47391 | K44: =K15 -> 47756
C45: Cash & equivalents, ST and LT marketable securities | E45: =29943+35228+91479 -> 156650 | F45: =35934+18763+77723 -> 132420 | G45: =G90+F45 -> 159695.56 | H45: =H90+G45 -> 190375.83 | I45: =I90+H45 -> 229067.56 | J45: =J90+I45 -> 276380.46 | K45: =K90+J45 -> 332961.71 | M45: Reference from 'net change in cash' line on the cash flow statement
C46: Accounts receivable | E46: 33410 | F46: 39777 | G46: =F46*(1+G36) -> 41765.85 | H46: =G46*(1+H36) -> 43854.143 | I46: =H46*(1+I36) -> 46046.85 | J46: =I46*(1+J36) -> 48349.192 | K46: =J46*(1+K36) -> 50766.652 | M46: Grow in-line with revenue growth
C47: Inventories | E47: 7286 | F47: 5718 | G47: =F47*G18/F18 -> 6003.9 | H47: =G47*H18/G18 -> 6304.095 | I47: =H47*I18/H18 -> 6619.2998 | J47: =I47*J18/I18 -> 6950.2647 | K47: =J47*K18/J18 -> 7297.778 | M47: Grow in-line with cost of sales growth
C48: Other current assets | E48: =14287+32833 -> 47120 | F48: =14585+33180 -> 47765 | G48: =F48*(1+G36) -> 50153.25 | H48: =G48*(1+H36) -> 52660.913 | I48: =H48*(1+I36) -> 55293.958 | J48: =I48*(1+J36) -> 58058.656 | K48: =J48*(1+K36) -> 60961.589 | M48: Grow in-line with revenue growth
C49: Property, plant & equipment | E49: 45680 | F49: 49834 | G49: =G99 -> 54517.735 | H49: =H99 -> 59155.291 | I49: =I99 -> 63730.341 | J49: =J99 -> 68225.04 | K49: =K99 -> 72619.915 | M49: Reference from PP&E schedule
C50: Other non current assets | E50: 74834 | F50: 83727 | G50: =F50*(1+G36) -> 87913.35 | H50: =G50*(1+H36) -> 92309.018 | I50: =H50*(1+I36) -> 96924.468 | J50: =I50*(1+J36) -> 101770.69 | K50: =J50*(1+K36) -> 106859.23 | M50: Grow in-line with revenue growth
C51: Total assets | E51: =SUM(E45:E50) -> 364980 | F51: =SUM(F45:F50) -> 359241 | G51: =SUM(G45:G50) -> 400049.65 | H51: =SUM(H45:H50) -> 444659.29 | I51: =SUM(I45:I50) -> 497682.48 | J51: =SUM(J45:J50) -> 559734.3 | K51: =SUM(K45:K50) -> 631466.87
C53: Accounts payable | E53: 68960 | F53: 69860 | G53: =F53*G18/F18 -> 73353 | H53: =G53*H18/G18 -> 77020.65 | I53: =H53*I18/H18 -> 80871.683 | J53: =I53*J18/I18 -> 84915.267 | K53: =J53*K18/J18 -> 89161.03 | M53: Grow in-line with cost of sales growth
C54: Other current liabilities | E54: 78304 | F54: 66387 | G54: =F54*(1+G36) -> 69706.35 | H54: =G54*(1+H36) -> 73191.668 | I54: =H54*(1+I36) -> 76851.251 | J54: =I54*(1+J36) -> 80693.813 | K54: =J54*(1+K36) -> 84728.504 | M54: Grow in-line with revenue growth
C55: Deferred revenue (current and non current) | E55: 8249 | F55: 9055 | G55: =F55*(1+G36) -> 9507.75 | H55: =G55*(1+H36) -> 9983.1375 | I55: =H55*(1+I36) -> 10482.294 | J55: =I55*(1+J36) -> 11006.409 | K55: =J55*(1+K36) -> 11556.73 | M55: Grow in-line with revenue growth
C56: Commercial paper / revolver | E56: 9967 | F56: 7979 | G56: =G135 -> 12000 | H56: =H135 -> 12000 | I56: =I135 -> 12000 | J56: =J135 -> 12000 | K56: =K135 -> 12000 | M56: Reference EOP balance from CP/revolver schedule
C57: Long term debt (includes current portion) | E57: =10912+85750 -> 96662 | F57: =12350+78328 -> 90678 | G57: =F57 -> 90678 | H57: =G57 -> 90678 | I57: =H57 -> 90678 | J57: =I57 -> 90678 | K57: =J57 -> 90678 | M57: WSP assumption: straight-line
C58: Other non current liabilities | E58: 45888 | F58: 41549 | G58: =F58*(1+G36) -> 43626.45 | H58: =G58*(1+H36) -> 45807.773 | I58: =H58*(1+I36) -> 48098.161 | J58: =I58*(1+J36) -> 50503.069 | K58: =J58*(1+K36) -> 53028.223 | M58: Grow in-line with revenue growth
C59: Total liabilities | E59: =SUM(E53:E58) -> 308030 | F59: =SUM(F53:F58) -> 285508 | G59: =SUM(G53:G58) -> 298871.55 | H59: =SUM(H53:H58) -> 308681.23 | I59: =SUM(I53:I58) -> 318981.39 | J59: =SUM(J53:J58) -> 329796.56 | K59: =SUM(K53:K58) -> 341152.49
C61: Common stock | E61: 83276 | F61: 93568 | G61: =F61+G32 -> 107074.15 | H61: =G61+H32 -> 121255.61 | I61: =H61+I32 -> 136146.14 | J61: =I61+J32 -> 151781.19 | K61: =J61+K32 -> 168198 | M61: Increase by stock-based compensation forecasted in the I/S section
C62: Retained earnings | E62: -19154 | F62: -14264 | G62: =G119 -> -325.05281 | H62: =H119 -> 20293.457 | I62: =I119 -> 48125.955 | J62: =J119 -> 83727.548 | K62: =K119 -> 127687.38 | M62: Reference from Retained Earnings schedule
C63: Other comprehensive income | E63: -7172 | F63: -5571 | G63: =F63 -> -5571 | H63: =G63 -> -5571 | I63: =H63 -> -5571 | J63: =I63 -> -5571 | K63: =J63 -> -5571 | M63: WSP assumption: straight-line
C64: Total equity | E64: =SUM(E61:E63) -> 56950 | F64: =SUM(F61:F63) -> 73733 | G64: =SUM(G61:G63) -> 101178.1 | H64: =SUM(H61:H63) -> 135978.06 | I64: =SUM(I61:I63) -> 178701.09 | J64: =SUM(J61:J63) -> 229937.74 | K64: =SUM(K61:K63) -> 290314.39
C66: Balance check | E66: =ROUND(E51-E59-E64,3) -> 0 | F66: =ROUND(F51-F59-F64,3) -> 0 | G66: =ROUND(G51-G59-G64,3) -> 0 | H66: =ROUND(H51-H59-H64,3) -> 0 | I66: =ROUND(I51-I59-I64,3) -> 0 | J66: =ROUND(J51-J59-J64,3) -> 0 | K66: =ROUND(K51-K59-K64,3) -> 0
C68: CASH FLOW STATEMENT
C69: =C14 -> Fiscal year | G69: =G14 -> 2026 | H69: =H14 -> 2027 | I69: =I14 -> 2028 | J69: =J14 -> 2029 | K69: =K14 -> 2030
C70: =C15 -> Fiscal year end date | G70: =G15 -> 46295 | H70: =H15 -> 46660 | I70: =I15 -> 47026 | J70: =J15 -> 47391 | K70: =K15 -> 47756
C72: Net income | G72: =G28 -> 119403.95 | H72: =H28 -> 126083.51 | I72: =I28 -> 133297.5 | J72: =J28 -> 141066.59 | K72: =K28 -> 149424.83
C73: Depreciation and amortization | G73: =G30 -> 12549.915 | H73: =H30 -> 13457.776 | I73: =I30 -> 14425.049 | J73: =J30 -> 15455.405 | K73: =K30 -> 16552.734 | M73: Reference from the I/S
C74: Stock based compensation | G74: =G32 -> 13506.15 | H74: =H32 -> 14181.458 | I74: =I32 -> 14890.53 | J74: =J32 -> 15635.057 | K74: =K32 -> 16416.81
C75: Decreases / (Increases) in working capital assets | G75: =-1*(SUM(G46:G48)-SUM(F46:F48)) -> -4663 | H75: =-1*(SUM(H46:H48)-SUM(G46:G48)) -> -4896.15 | I75: =-1*(SUM(I46:I48)-SUM(H46:H48)) -> -5140.9575 | J75: =-1*(SUM(J46:J48)-SUM(I46:I48)) -> -5398.0054 | K75: =-1*(SUM(K46:K48)-SUM(J46:J48)) -> -5667.9056
C76: Increases / (Decreases) in working capital liabilities | G76: =SUM(G53:G55)-SUM(F53:F55) -> 7265.1 | H76: =SUM(H53:H55)-SUM(G53:G55) -> 7628.355 | I76: =SUM(I53:I55)-SUM(H53:H55) -> 8009.7728 | J76: =SUM(J53:J55)-SUM(I53:I55) -> 8410.2614 | K76: =SUM(K53:K55)-SUM(J53:J55) -> 8830.7745
C77: Other non current assets | G77: =-(G111) -> -8069.25 | H77: =-(H111) -> -8472.7125 | I77: =-(I111) -> -8896.3481 | J77: =-(J111) -> -9341.1655 | K77: =-(K111) -> -9808.2238 | M77: Reference from schedule NOT the B/S: Only include 'Additions' (as outflow)
C78: Other non current liabilities | G78: =G58-F58 -> 2077.45 | H78: =H58-G58 -> 2181.3225 | I78: =I58-H58 -> 2290.3886 | J78: =J58-I58 -> 2404.9081 | K78: =K58-J58 -> 2525.1535
C79: Cash from operating activities | G79: =SUM(G72:G78) -> 142070.31 | H79: =SUM(H72:H78) -> 150163.56 | I79: =SUM(I72:I78) -> 158875.93 | J79: =SUM(J72:J78) -> 168233.05 | K79: =SUM(K72:K78) -> 178274.18
C81: Capital expenditures | G81: =-(G97) -> -13350.75 | H81: =-(H97) -> -14018.288 | I81: =-(I97) -> -14719.202 | J81: =-(J97) -> -15455.162 | K81: =-(K97) -> -16227.92 | M81: Reference from PP&E schedule
C82: Cash from investing activities | G82: =IFERROR(G81,"NA") -> -13350.75 | H82: =IFERROR(H81,"NA") -> -14018.288 | I82: =IFERROR(I81,"NA") -> -14719.202 | J82: =IFERROR(J81,"NA") -> -15455.162 | K82: =IFERROR(K81,"NA") -> -16227.92
C84: Long term debt | G84: =G57-F57 -> 0 | H84: =H57-G57 -> 0 | I84: =I57-H57 -> 0 | J84: =J57-I57 -> 0 | K84: =K57-J57 -> 0
C85: Revolver | G85: =G56-F56 -> 4021 | H85: =H56-G56 -> 0 | I85: =I56-H56 -> 0 | J85: =J56-I56 -> 0 | K85: =K56-J56 -> 0 | M85: Reference from B/S
C86: Share repurchases | G86: =G118 -> -90052 | H86: =H118 -> -90052 | I86: =I118 -> -90052 | J86: =J118 -> -90052 | K86: =K118 -> -90052 | M86: Reference from Retained Earnings schedule
C87: Common dividends | G87: =G117 -> -15413 | H87: =H117 -> -15413 | I87: =I117 -> -15413 | J87: =J117 -> -15413 | K87: =K117 -> -15413 | M87: Reference from Retained Earnings schedule
C88: Cash from financing activities | G88: =SUM(G84:G87) -> -101444 | H88: =SUM(H84:H87) -> -105465 | I88: =SUM(I84:I87) -> -105465 | J88: =SUM(J84:J87) -> -105465 | K88: =SUM(K84:K87) -> -105465
C90: Net change in cash during period | G90: =G79+G82+G88 -> 27275.562 | H90: =H79+H82+H88 -> 30680.272 | I90: =I79+I82+I88 -> 38691.731 | J90: =J79+J82+J88 -> 47312.892 | K90: =K79+K82+K88 -> 56581.256
C92: PROPERTY, PLANT & EQUIPMENT
C93: =C14 -> Fiscal year | D93: =D14 -> 2023 | E93: =E14 -> 2024 | F93: =F14 -> 2025 | G93: =G14 -> 2026 | H93: =H14 -> 2027 | I93: =I14 -> 2028 | J93: =J14 -> 2029 | K93: =K14 -> 2030
C94: =C15 -> Fiscal year end date | D94: =D15 -> 45199 | E94: =E15 -> 45565 | F94: =F15 -> 45927 | G94: =G15 -> 46295 | H94: =H15 -> 46660 | I94: =I15 -> 47026 | J94: =J15 -> 47391 | K94: =K15 -> 47756
G95: Forecast
C96: Beginning of period | G96: =F99 -> 49834 | H96: =G99 -> 54517.735 | I96: =H99 -> 59155.291 | J96: =I99 -> 63730.341 | K96: =J99 -> 68225.04 | M96: BOP = Previous year EOP
C97: Plus: Capital expenditures | D97: 10959 | E97: 9447 | F97: 12715 | G97: =F97*(1+G36) -> 13350.75 | H97: =G97*(1+H36) -> 14018.288 | I97: =H97*(1+I36) -> 14719.202 | J97: =I97*(1+J36) -> 15455.162 | K97: =J97*(1+K36) -> 16227.92 | M97: JP Morgan through 2021; WSP assumption thereafter
C98: Less: Depreciation | D98: -8500 | E98: -8200 | F98: -8000 | G98: =-(G101*G97) -> -8667.015 | H98: =-(H101*H97) -> -9380.7315 | I98: =-(I101*I97) -> -10144.152 | J98: =-(J101*J97) -> -10960.463 | K98: =-(K101*K97) -> -11833.045 | M98: Capex x 'D&A related to PP&E as a % of capex' ratio (below)
C99: End of period | E99: =E49 -> 45680 | F99: =F49 -> 49834 | G99: =SUM(G96:G98) -> 54517.735 | H99: =SUM(H96:H98) -> 59155.291 | I99: =SUM(I96:I98) -> 63730.341 | J99: =SUM(J96:J98) -> 68225.04 | K99: =SUM(K96:K98) -> 72619.915 | M99: BOP + Capex - Depreciation
M100: Step
C101: D&A related to PP&E as a % of capex | D101: =-(D98/D97) -> 0.77561821 | E101: =-(E98/E97) -> 0.86800042 | F101: =-(F98/F97) -> 0.62917814 | G101: =F101+$M$101 -> 0.64917814 | H101: =G101+$M$101 -> 0.66917814 | I101: =H101+$M$101 -> 0.68917814 | J101: =I101+$M$101 -> 0.70917814 | K101: =J101+$M$101 -> 0.72917814 | M101: 0.02
C103: IMPUTING TOTAL DEPRECIATION & AMORTIZATION
C104: D&A not related to PP&E | D104: =D106+D98 -> 3019 | E104: =E106+E98 -> 3245 | F104: =F106+F98 -> 3698 | G104: =G105*G17 -> 3882.9 | H104: =H105*H17 -> 4077.045 | I104: =I105*I17 -> 4280.8973 | J104: =J105*J17 -> 4494.9421 | K104: =K105*K17 -> 4719.6892 | M104: Revenue x 'as % of revenue' assumption
C105: as % of revenue | D105: =D104/D17 -> 0.0078766453 | E105: =E104/E17 -> 0.0082984899 | F105: =F104/F17 -> 0.008885984 | G105: =F105 -> 0.008885984 | H105: =G105 -> 0.008885984 | I105: =H105 -> 0.008885984 | J105: =I105 -> 0.008885984 | K105: =J105 -> 0.008885984 | M105: Straight line last historical % of revenue - WSP assumption
C106: Depreciation & Amortization - Total | D106: =D30 -> 11519 | E106: =E30 -> 11445 | F106: =F30 -> 11698 | G106: =-G98+G104 -> 12549.915 | H106: =-H98+H104 -> 13457.776 | I106: =-I98+I104 -> 14425.049 | J106: =-J98+J104 -> 15455.405 | K106: =-K98+K104 -> 16552.734 | M106: D&A from PP&E + D&A not from PP&E
C108: OTHER NON-CURRENT ASSETS
C109: Beginning of period | G109: =F112 -> 83727 | H109: =G112 -> 87913.35 | I109: =H112 -> 92309.018 | J109: =I112 -> 96924.468 | K109: =J112 -> 101770.69 | M109: BOP = Previous year EOP
C110: Less: Amortization of intangible assets | G110: =-(G104) -> -3882.9 | H110: =-(H104) -> -4077.045 | I110: =-(I104) -> -4280.8973 | J110: =-(J104) -> -4494.9421 | K110: =-(K104) -> -4719.6892 | M110: Assume all D&A not from PP&E is in non-current assets
C111: Plus: Additions | G111: =G112-G110-G109 -> 8069.25 | H111: =H112-H110-H109 -> 8472.7125 | I111: =I112-I110-I109 -> 8896.3481 | J111: =J112-J110-J109 -> 9341.1655 | K111: =K112-K110-K109 -> 9808.2238 | M111: Because we already know the EOP balance, this is a plug: EOP - D&A not from PP&E - BOP
C112: End of period | E112: =E50 -> 74834 | F112: =F50 -> 83727 | G112: =G50 -> 87913.35 | H112: =H50 -> 92309.018 | I112: =I50 -> 96924.468 | J112: =J50 -> 101770.69 | K112: =K50 -> 106859.23 | M112: Referenced from balance sheet
C114: RETAINED EARNINGS
C115: Beginning of period | G115: =F119 -> -14264 | H115: =G119 -> -325.05281 | I115: =H119 -> 20293.457 | J115: =I119 -> 48125.955 | K115: =J119 -> 83727.548 | M115: BOP = Previous year EOP
C116: Plus: Net income | D116: =D28 -> 96995 | E116: =E28 -> 93736 | F116: =F28 -> 112010 | G116: =G28 -> 119403.95 | H116: =H28 -> 126083.51 | I116: =I28 -> 133297.5 | J116: =J28 -> 141066.59 | K116: =K28 -> 149424.83 | M116: Reference from income statement
C117: Less: Dividends | D117: -14996 | E117: -15218 | F117: -15413 | G117: =F117 -> -15413 | H117: =G117 -> -15413 | I117: =H117 -> -15413 | J117: =I117 -> -15413 | K117: =J117 -> -15413 | M117: WSP assumption: Straight-line last historical year dividends
C118: Less: Repurchases | D118: -77046 | E118: -95846 | F118: -90052 | G118: =F118 -> -90052 | H118: =G118 -> -90052 | I118: =H118 -> -90052 | J118: =I118 -> -90052 | K118: =J118 -> -90052 | M118: WSP assumption: Straight-line last historical year repurchases
C119: End of period | D119: =D62 -> 0 | E119: =E62 -> -19154 | F119: =F62 -> -14264 | G119: =SUM(G115:G118) -> -325.05281 | H119: =SUM(H115:H118) -> 20293.457 | I119: =SUM(I115:I118) -> 48125.955 | J119: =SUM(J115:J118) -> 83727.548 | K119: =SUM(K115:K118) -> 127687.38 | M119: BOP + net income - dividends - repurchases
...

Sheet Find the errors
C2: ="Financial Statement Model for "&D5 -> Financial Statement Model for Apple
C3: $ in thousands except per share
C5: Company name | D5: Apple
C6: Ticker | D6: AAPL
C7: Circ break 1=off, 0=on | D7: 1
C8: Latest closing share price | D8: 171.25
C9: Latest closing share price date | D9: 43500
C10: Latest fiscal year end date | D10: 43372
C11: Shares outstanding (millions) | D11: 4745.398
C13: INCOME STATEMENT
C14: Fiscal year | D14: =E14-1 -> 2016 | E14: =F14-1 -> 2017 | F14: =YEAR(D10) -> 2018 | G14: =F14+1 -> 2019 | H14: =G14+1 -> 2020 | I14: =H14+1 -> 2021 | J14: =I14+1 -> 2022 | K14: =J14+1 -> 2023
C15: Fiscal year end date | D15: =EOMONTH(E15,-12) -> 42643 | E15: =EOMONTH(F15,-12) -> 43008 | F15: =D10 -> 43372 | G15: =EOMONTH(F15,12) -> 43738 | H15: =EOMONTH(G15,12) -> 44104 | I15: =EOMONTH(H15,12) -> 44469 | J15: =EOMONTH(I15,12) -> 44834 | K15: =EOMONTH(J15,12) -> 45199 | M15: WSP Comments
C17: Revenue | D17: 215639 | E17: 229234 | F17: 265595 | G17: =F17*(1+G36) -> 254971.2 | H17: =G17*(1+H36) -> 270269.47 | I17: =H17*(1+I36) -> 288918.07 | J17: =I17*(1+J36) -> 308853.41 | K17: =J17*(1+K36) -> 330164.3 | M17: Previous year's revenues x (1+revenue growth rate)
C18: Cost of sales (enter as -) | D18: -131376 | E18: -141048 | F18: -163756 | G18: =G19-G17 -> -158592.09 | H18: =H19-H17 -> -167296.8 | I18: =I19-I17 -> -178551.36 | J18: =J19-J17 -> -190871.41 | K18: =K19-K17 -> -204041.54 | M18: Plug = Revenue - Gross Profit
C19: Gross Profit | D19: =SUM(D17:D18) -> 84263 | E19: =SUM(E17:E18) -> 88186 | F19: =SUM(F17:F18) -> 101839 | G19: =G17*G37 -> 96379.114 | H19: =H17*H37 -> 102972.67 | I19: =I17*I37 -> 110366.7 | J19: =J17*J37 -> 117982 | K19: =K17*K37 -> 126122.76 | M19: Revenue x Gross Profit Margin forecast
C20: Research & development (enter as -) | D20: -10045 | E20: -11581 | F20: -14236 | G20: =-G38*G17 -> -15808.214 | H20: =-H38*H17 -> -17026.977 | I20: =-I38*I17 -> -18201.838 | J20: =-J38*J17 -> -19457.765 | K20: =-K38*K17 -> -20800.351 | M20: Revenue x R&D % of sales forecast
C21: Selling, general & administrative (enter as -) | D21: -14194 | E21: -15261 | F21: -16705 | G21: =-G17*G39 -> -18867.869 | H21: =-H17*H39 -> -18648.594 | I21: =-I17*I39 -> -19935.347 | J21: =-J17*J39 -> -21310.885 | K21: =-K17*K39 -> -22781.337 | M21: Revenue x SG&A % of sales forecast
C22: Operating profit (EBIT) | D22: =D19+D20+D21 -> 60024 | E22: =E19+E20+E21 -> 61344 | F22: =F19+F20+F21 -> 70898 | G22: =G19+G20+G21 -> 61703.03 | H22: =H19+H20+H21 -> 67297.099 | I22: =I19+I20+I21 -> 72229.516 | J22: =J19+J20+J21 -> 77213.353 | K22: =K19+K20+K21 -> 82541.074 | M22: Gross Profit - R&D - SG&A
C23: Interest income | D23: 3999 | E23: 5201 | F23: 5686 | G23: =G156 -> 4854.9195 | H23: =H156 -> 4561.8995 | I23: =I156 -> 4589.125 | J23: =J156 -> 4760.1829 | K23: =K156 -> 5062.6676 | M23: Reference from interest on cash schedule
C24: Interest expense (enter as -) | D24: -1456 | E24: -2323 | F24: -3240 | G24: =-G142 -> -3223.1469 | H24: =-H142 -> -3223.5393 | I24: =-I142 -> -3223.5393 | J24: =-J142 -> -3223.5393 | K24: =-K142 -> -3223.5393 | M24: Reference from interest expense schedule
C25: Other expense, net (enter as -) | D25: -1195 | E25: -133 | F25: -441 | G25: =F25 -> -441 | H25: =G25 -> -441 | I25: =H25 -> -441 | J25: =I25 -> -441 | K25: =J25 -> -441 | M25: Straight-line
C26: Pretax profit | D26: =SUM(D22:D25) -> 61372 | E26: =SUM(E22:E25) -> 64089 | F26: =SUM(F22:F25) -> 72903 | G26: =SUM(G22:G25) -> 62893.803 | H26: =SUM(H22:H25) -> 68194.459 | I26: =SUM(I22:I25) -> 73154.102 | J26: =SUM(J22:J25) -> 78308.997 | K26: =SUM(K22:K25) -> 83939.203 | M26: EBIT + interest income less interest expense less other expense
C27: Taxes (enter expense as -) | D27: -15685 | E27: -15738 | F27: -13372 | G27: =-G40*G26 -> -10503.265 | H27: =-H40*H26 -> -11593.058 | I27: =-I40*I26 -> -12363.043 | J27: =-J40*J26 -> -13234.22 | K27: =-K40*K26 -> -14185.725 | M27: Pre-tax Profit x Tax Rate forecast
C28: Net income | D28: =SUM(D26:D27) -> 45687 | E28: =SUM(E26:E27) -> 48351 | F28: =SUM(F26:F27) -> 59531 | G28: =SUM(G26:G27) -> 52390.538 | H28: =SUM(H26:H27) -> 56601.401 | I28: =SUM(I26:I27) -> 60791.059 | J28: =SUM(J26:J27) -> 65074.776 | K28: =SUM(K26:K27) -> 69753.477 | M28: Pre-tax Profit less taxes
C30: Depreciation & amortization | D30: 10505 | E30: 10157 | F30: 10903 | G30: =G106 -> 11085.02 | H30: =H106 -> 11711.891 | I30: =I106 -> 12226.381 | J30: =J106 -> 13365.451 | K30: =K106 -> 14603.503 | M30: Reference from D&A schedule
C31: EBITDA | D31: =D22+D30 -> 70529 | E31: =E22+E30 -> 71501 | F31: =F22+F30 -> 81801 | G31: =G22+G30 -> 72788.051 | H31: =H22+H30 -> 79008.989 | I31: =I22+I30 -> 84455.897 | J31: =J22+J30 -> 90578.804 | K31: =K22+K30 -> 97144.578 | M31: EBIT + D&A
C32: Stock based compensation | D32: 4210 | E32: 4840 | F32: 5340 | G32: =F32*(1+G36) -> 5126.4 | H32: =G32*(1+H36) -> 5433.984 | I32: =H32*(1+I36) -> 5808.9289 | J32: =I32*(1+J36) -> 6209.745 | K32: =J32*(1+K36) -> 6638.2174 | M32: WSP assumption: grow SBC in-line with revenue growth
C33: Adjusted EBITDA | D33: =SUM(D31:D32) -> 74739 | E33: =SUM(E31:E32) -> 76341 | F33: =SUM(F31:F32) -> 87141 | G33: =SUM(G31:G32) -> 77914.451 | H33: =SUM(H31:H32) -> 84442.973 | I33: =SUM(I31:I32) -> 90264.826 | J33: =SUM(J31:J32) -> 96788.549 | K33: =SUM(K31:K32) -> 103782.8 | M33: EBITDA + Stock-based compensation
C35: Growth rates & margins
C36: Revenue growth | E36: =E17/D17-1 -> 0.063045182 | F36: =F17/E17-1 -> 0.15861958 | G36: -0.04 | H36: 0.06 | I36: 0.069 | J36: =I36 -> 0.069 | K36: =J36 -> 0.069 | M36: JP Morgan estimates through 2021; straight-line growth rate thereafter
C37: Gross profit margin | D37: =D19/D17 -> 0.39075956 | E37: =E19/E17 -> 0.3846986 | F37: =F19/F17 -> 0.38343719 | G37: 0.378 | H37: 0.381 | I37: 0.382 | J37: =I37 -> 0.382 | K37: =J37 -> 0.382 | M37: JP Morgan estimates through 2021; straight-line margin thereafter
C38: R&D % of sales | D38: =-D20/D17 -> 0.046582483 | E38: =-E20/E17 -> 0.050520429 | F38: =-F20/F17 -> 0.053600407 | G38: 0.062 | H38: 0.063 | I38: 0.063 | J38: =I38 -> 0.063 | K38: =J38 -> 0.063 | M38: JP Morgan estimates through 2021: straight-line margin thereafter
C39: SG&A % of sales | D39: =-D21/D17 -> 0.065822973 | E39: =-E21/E17 -> 0.066573894 | F39: =-F21/F17 -> 0.062896515 | G39: 0.074 | H39: 0.069 | I39: 0.069 | J39: =I39 -> 0.069 | K39: =J39 -> 0.069 | M39: JP Morgan estimates through 2021: straight-line margin thereafter
C40: Tax rate | D40: =-(D27/D26) -> 0.25557257 | E40: =-(E27/E26) -> 0.24556476 | F40: =-(F27/F26) -> 0.18342181 | G40: 0.167 | H40: 0.17 | I40: 0.169 | J40: =I40 -> 0.169 | K40: =J40 -> 0.169 | M40: JP Morgan estimates through 2021: straight-line margin thereafter
C42: BALANCE SHEET
C43: =C14 -> Fiscal year | E43: =E14 -> 2017 | F43: =F14 -> 2018 | G43: =G14 -> 2019 | H43: =H14 -> 2020 | I43: =I14 -> 2021 | J43: =J14 -> 2022 | K43: =K14 -> 2023
C44: =C15 -> Fiscal year end date | E44: =E15 -> 43008 | F44: =F15 -> 43372 | G44: =G15 -> 43738 | H44: =H15 -> 44104 | I44: =I15 -> 44469 | J44: =J15 -> 44834 | K44: =K15 -> 45199
C45: Cash & equivalents, ST and LT marketable securities | E45: =20289+53892+194714 -> 268895 | F45: =25913+40388+170799 -> 237100 | G45: =G90+F45 -> 212429.59 | H45: =H90+G45 -> 209968.51 | I45: =I90+H45 -> 214950.47 | J45: =J90+I45 -> 225807.21 | K45: =K90+J45 -> 242958.31 | M45: Reference from 'net change in cash' line on the cash flow statement
C46: Accounts receivable | E46: 17874 | F46: 23186 | G46: =F46*(1+G36) -> 22258.56 | H46: =G46*(1+H36) -> 23594.074 | I46: =H46*(1+I36) -> 25222.065 | J46: =I46*(1+J36) -> 26962.387 | K46: =J46*(1+K36) -> 28822.792 | M46: Grow in-line with revenue growth
C47: Inventories | E47: 4855 | F47: 3956 | G47: =F47*G18/F18 -> 3831.2507 | H47: =G47*H18/G18 -> 4041.5383 | I47: =H47*I18/H18 -> 4313.4248 | J47: =I47*J18/I18 -> 4611.0512 | K47: =J47*K18/J18 -> 4929.2137 | M47: Grow in-line with cost of sales growth
C48: Other current assets | E48: =17799+13936 -> 31735 | F48: =25809+12087 -> 37896 | G48: =F48*(1+G36) -> 36380.16 | H48: =G48*(1+H36) -> 38562.97 | I48: =H48*(1+I36) -> 41223.815 | J48: =I48*(1+J36) -> 44068.258 | K48: =J48*(1+K36) -> 47108.967 | M48: Grow in-line with revenue growth
C49: Property, plant & equipment | E49: 33783 | F49: 41304 | G49: =G99 -> 45042.86 | H49: =H99 -> 48611.182 | I49: =I99 -> 51947.568 | J49: =J99 -> 55218.714 | K49: =K99 -> 58399.733 | M49: Reference from PP&E schedule
C50: Other non current assets | E50: 18177 | F50: 22283 | G50: =F50*(1+G36) -> 21391.68 | H50: =G50*(1+H36) -> 22675.181 | I50: =H50*(1+I36) -> 24239.768 | J50: =I50*(1+J36) -> 25912.312 | K50: =J50*(1+K36) -> 27700.262 | M50: Grow in-line with revenue growth
C51: Total assets | E51: =SUM(E45:E50) -> 375319 | F51: =SUM(F45:F50) -> 365725 | G51: =SUM(G45:G50) -> 341334.1 | H51: =SUM(H45:H50) -> 347453.46 | I51: =SUM(I45:I50) -> 361897.11 | J51: =SUM(J45:J50) -> 382579.93 | K51: =SUM(K45:K50) -> 409919.28
C53: Accounts payable | E53: 44242 | F53: 55888 | G53: =F53*G18/F18 -> 54125.617 | H53: =G53*H18/G18 -> 57096.435 | I53: =H53*I18/H18 -> 60937.484 | J53: =I53*J18/I18 -> 65142.171 | K53: =J53*K18/J18 -> 69636.98 | M53: Grow in-line with cost of sales growth
C54: Other current liabilities | E54: 30551 | F54: 32687 | G54: =F54*(1+G36) -> 31379.52 | H54: =G54*(1+H36) -> 33262.291 | I54: =H54*(1+I36) -> 35557.389 | J54: =I54*(1+J36) -> 38010.849 | K54: =J54*(1+K36) -> 40633.598 | M54: Grow in-line with revenue growth
C55: Deferred revenue (current and non current) | E55: =7548+2836 -> 10384 | F55: =7543+2797 -> 10340 | G55: =F55*(1+G36) -> 9926.4 | H55: =G55*(1+H36) -> 10521.984 | I55: =H55*(1+I36) -> 11248.001 | J55: =I55*(1+J36) -> 12024.113 | K55: =J55*(1+K36) -> 12853.777 | M55: Grow in-line with revenue growth
C56: Commercial paper / revolver | E56: 11977 | F56: 11964 | G56: =G135 -> 12000 | H56: =H135 -> 12000 | I56: =I135 -> 12000 | J56: =J135 -> 12000 | K56: =K135 -> 12000 | M56: Reference EOP balance from CP/revolver schedule
C57: Long term debt (includes current portion) | E57: =6496+97207 -> 103703 | F57: =8784+93735 -> 102519 | G57: =F57 -> 102519 | H57: =G57 -> 102519 | I57: =H57 -> 102519 | J57: =I57 -> 102519 | K57: =J57 -> 102519 | M57: WSP assumption: straight-line
C58: Other non current liabilities | E58: 40415 | F58: 45180 | G58: =F58*(1+G36) -> 43372.8 | H58: =G58*(1+H36) -> 45975.168 | I58: =H58*(1+I36) -> 49147.455 | J58: =I58*(1+J36) -> 52538.629 | K58: =J58*(1+K36) -> 56163.794 | M58: Grow in-line with revenue growth
C59: Total liabilities | E59: =SUM(E53:E58) -> 241272 | F59: =SUM(F53:F58) -> 258578 | G59: =SUM(G53:G58) -> 253323.34 | H59: =SUM(H53:H58) -> 261374.88 | I59: =SUM(I53:I58) -> 271409.33 | J59: =SUM(J53:J58) -> 282234.76 | K59: =SUM(K53:K58) -> 293807.15
C61: Common stock | E61: 35867 | F61: 40201 | G61: =F61 -> 40201 | H61: =G61 -> 40201 | I61: =H61 -> 40201 | J61: =I61 -> 40201 | K61: =J61 -> 40201 | M61: Increase by stock-based compensation forecasted in the I/S section
C62: Retained earnings | E62: =98330 -> 98330 | F62: 70400 | G62: =G116+G117+G118 -> -34400.462 | H62: =H116+H117+H118 -> -30189.599 | I62: =I116+I117+I118 -> -25999.941 | J62: =J116+J117+J118 -> -21716.224 | K62: =K116+K117+K118 -> -17037.523 | M62: Reference from Retained Earnings schedule
C63: Other comprehensive income | E63: -150 | F63: -3454 | G63: =F63 -> -3454 | H63: =G63 -> -3454 | I63: =H63 -> -3454 | J63: =I63 -> -3454 | K63: =J63 -> -3454 | M63: WSP assumption: straight-line
C64: Total equity | E64: =SUM(E61:E63) -> 134047 | F64: =SUM(F61:F63) -> 107147 | G64: =SUM(G61:G63) -> 2346.5379 | H64: =SUM(H61:H63) -> 6557.4007 | I64: =SUM(I61:I63) -> 10747.059 | J64: =SUM(J61:J63) -> 15030.776 | K64: =SUM(K61:K63) -> 19709.477
C66: Balance check | E66: =ROUND(E51-E59-E64,3) -> 0 | F66: =ROUND(F51-F59-F64,3) -> 0 | G66: =ROUND(G51-G59-G64,3) -> 85664.221 | H66: =ROUND(H51-H59-H64,3) -> 79521.178 | I66: =ROUND(I51-I59-I64,3) -> 79740.719 | J66: =ROUND(J51-J59-J64,3) -> 85314.393 | K66: =ROUND(K51-K59-K64,3) -> 96402.649
C68: CASH FLOW STATEMENT
C69: =C14 -> Fiscal year | G69: =G14 -> 2019 | H69: =H14 -> 2020 | I69: =I14 -> 2021 | J69: =J14 -> 2022 | K69: =K14 -> 2023
C70: =C15 -> Fiscal year end date | G70: =G15 -> 43738 | H70: =H15 -> 44104 | I70: =I15 -> 44469 | J70: =J15 -> 44834 | K70: =K15 -> 45199
C72: Net income | G72: =G28 -> 52390.538 | H72: =H28 -> 56601.401 | I72: =I28 -> 60791.059 | J72: =J28 -> 65074.776 | K72: =K28 -> 69753.477
C73: Depreciation and amortization | G73: =G30 -> 11085.02 | H73: =H30 -> 11711.891 | I73: =I30 -> 12226.381 | J73: =J30 -> 13365.451 | K73: =K30 -> 14603.503 | M73: Reference from the I/S
C74: Stock based compensation | G74: =G32 -> 5126.4 | H74: =H32 -> 5433.984 | I74: =I32 -> 5808.9289 | J74: =J32 -> 6209.745 | K74: =K32 -> 6638.2174
C75: Decreases / (Increases) in working capital assets | G75: =SUM(G46:G48)-SUM(F46:F48) -> -2568.0293 | H75: =SUM(H46:H48)-SUM(G46:G48) -> 3728.6108 | I75: =SUM(I46:I48)-SUM(H46:H48) -> 4560.7225 | J75: =SUM(J46:J48)-SUM(I46:I48) -> 4882.392 | K75: =SUM(K46:K48)-SUM(J46:J48) -> 5219.277
C76: Increases / (Decreases) in working capital liabilities | G76: =SUM(G53:G55)-SUM(F53:F55) -> -3483.4631 | H76: =SUM(H53:H55)-SUM(G53:G55) -> 5449.1728 | I76: =SUM(I53:I55)-SUM(H53:H55) -> 6862.1646 | J76: =SUM(J53:J55)-SUM(I53:I55) -> 7434.2583 | K76: =SUM(K53:K55)-SUM(J53:J55) -> 7947.2222
C77: Other non current assets | G77: =F50-G50 -> 891.32 | H77: =G50-H50 -> -1283.5008 | I77: =H50-I50 -> -1564.5875 | J77: =I50-J50 -> -1672.544 | K77: =J50-K50 -> -1787.9495 | M77: Reference from schedule NOT the B/S: Only include 'Additions' (as outflow)
C78: Other non current liabilities | G78: =G58-F58 -> -1807.2 | H78: =H58-G58 -> 2602.368 | I78: =I58-H58 -> 3172.2866 | J78: =J58-I58 -> 3391.1744 | K78: =K58-J58 -> 3625.1654
C79: Cash from operating activities | G79: =SUM(G72:G78) -> 61634.586 | H79: =SUM(H72:H78) -> 84243.926 | I79: =SUM(I72:I78) -> 91856.954 | J79: =SUM(J72:J78) -> 98685.253 | K79: =SUM(K72:K78) -> 105998.91
C81: Capital expenditures | G81: =-(G97) -> -13285 | H81: =-(H97) -> -13649 | I81: =-(I97) -> -13819 | J81: =-(J97) -> -14772.511 | K81: =-(K97) -> -15791.814 | M81: Reference from PP&E schedule
C82: Cash from investing activities | G82: =IFERROR(G81,"NA") -> -13285 | H82: =IFERROR(H81,"NA") -> -13649 | I82: =IFERROR(I81,"NA") -> -13819 | J82: =IFERROR(J81,"NA") -> -14772.511 | K82: =IFERROR(K81,"NA") -> -15791.814
C84: Long term debt | G84: =G57-F57 -> 0 | H84: =H57-G57 -> 0 | I84: =I57-H57 -> 0 | J84: =J57-I57 -> 0 | K84: =K57-J57 -> 0
C85: Commercial paper/ Revolver | G85: =G56-F56 -> 36 | H85: =H56-G56 -> 0 | I85: =I56-H56 -> 0 | J85: =J56-I56 -> 0 | K85: =K56-J56 -> 0 | M85: Reference from B/S
C86: Share repurchases | G86: =G118 -> -73056 | H86: =H118 -> -73056 | I86: =I118 -> -73056 | J86: =J118 -> -73056 | K86: =K118 -> -73056 | M86: Reference from Retained Earnings schedule
C87: Common dividends | G87: =G117 -> -13735 | H87: =H117 -> -13735 | I87: =I117 -> -13735 | J87: =J117 -> -13735 | K87: =K117 -> -13735 | M87: Reference from Retained Earnings schedule
C88: Cash from financing activities | G88: =SUM(G84:G86) -> -73020 | H88: =SUM(H84:H86) -> -73056 | I88: =SUM(I84:I86) -> -73056 | J88: =SUM(J84:J86) -> -73056 | K88: =SUM(K84:K86) -> -73056
C90: Net change in cash during period | G90: =G79+G82+G88 -> -24670.414 | H90: =H79+H82+H88 -> -2461.0737 | I90: =I79+I82+I88 -> 4981.9545 | J90: =J79+J82+J88 -> 10856.742 | K90: =K79+K82+K88 -> 17151.099
C92: PROPERTY, PLANT & EQUIPMENT
C93: =C14 -> Fiscal year | D93: =D14 -> 2016 | E93: =E14 -> 2017 | F93: =F14 -> 2018 | G93: =G14 -> 2019 | H93: =H14 -> 2020 | I93: =I14 -> 2021 | J93: =J14 -> 2022 | K93: =K14 -> 2023
C94: =C15 -> Fiscal year end date | D94: =D15 -> 42643 | E94: =E15 -> 43008 | F94: =F15 -> 43372 | G94: =G15 -> 43738 | H94: =H15 -> 44104 | I94: =I15 -> 44469 | J94: =J15 -> 44834 | K94: =K15 -> 45199
G95: Forecast
C96: Beginning of period | G96: =F99 -> 41304 | H96: =G99 -> 45042.86 | I96: =H99 -> 48611.182 | J96: =I99 -> 51947.568 | K96: =J99 -> 55218.714 | M96: BOP = Previous year EOP
C97: Plus: Capital expenditures | D97: 12734 | E97: 12451 | F97: 13313 | G97: 13285 | H97: 13649 | I97: 13819 | J97: =I97*(1+J36) -> 14772.511 | K97: =J97*(1+K36) -> 15791.814 | M97: JP Morgan through 2021; WSP assumption thereafter
C98: Less: Depreciation | D98: -8300 | E98: -8200 | F98: -9300 | G98: =-(G101*G97) -> -9546.1402 | H98: =-(H101*H97) -> -10080.678 | I98: =-(I101*I97) -> -10482.614 | J98: =-(J101*J97) -> -11501.365 | K98: =-(K101*K97) -> -12610.795 | M98: Capex x 'D&A related to PP&E as a % of capex' ratio (below)
C99: End of period | E99: =E49 -> 33783 | F99: =F49 -> 41304 | G99: =SUM(G96:G98) -> 45042.86 | H99: =SUM(H96:H98) -> 48611.182 | I99: =SUM(I96:I98) -> 51947.568 | J99: =SUM(J96:J98) -> 55218.714 | K99: =SUM(K96:K98) -> 58399.733 | M99: BOP + Capex - Depreciation
M100: Step
C101: D&A related to PP&E as a % of capex | D101: =-(D98/D97) -> 0.65179834 | E101: =-(E98/E97) -> 0.65858164 | F101: =-(F98/F97) -> 0.69856531 | G101: =F101+$M$101 -> 0.71856531 | H101: =G101+$M$101 -> 0.73856531 | I101: =H101+$M$101 -> 0.75856531 | J101: =I101+$M$101 -> 0.77856531 | K101: =J101+$M$101 -> 0.79856531 | M101: 0.02
C103: IMPUTING TOTAL DEPRECIATION & AMORTIZATION
C104: D&A not related to PP&E | D104: =D106+D98 -> 2205 | E104: =E106+E98 -> 1957 | F104: =F106+F98 -> 1603 | G104: =G105*G17 -> 1538.88 | H104: =H105*H17 -> 1631.2128 | I104: =I105*I17 -> 1743.7665 | J104: =J105*J17 -> 1864.0864 | K104: =K105*K17 -> 1992.7083 | M104: Revenue x 'as % of revenue' assumption
C105: as % of revenue | D105: =D104/D17 -> 0.010225423 | E105: =E104/E17 -> 0.008537128 | F105: =F104/F17 -> 0.0060355052 | G105: =F105 -> 0.0060355052 | H105: =G105 -> 0.0060355052 | I105: =H105 -> 0.0060355052 | J105: =I105 -> 0.0060355052 | K105: =J105 -> 0.0060355052 | M105: Straight line last historical % of revenue - WSP assumption
C106: Depreciation & Amortization - Total | D106: =D30 -> 10505 | E106: =E30 -> 10157 | F106: =F30 -> 10903 | G106: =-G98+G104 -> 11085.02 | H106: =-H98+H104 -> 11711.891 | I106: =-I98+I104 -> 12226.381 | J106: =-J98+J104 -> 13365.451 | K106: =-K98+K104 -> 14603.503 | M106: D&A from PP&E + D&A not from PP&E
C108: OTHER NON-CURRENT ASSETS
C109: Beginning of period | G109: =F112 -> 22283 | H109: =G112 -> 21391.68 | I109: =H112 -> 22675.181 | J109: =I112 -> 24239.768 | K109: =J112 -> 25912.312 | M109: BOP = Previous year EOP
C110: Less: Amortization of intangible assets | G110: =-(G104) -> -1538.88 | H110: =-(H104) -> -1631.2128 | I110: =-(I104) -> -1743.7665 | J110: =-(J104) -> -1864.0864 | K110: =-(K104) -> -1992.7083 | M110: Assume all D&A not from PP&E is in non-current assets
C111: Plus: Additions | G111: =G112-G110-G109 -> 647.56 | H111: =H112-H110-H109 -> 2914.7136 | I111: =I112-I110-I109 -> 3308.354 | J111: =J112-J110-J109 -> 3536.6304 | K111: =K112-K110-K109 -> 3780.6579 | M111: Because we already know the EOP balance, this is a plug: EOP - D&A not from PP&E - BOP
C112: End of period | E112: =E50 -> 18177 | F112: =F50 -> 22283 | G112: =G50 -> 21391.68 | H112: =H50 -> 22675.181 | I112: =I50 -> 24239.768 | J112: =J50 -> 25912.312 | K112: =K50 -> 27700.262 | M112: Referenced from balance sheet
C114: RETAINED EARNINGS
C115: Beginning of period | G115: =F119 -> 70400 | H115: =G119 -> 35999.538 | I115: =H119 -> 5809.9387 | J115: =I119 -> -20190.002 | K115: =J119 -> -41906.226 | M115: BOP = Previous year EOP
C116: Plus: Net income | D116: =D28 -> 45687 | E116: =E28 -> 48351 | F116: =F28 -> 59531 | G116: =G28 -> 52390.538 | H116: =H28 -> 56601.401 | I116: =I28 -> 60791.059 | J116: =J28 -> 65074.776 | K116: =K28 -> 69753.477 | M116: Reference from income statement
C117: Less: Dividends | D117: -12188 | E117: -12803 | F117: -13735 | G117: =F117 -> -13735 | H117: =G117 -> -13735 | I117: =H117 -> -13735 | J117: =I117 -> -13735 | K117: =J117 -> -13735 | M117: WSP assumption: Straight-line last historical year dividends
C118: Less: Repurchases | D118: -29000 | E118: -33001 | F118: -73056 | G118: =F118 -> -73056 | H118: =G118 -> -73056 | I118: =H118 -> -73056 | J118: =I118 -> -73056 | K118: =J118 -> -73056 | M118: WSP assumption: Straight-line last historical year repurchases
C119: End of period | D119: =D62 -> 0 | E119: =E62 -> 98330 | F119: =F62 -> 70400 | G119: =SUM(G115:G118) -> 35999.538 | H119: =SUM(H115:H118) -> 5809.9387 | I119: =SUM(I115:I118) -> -20190.002 | J119: =SUM(J115:J118) -> -41906.226 | K119: =SUM(K115:K118) -> -58943.749 | M119: BOP + net income - dividends - repurchases
...

Sheet Find the errors Complete
C2: ="Financial Statement Model for "&D5 -> Financial Statement Model for Apple
C3: $ in thousands except per share
C5: Company name | D5: Apple
C6: Ticker | D6: AAPL
C7: Circ break 1=off, 0=on | D7: 1
C8: Latest closing share price | D8: 171.25
C9: Latest closing share price date | D9: 43500
C10: Latest fiscal year end date | D10: 43372
C11: Shares outstanding (millions) | D11: 4745.398
C13: INCOME STATEMENT
C14: Fiscal year | D14: =E14-1 -> 2016 | E14: =F14-1 -> 2017 | F14: =YEAR(D10) -> 2018 | G14: =F14+1 -> 2019 | H14: =G14+1 -> 2020 | I14: =H14+1 -> 2021 | J14: =I14+1 -> 2022 | K14: =J14+1 -> 2023
C15: Fiscal year end date | D15: =EOMONTH(E15,-12) -> 42643 | E15: =EOMONTH(F15,-12) -> 43008 | F15: =D10 -> 43372 | G15: =EOMONTH(F15,12) -> 43738 | H15: =EOMONTH(G15,12) -> 44104 | I15: =EOMONTH(H15,12) -> 44469 | J15: =EOMONTH(I15,12) -> 44834 | K15: =EOMONTH(J15,12) -> 45199 | M15: WSP Comments
C17: Revenue | D17: 215639 | E17: 229234 | F17: 265595 | G17: =F17*(1+G36) -> 254971.2 | H17: =G17*(1+H36) -> 270269.47 | I17: =H17*(1+I36) -> 288918.07 | J17: =I17*(1+J36) -> 308853.41 | K17: =J17*(1+K36) -> 330164.3 | M17: Previous year's revenues x (1+revenue growth rate)
C18: Cost of sales (enter as -) | D18: -131376 | E18: -141048 | F18: -163756 | G18: =G19-G17 -> -158592.09 | H18: =H19-H17 -> -167296.8 | I18: =I19-I17 -> -178551.36 | J18: =J19-J17 -> -190871.41 | K18: =K19-K17 -> -204041.54 | M18: Plug = Revenue - Gross Profit
C19: Gross Profit | D19: =SUM(D17:D18) -> 84263 | E19: =SUM(E17:E18) -> 88186 | F19: =SUM(F17:F18) -> 101839 | G19: =G17*G37 -> 96379.114 | H19: =H17*H37 -> 102972.67 | I19: =I17*I37 -> 110366.7 | J19: =J17*J37 -> 117982 | K19: =K17*K37 -> 126122.76 | M19: Revenue x Gross Profit Margin forecast
C20: Research & development (enter as -) | D20: -10045 | E20: -11581 | F20: -14236 | G20: =-G38*G17 -> -15808.214 | H20: =-H38*H17 -> -17026.977 | I20: =-I38*I17 -> -18201.838 | J20: =-J38*J17 -> -19457.765 | K20: =-K38*K17 -> -20800.351 | M20: Revenue x R&D % of sales forecast
C21: Selling, general & administrative (enter as -) | D21: -14194 | E21: -15261 | F21: -16705 | G21: =-G17*G39 -> -18867.869 | H21: =-H17*H39 -> -18648.594 | I21: =-I17*I39 -> -19935.347 | J21: =-J17*J39 -> -21310.885 | K21: =-K17*K39 -> -22781.337 | M21: Revenue x SG&A % of sales forecast
C22: Operating profit (EBIT) | D22: =D19+D20+D21 -> 60024 | E22: =E19+E20+E21 -> 61344 | F22: =F19+F20+F21 -> 70898 | G22: =G19+G20+G21 -> 61703.03 | H22: =H19+H20+H21 -> 67297.099 | I22: =I19+I20+I21 -> 72229.516 | J22: =J19+J20+J21 -> 77213.353 | K22: =K19+K20+K21 -> 82541.074 | M22: Gross Profit - R&D - SG&A
C23: Interest income | D23: 3999 | E23: 5201 | F23: 5686 | G23: =G156 -> 4744.4371 | H23: =H156 -> 4090.2133 | I23: =I156 -> 3592.0871 | J23: =J156 -> 3200.5876 | K23: =K156 -> 2913.2593 | M23: Reference from interest on cash schedule
C24: Interest expense (enter as -) | D24: -1456 | E24: -2323 | F24: -3240 | G24: =-G142 -> -3223.1469 | H24: =-H142 -> -3223.5393 | I24: =-I142 -> -3223.5393 | J24: =-J142 -> -3223.5393 | K24: =-K142 -> -3223.5393 | M24: Reference from interest expense schedule
C25: Other expense, net (enter as -) | D25: -1195 | E25: -133 | F25: -441 | G25: =F25 -> -441 | H25: =G25 -> -441 | I25: =H25 -> -441 | J25: =I25 -> -441 | K25: =J25 -> -441 | M25: Straight-line
C26: Pretax profit | D26: =SUM(D22:D25) -> 61372 | E26: =SUM(E22:E25) -> 64089 | F26: =SUM(F22:F25) -> 72903 | G26: =SUM(G22:G25) -> 62783.321 | H26: =SUM(H22:H25) -> 67722.773 | I26: =SUM(I22:I25) -> 72157.064 | J26: =SUM(J22:J25) -> 76749.401 | K26: =SUM(K22:K25) -> 81789.794 | M26: EBIT + interest income less interest expense less other expense
C27: Taxes (enter expense as -) | D27: -15685 | E27: -15738 | F27: -13372 | G27: =-G40*G26 -> -10484.815 | H27: =-H40*H26 -> -11512.871 | I27: =-I40*I26 -> -12194.544 | J27: =-J40*J26 -> -12970.649 | K27: =-K40*K26 -> -13822.475 | M27: Pre-tax Profit x Tax Rate forecast
C28: Net income | D28: =SUM(D26:D27) -> 45687 | E28: =SUM(E26:E27) -> 48351 | F28: =SUM(F26:F27) -> 59531 | G28: =SUM(G26:G27) -> 52298.506 | H28: =SUM(H26:H27) -> 56209.901 | I28: =SUM(I26:I27) -> 59962.52 | J28: =SUM(J26:J27) -> 63778.753 | K28: =SUM(K26:K27) -> 67967.319 | M28: Pre-tax Profit less taxes
C30: Depreciation & amortization | D30: 10505 | E30: 10157 | F30: 10903 | G30: =G106 -> 11085.02 | H30: =H106 -> 11711.891 | I30: =I106 -> 12226.381 | J30: =J106 -> 13365.451 | K30: =K106 -> 14603.503 | M30: Reference from D&A schedule
C31: EBITDA | D31: =D22+D30 -> 70529 | E31: =E22+E30 -> 71501 | F31: =F22+F30 -> 81801 | G31: =G22+G30 -> 72788.051 | H31: =H22+H30 -> 79008.989 | I31: =I22+I30 -> 84455.897 | J31: =J22+J30 -> 90578.804 | K31: =K22+K30 -> 97144.578 | M31: EBIT + D&A
C32: Stock based compensation | D32: 4210 | E32: 4840 | F32: 5340 | G32: =F32*(1+G36) -> 5126.4 | H32: =G32*(1+H36) -> 5433.984 | I32: =H32*(1+I36) -> 5808.9289 | J32: =I32*(1+J36) -> 6209.745 | K32: =J32*(1+K36) -> 6638.2174 | M32: WSP assumption: grow SBC in-line with revenue growth
C33: Adjusted EBITDA | D33: =SUM(D31:D32) -> 74739 | E33: =SUM(E31:E32) -> 76341 | F33: =SUM(F31:F32) -> 87141 | G33: =SUM(G31:G32) -> 77914.451 | H33: =SUM(H31:H32) -> 84442.973 | I33: =SUM(I31:I32) -> 90264.826 | J33: =SUM(J31:J32) -> 96788.549 | K33: =SUM(K31:K32) -> 103782.8 | M33: EBITDA + Stock-based compensation
C35: Growth rates & margins
C36: Revenue growth | E36: =E17/D17-1 -> 0.063045182 | F36: =F17/E17-1 -> 0.15861958 | G36: -0.04 | H36: 0.06 | I36: 0.069 | J36: =I36 -> 0.069 | K36: =J36 -> 0.069 | M36: JP Morgan estimates through 2021; straight-line growth rate thereafter
C37: Gross profit margin | D37: =D19/D17 -> 0.39075956 | E37: =E19/E17 -> 0.3846986 | F37: =F19/F17 -> 0.38343719 | G37: 0.378 | H37: 0.381 | I37: 0.382 | J37: =I37 -> 0.382 | K37: =J37 -> 0.382 | M37: JP Morgan estimates through 2021; straight-line margin thereafter
C38: R&D % of sales | D38: =-D20/D17 -> 0.046582483 | E38: =-E20/E17 -> 0.050520429 | F38: =-F20/F17 -> 0.053600407 | G38: 0.062 | H38: 0.063 | I38: 0.063 | J38: =I38 -> 0.063 | K38: =J38 -> 0.063 | M38: JP Morgan estimates through 2021: straight-line margin thereafter
C39: SG&A % of sales | D39: =-D21/D17 -> 0.065822973 | E39: =-E21/E17 -> 0.066573894 | F39: =-F21/F17 -> 0.062896515 | G39: 0.074 | H39: 0.069 | I39: 0.069 | J39: =I39 -> 0.069 | K39: =J39 -> 0.069 | M39: JP Morgan estimates through 2021: straight-line margin thereafter
C40: Tax rate | D40: =-(D27/D26) -> 0.25557257 | E40: =-(E27/E26) -> 0.24556476 | F40: =-(F27/F26) -> 0.18342181 | G40: 0.167 | H40: 0.17 | I40: 0.169 | J40: =I40 -> 0.169 | K40: =J40 -> 0.169 | M40: JP Morgan estimates through 2021: straight-line margin thereafter
C42: BALANCE SHEET
C43: =C14 -> Fiscal year | E43: =E14 -> 2017 | F43: =F14 -> 2018 | G43: =G14 -> 2019 | H43: =H14 -> 2020 | I43: =I14 -> 2021 | J43: =J14 -> 2022 | K43: =K14 -> 2023
C44: =C15 -> Fiscal year end date | E44: =E15 -> 43008 | F44: =F15 -> 43372 | G44: =G15 -> 43738 | H44: =H15 -> 44104 | I44: =I15 -> 44469 | J44: =J15 -> 44834 | K44: =K15 -> 45199
B45: x | C45: Cash & equivalents, ST and LT marketable securities | E45: =20289+53892+194714 -> 268895 | F45: =25913+40388+170799 -> 237100 | G45: =G90+F45 -> 202199.73 | H45: =H90+G45 -> 176523.72 | I45: =I90+H45 -> 156076.93 | J45: =J90+I45 -> 140273.78 | K45: =K90+J45 -> 129472.46 | M45: Reference from 'net change in cash' line on the cash flow statement
B46: x | C46: Accounts receivable | E46: 17874 | F46: 23186 | G46: =F46*(1+G36) -> 22258.56 | H46: =G46*(1+H36) -> 23594.074 | I46: =H46*(1+I36) -> 25222.065 | J46: =I46*(1+J36) -> 26962.387 | K46: =J46*(1+K36) -> 28822.792 | M46: Grow in-line with revenue growth
B47: x | C47: Inventories | E47: 4855 | F47: 3956 | G47: =F47*G18/F18 -> 3831.2507 | H47: =G47*H18/G18 -> 4041.5383 | I47: =H47*I18/H18 -> 4313.4248 | J47: =I47*J18/I18 -> 4611.0512 | K47: =J47*K18/J18 -> 4929.2137 | M47: Grow in-line with cost of sales growth
B48: x | C48: Other current assets | E48: =17799+13936 -> 31735 | F48: =25809+12087 -> 37896 | G48: =F48*(1+G36) -> 36380.16 | H48: =G48*(1+H36) -> 38562.97 | I48: =H48*(1+I36) -> 41223.815 | J48: =I48*(1+J36) -> 44068.258 | K48: =J48*(1+K36) -> 47108.967 | M48: Grow in-line with revenue growth
B49: x | C49: Property, plant & equipment | E49: 33783 | F49: 41304 | G49: =G99 -> 45042.86 | H49: =H99 -> 48611.182 | I49: =I99 -> 51947.568 | J49: =J99 -> 55218.714 | K49: =K99 -> 58399.733 | M49: Reference from PP&E schedule
B50: x | C50: Other non current assets | E50: 18177 | F50: 22283 | G50: =F50*(1+G36) -> 21391.68 | H50: =G50*(1+H36) -> 22675.181 | I50: =H50*(1+I36) -> 24239.768 | J50: =I50*(1+J36) -> 25912.312 | K50: =J50*(1+K36) -> 27700.262 | M50: Grow in-line with revenue growth
C51: Total assets | E51: =SUM(E45:E50) -> 375319 | F51: =SUM(F45:F50) -> 365725 | G51: =SUM(G45:G50) -> 331104.24 | H51: =SUM(H45:H50) -> 314008.67 | I51: =SUM(I45:I50) -> 303023.57 | J51: =SUM(J45:J50) -> 297046.5 | K51: =SUM(K45:K50) -> 296433.42
B53: x | C53: Accounts payable | E53: 44242 | F53: 55888 | G53: =F53*G18/F18 -> 54125.617 | H53: =G53*H18/G18 -> 57096.435 | I53: =H53*I18/H18 -> 60937.484 | J53: =I53*J18/I18 -> 65142.171 | K53: =J53*K18/J18 -> 69636.98 | M53: Grow in-line with cost of sales growth
B54: x | C54: Other current liabilities | E54: 30551 | F54: 32687 | G54: =F54*(1+G36) -> 31379.52 | H54: =G54*(1+H36) -> 33262.291 | I54: =H54*(1+I36) -> 35557.389 | J54: =I54*(1+J36) -> 38010.849 | K54: =J54*(1+K36) -> 40633.598 | M54: Grow in-line with revenue growth
B55: x | C55: Deferred revenue (current and non current) | E55: =7548+2836 -> 10384 | F55: =7543+2797 -> 10340 | G55: =F55*(1+G36) -> 9926.4 | H55: =G55*(1+H36) -> 10521.984 | I55: =H55*(1+I36) -> 11248.001 | J55: =I55*(1+J36) -> 12024.113 | K55: =J55*(1+K36) -> 12853.777 | M55: Grow in-line with revenue growth
B56: x | C56: Commercial paper / revolver | E56: 11977 | F56: 11964 | G56: =G135 -> 12000 | H56: =H135 -> 12000 | I56: =I135 -> 12000 | J56: =J135 -> 12000 | K56: =K135 -> 12000 | M56: Reference EOP balance from CP/revolver schedule
B57: x | C57: Long term debt (includes current portion) | E57: =6496+97207 -> 103703 | F57: =8784+93735 -> 102519 | G57: =F57 -> 102519 | H57: =G57 -> 102519 | I57: =H57 -> 102519 | J57: =I57 -> 102519 | K57: =J57 -> 102519 | M57: WSP assumption: straight-line
B58: x | C58: Other non current liabilities | E58: 40415 | F58: 45180 | G58: =F58*(1+G36) -> 43372.8 | H58: =G58*(1+H36) -> 45975.168 | I58: =H58*(1+I36) -> 49147.455 | J58: =I58*(1+J36) -> 52538.629 | K58: =J58*(1+K36) -> 56163.794 | M58: Grow in-line with revenue growth
C59: Total liabilities | E59: =SUM(E53:E58) -> 241272 | F59: =SUM(F53:F58) -> 258578 | G59: =SUM(G53:G58) -> 253323.34 | H59: =SUM(H53:H58) -> 261374.88 | I59: =SUM(I53:I58) -> 271409.33 | J59: =SUM(J53:J58) -> 282234.76 | K59: =SUM(K53:K58) -> 293807.15
B61: x | C61: Common stock | E61: 35867 | F61: 40201 | G61: =F61+G32 -> 45327.4 | H61: =G61+H32 -> 50761.384 | I61: =H61+I32 -> 56570.313 | J61: =I61+J32 -> 62780.058 | K61: =J61+K32 -> 69418.275 | M61: Increase by stock-based compensation forecasted in the I/S section
B62: x | C62: Retained earnings | E62: =98330 -> 98330 | F62: 70400 | G62: =G119 -> 35907.506 | H62: =H119 -> 5326.4074 | I62: =I119 -> -21502.072 | J62: =J119 -> -44514.32 | K62: =K119 -> -63338.001 | M62: Reference from Retained Earnings schedule
B63: x | C63: Other comprehensive income | E63: -150 | F63: -3454 | G63: =F63 -> -3454 | H63: =G63 -> -3454 | I63: =H63 -> -3454 | J63: =I63 -> -3454 | K63: =J63 -> -3454 | M63: WSP assumption: straight-line
C64: Total equity | E64: =SUM(E61:E63) -> 134047 | F64: =SUM(F61:F63) -> 107147 | G64: =SUM(G61:G63) -> 77780.906 | H64: =SUM(H61:H63) -> 52633.791 | I64: =SUM(I61:I63) -> 31614.241 | J64: =SUM(J61:J63) -> 14811.738 | K64: =SUM(K61:K63) -> 2626.2747
C66: Balance check | E66: =ROUND(E51-E59-E64,3) -> 0 | F66: =ROUND(F51-F59-F64,3) -> 0 | G66: =ROUND(G51-G59-G64,3) -> 0 | H66: =ROUND(H51-H59-H64,3) -> 0 | I66: =ROUND(I51-I59-I64,3) -> 0 | J66: =ROUND(J51-J59-J64,3) -> 0 | K66: =ROUND(K51-K59-K64,3) -> 0
C68: CASH FLOW STATEMENT
C69: =C14 -> Fiscal year | G69: =G14 -> 2019 | H69: =H14 -> 2020 | I69: =I14 -> 2021 | J69: =J14 -> 2022 | K69: =K14 -> 2023
C70: =C15 -> Fiscal year end date | G70: =G15 -> 43738 | H70: =H15 -> 44104 | I70: =I15 -> 44469 | J70: =J15 -> 44834 | K70: =K15 -> 45199
B72: x | C72: Net income | G72: =G28 -> 52298.506 | H72: =H28 -> 56209.901 | I72: =I28 -> 59962.52 | J72: =J28 -> 63778.753 | K72: =K28 -> 67967.319
B73: x | C73: Depreciation and amortization | G73: =G30 -> 11085.02 | H73: =H30 -> 11711.891 | I73: =I30 -> 12226.381 | J73: =J30 -> 13365.451 | K73: =K30 -> 14603.503 | M73: Reference from the I/S
B74: x | C74: Stock based compensation | G74: =G32 -> 5126.4 | H74: =H32 -> 5433.984 | I74: =I32 -> 5808.9289 | J74: =J32 -> 6209.745 | K74: =K32 -> 6638.2174
B75: x | C75: Decreases / (Increases) in working capital assets | G75: =SUM(F46:F48)-SUM(G46:G48) -> 2568.0293 | H75: =SUM(G46:G48)-SUM(H46:H48) -> -3728.6108 | I75: =SUM(H46:H48)-SUM(I46:I48) -> -4560.7225 | J75: =SUM(I46:I48)-SUM(J46:J48) -> -4882.392 | K75: =SUM(J46:J48)-SUM(K46:K48) -> -5219.277
B76: x | C76: Increases / (Decreases) in working capital liabilities | G76: =SUM(G53:G55)-SUM(F53:F55) -> -3483.4631 | H76: =SUM(H53:H55)-SUM(G53:G55) -> 5449.1728 | I76: =SUM(I53:I55)-SUM(H53:H55) -> 6862.1646 | J76: =SUM(J53:J55)-SUM(I53:I55) -> 7434.2583 | K76: =SUM(K53:K55)-SUM(J53:J55) -> 7947.2222
B77: x | C77: Other non current assets | G77: =-G111 -> -647.56 | H77: =-H111 -> -2914.7136 | I77: =-I111 -> -3308.354 | J77: =-J111 -> -3536.6304 | K77: =-K111 -> -3780.6579 | M77: Reference from schedule NOT the B/S: Only include 'Additions' (as outflow)
B78: x | C78: Other non current liabilities | G78: =G58-F58 -> -1807.2 | H78: =H58-G58 -> 2602.368 | I78: =I58-H58 -> 3172.2866 | J78: =J58-I58 -> 3391.1744 | K78: =K58-J58 -> 3625.1654
C79: Cash from operating activities | G79: =SUM(G72:G78) -> 65139.732 | H79: =SUM(H72:H78) -> 74763.992 | I79: =SUM(I72:I78) -> 80163.205 | J79: =SUM(J72:J78) -> 85760.359 | K79: =SUM(K72:K78) -> 91781.493
B81: x | C81: Capital expenditures | G81: =-(G97) -> -13285 | H81: =-(H97) -> -13649 | I81: =-(I97) -> -13819 | J81: =-(J97) -> -14772.511 | K81: =-(K97) -> -15791.814 | M81: Reference from PP&E schedule
C82: Cash from investing activities | G82: =IFERROR(G81,"NA") -> -13285 | H82: =IFERROR(H81,"NA") -> -13649 | I82: =IFERROR(I81,"NA") -> -13819 | J82: =IFERROR(J81,"NA") -> -14772.511 | K82: =IFERROR(K81,"NA") -> -15791.814
B84: x | C84: Long term debt | G84: =G57-F57 -> 0 | H84: =H57-G57 -> 0 | I84: =I57-H57 -> 0 | J84: =J57-I57 -> 0 | K84: =K57-J57 -> 0
B85: x | C85: Commercial paper/ Revolver | G85: =G56-F56 -> 36 | H85: =H56-G56 -> 0 | I85: =I56-H56 -> 0 | J85: =J56-I56 -> 0 | K85: =K56-J56 -> 0 | M85: Reference from B/S
B86: x | C86: Share repurchases | G86: =G118 -> -73056 | H86: =H118 -> -73056 | I86: =I118 -> -73056 | J86: =J118 -> -73056 | K86: =K118 -> -73056 | M86: Reference from Retained Earnings schedule
B87: x | C87: Common dividends | G87: =G117 -> -13735 | H87: =H117 -> -13735 | I87: =I117 -> -13735 | J87: =J117 -> -13735 | K87: =K117 -> -13735 | M87: Reference from Retained Earnings schedule
C88: Cash from financing activities | G88: =SUM(G84:G87) -> -86755 | H88: =SUM(H84:H87) -> -86791 | I88: =SUM(I84:I87) -> -86791 | J88: =SUM(J84:J87) -> -86791 | K88: =SUM(K84:K87) -> -86791
C90: Net change in cash during period | G90: =G79+G82+G88 -> -34900.268 | H90: =H79+H82+H88 -> -25676.008 | I90: =I79+I82+I88 -> -20446.795 | J90: =J79+J82+J88 -> -15803.152 | K90: =K79+K82+K88 -> -10801.322
C92: PROPERTY, PLANT & EQUIPMENT
C93: =C14 -> Fiscal year | D93: =D14 -> 2016 | E93: =E14 -> 2017 | F93: =F14 -> 2018 | G93: =G14 -> 2019 | H93: =H14 -> 2020 | I93: =I14 -> 2021 | J93: =J14 -> 2022 | K93: =K14 -> 2023
C94: =C15 -> Fiscal year end date | D94: =D15 -> 42643 | E94: =E15 -> 43008 | F94: =F15 -> 43372 | G94: =G15 -> 43738 | H94: =H15 -> 44104 | I94: =I15 -> 44469 | J94: =J15 -> 44834 | K94: =K15 -> 45199
G95: Forecast
C96: Beginning of period | G96: =F99 -> 41304 | H96: =G99 -> 45042.86 | I96: =H99 -> 48611.182 | J96: =I99 -> 51947.568 | K96: =J99 -> 55218.714 | M96: BOP = Previous year EOP
C97: Plus: Capital expenditures | D97: 12734 | E97: 12451 | F97: 13313 | G97: 13285 | H97: 13649 | I97: 13819 | J97: =I97*(1+J36) -> 14772.511 | K97: =J97*(1+K36) -> 15791.814 | M97: JP Morgan through 2021; WSP assumption thereafter
C98: Less: Depreciation | D98: -8300 | E98: -8200 | F98: -9300 | G98: =-(G101*G97) -> -9546.1402 | H98: =-(H101*H97) -> -10080.678 | I98: =-(I101*I97) -> -10482.614 | J98: =-(J101*J97) -> -11501.365 | K98: =-(K101*K97) -> -12610.795 | M98: Capex x 'D&A related to PP&E as a % of capex' ratio (below)
C99: End of period | E99: =E49 -> 33783 | F99: =F49 -> 41304 | G99: =SUM(G96:G98) -> 45042.86 | H99: =SUM(H96:H98) -> 48611.182 | I99: =SUM(I96:I98) -> 51947.568 | J99: =SUM(J96:J98) -> 55218.714 | K99: =SUM(K96:K98) -> 58399.733 | M99: BOP + Capex - Depreciation
M100: Step
C101: D&A related to PP&E as a % of capex | D101: =-(D98/D97) -> 0.65179834 | E101: =-(E98/E97) -> 0.65858164 | F101: =-(F98/F97) -> 0.69856531 | G101: =F101+$M$101 -> 0.71856531 | H101: =G101+$M$101 -> 0.73856531 | I101: =H101+$M$101 -> 0.75856531 | J101: =I101+$M$101 -> 0.77856531 | K101: =J101+$M$101 -> 0.79856531 | M101: 0.02
C103: IMPUTING TOTAL DEPRECIATION & AMORTIZATION
C104: D&A not related to PP&E | D104: =D106+D98 -> 2205 | E104: =E106+E98 -> 1957 | F104: =F106+F98 -> 1603 | G104: =G105*G17 -> 1538.88 | H104: =H105*H17 -> 1631.2128 | I104: =I105*I17 -> 1743.7665 | J104: =J105*J17 -> 1864.0864 | K104: =K105*K17 -> 1992.7083 | M104: Revenue x 'as % of revenue' assumption
C105: as % of revenue | D105: =D104/D17 -> 0.010225423 | E105: =E104/E17 -> 0.008537128 | F105: =F104/F17 -> 0.0060355052 | G105: =F105 -> 0.0060355052 | H105: =G105 -> 0.0060355052 | I105: =H105 -> 0.0060355052 | J105: =I105 -> 0.0060355052 | K105: =J105 -> 0.0060355052 | M105: Straight line last historical % of revenue - WSP assumption
C106: Depreciation & Amortization - Total | D106: =D30 -> 10505 | E106: =E30 -> 10157 | F106: =F30 -> 10903 | G106: =-G98+G104 -> 11085.02 | H106: =-H98+H104 -> 11711.891 | I106: =-I98+I104 -> 12226.381 | J106: =-J98+J104 -> 13365.451 | K106: =-K98+K104 -> 14603.503 | M106: D&A from PP&E + D&A not from PP&E
C108: OTHER NON-CURRENT ASSETS
C109: Beginning of period | G109: =F112 -> 22283 | H109: =G112 -> 21391.68 | I109: =H112 -> 22675.181 | J109: =I112 -> 24239.768 | K109: =J112 -> 25912.312 | M109: BOP = Previous year EOP
C110: Less: Amortization of intangible assets | G110: =-(G104) -> -1538.88 | H110: =-(H104) -> -1631.2128 | I110: =-(I104) -> -1743.7665 | J110: =-(J104) -> -1864.0864 | K110: =-(K104) -> -1992.7083 | M110: Assume all D&A not from PP&E is in non-current assets
C111: Plus: Additions | G111: =G112-G110-G109 -> 647.56 | H111: =H112-H110-H109 -> 2914.7136 | I111: =I112-I110-I109 -> 3308.354 | J111: =J112-J110-J109 -> 3536.6304 | K111: =K112-K110-K109 -> 3780.6579 | M111: Because we already know the EOP balance, this is a plug: EOP - D&A not from PP&E - BOP
C112: End of period | E112: =E50 -> 18177 | F112: =F50 -> 22283 | G112: =G50 -> 21391.68 | H112: =H50 -> 22675.181 | I112: =I50 -> 24239.768 | J112: =J50 -> 25912.312 | K112: =K50 -> 27700.262 | M112: Referenced from balance sheet
C114: RETAINED EARNINGS
C115: Beginning of period | G115: =F119 -> 70400 | H115: =G119 -> 35907.506 | I115: =H119 -> 5326.4074 | J115: =I119 -> -21502.072 | K115: =J119 -> -44514.32 | M115: BOP = Previous year EOP
C116: Plus: Net income | D116: =D28 -> 45687 | E116: =E28 -> 48351 | F116: =F28 -> 59531 | G116: =G28 -> 52298.506 | H116: =H28 -> 56209.901 | I116: =I28 -> 59962.52 | J116: =J28 -> 63778.753 | K116: =K28 -> 67967.319 | M116: Reference from income statement
C117: Less: Dividends | D117: -12188 | E117: -12803 | F117: -13735 | G117: =F117 -> -13735 | H117: =G117 -> -13735 | I117: =H117 -> -13735 | J117: =I117 -> -13735 | K117: =J117 -> -13735 | M117: WSP assumption: Straight-line last historical year dividends
C118: Less: Repurchases | D118: -29000 | E118: -33001 | F118: -73056 | G118: =F118 -> -73056 | H118: =G118 -> -73056 | I118: =H118 -> -73056 | J118: =I118 -> -73056 | K118: =J118 -> -73056 | M118: WSP assumption: Straight-line last historical year repurchases
C119: End of period | D119: =D62 -> 0 | E119: =E62 -> 98330 | F119: =F62 -> 70400 | G119: =SUM(G115:G118) -> 35907.506 | H119: =SUM(H115:H118) -> 5326.4074 | I119: =SUM(I115:I118) -> -21502.072 | J119: =SUM(J115:J118) -> -44514.32 | K119: =SUM(K115:K118) -> -63338.001 | M119: BOP + net income - dividends - repurchases
...

Sheet Extras
C2: ="Financial Statement Model for "&D5 -> Financial Statement Model for Apple
C3: $ in thousands except per share
C5: Company name | D5: Apple
C6: Ticker | D6: AAPL
C7: Circ break 1=off, 0=on | D7: 1
C8: Latest closing share price | D8: 171.25
C9: Latest closing share price date | D9: 43500
C10: Latest fiscal year end date | D10: 43372
C11: Shares outstanding (millions) | D11: 4745.398
C12: Select an operating scenario: | D12: Base case
C14: INCOME STATEMENT
C15: Fiscal year | D15: =E15-1 -> 2016 | E15: =F15-1 -> 2017 | F15: =YEAR(D10) -> 2018 | G15: =F15+1 -> 2019 | H15: =G15+1 -> 2020 | I15: =H15+1 -> 2021 | J15: =I15+1 -> 2022 | K15: =J15+1 -> 2023
C16: Fiscal year end date | D16: =EOMONTH(E16,-12) -> 42643 | E16: =EOMONTH(F16,-12) -> 43008 | F16: =D10 -> 43372 | G16: =EOMONTH(F16,12) -> 43738 | H16: =EOMONTH(G16,12) -> 44104 | I16: =EOMONTH(H16,12) -> 44469 | J16: =EOMONTH(I16,12) -> 44834 | K16: =EOMONTH(J16,12) -> 45199 | M16: WSP Comments
C18: Revenue | D18: 215639 | E18: 229234 | F18: 265595 | G18: =F18*(1+G37) -> 254971.2 | H18: =G18*(1+H37) -> 270269.47 | I18: =H18*(1+I37) -> 288918.07 | J18: =I18*(1+J37) -> 308853.41 | K18: =J18*(1+K37) -> 330164.3 | M18: Previous year's revenues x (1+revenue growth rate)
C19: Cost of sales (enter as -) | D19: -131376 | E19: -141048 | F19: -163756 | G19: =G20-G18 -> -158592.09 | H19: =H20-H18 -> -167296.8 | I19: =I20-I18 -> -178551.36 | J19: =J20-J18 -> -190871.41 | K19: =K20-K18 -> -204041.54 | M19: Plug = Revenue - Gross Profit
C20: Gross Profit | D20: =SUM(D18:D19) -> 84263 | E20: =SUM(E18:E19) -> 88186 | F20: =SUM(F18:F19) -> 101839 | G20: =G18*G38 -> 96379.114 | H20: =H18*H38 -> 102972.67 | I20: =I18*I38 -> 110366.7 | J20: =J18*J38 -> 117982 | K20: =K18*K38 -> 126122.76 | M20: Revenue x Gross Profit Margin forecast
C21: Research & development (enter as -) | D21: -10045 | E21: -11581 | F21: -14236 | G21: =-G39*G18 -> -15808.214 | H21: =-H39*H18 -> -17026.977 | I21: =-I39*I18 -> -18201.838 | J21: =-J39*J18 -> -19457.765 | K21: =-K39*K18 -> -20800.351 | M21: Revenue x R&D % of sales forecast
C22: Selling, general & administrative (enter as -) | D22: -14194 | E22: -15261 | F22: -16705 | G22: =-G18*G40 -> -18867.869 | H22: =-H18*H40 -> -18648.594 | I22: =-I18*I40 -> -19935.347 | J22: =-J18*J40 -> -21310.885 | K22: =-K18*K40 -> -22781.337 | M22: Revenue x SG&A % of sales forecast
C23: Operating profit (EBIT) | D23: =D20+D21+D22 -> 60024 | E23: =E20+E21+E22 -> 61344 | F23: =F20+F21+F22 -> 70898 | G23: =G20+G21+G22 -> 61703.03 | H23: =H20+H21+H22 -> 67297.099 | I23: =I20+I21+I22 -> 72229.516 | J23: =J20+J21+J22 -> 77213.353 | K23: =K20+K21+K22 -> 82541.074 | M23: Gross Profit - R&D - SG&A
C24: Interest income | D24: 3999 | E24: 5201 | F24: 5686 | G24: =G157 -> 4744.4371 | H24: =H157 -> 4090.2133 | I24: =I157 -> 3592.0871 | J24: =J157 -> 3200.5876 | K24: =K157 -> 2913.2593 | M24: Reference from interest on cash schedule
C25: Interest expense (enter as -) | D25: -1456 | E25: -2323 | F25: -3240 | G25: =-G143 -> -3223.1469 | H25: =-H143 -> -3223.5393 | I25: =-I143 -> -3223.5393 | J25: =-J143 -> -3223.5393 | K25: =-K143 -> -3223.5393 | M25: Reference from interest expense schedule
C26: Other expense, net (enter as -) | D26: -1195 | E26: -133 | F26: -441 | G26: =F26 -> -441 | H26: =G26 -> -441 | I26: =H26 -> -441 | J26: =I26 -> -441 | K26: =J26 -> -441 | M26: Straight-line
C27: Pretax profit | D27: =SUM(D23:D26) -> 61372 | E27: =SUM(E23:E26) -> 64089 | F27: =SUM(F23:F26) -> 72903 | G27: =SUM(G23:G26) -> 62783.321 | H27: =SUM(H23:H26) -> 67722.773 | I27: =SUM(I23:I26) -> 72157.064 | J27: =SUM(J23:J26) -> 76749.401 | K27: =SUM(K23:K26) -> 81789.794 | M27: EBIT + interest income less interest expense less other expense
C28: Taxes (enter expense as -) | D28: -15685 | E28: -15738 | F28: -13372 | G28: =-G41*G27 -> -10484.815 | H28: =-H41*H27 -> -11512.871 | I28: =-I41*I27 -> -12194.544 | J28: =-J41*J27 -> -12970.649 | K28: =-K41*K27 -> -13822.475 | M28: Pre-tax Profit x Tax Rate forecast
C29: Net income | D29: =SUM(D27:D28) -> 45687 | E29: =SUM(E27:E28) -> 48351 | F29: =SUM(F27:F28) -> 59531 | G29: =SUM(G27:G28) -> 52298.506 | H29: =SUM(H27:H28) -> 56209.901 | I29: =SUM(I27:I28) -> 59962.52 | J29: =SUM(J27:J28) -> 63778.753 | K29: =SUM(K27:K28) -> 67967.319 | M29: Pre-tax Profit less taxes
C31: Depreciation & amortization | D31: 10505 | E31: 10157 | F31: 10903 | G31: =G107 -> 11085.02 | H31: =H107 -> 11711.891 | I31: =I107 -> 12226.381 | J31: =J107 -> 13365.451 | K31: =K107 -> 14603.503 | M31: Reference from D&A schedule
C32: EBITDA | D32: =D23+D31 -> 70529 | E32: =E23+E31 -> 71501 | F32: =F23+F31 -> 81801 | G32: =G23+G31 -> 72788.051 | H32: =H23+H31 -> 79008.989 | I32: =I23+I31 -> 84455.897 | J32: =J23+J31 -> 90578.804 | K32: =K23+K31 -> 97144.578 | M32: EBIT + D&A
C33: Stock based compensation | D33: 4210 | E33: 4840 | F33: 5340 | G33: =F33*(1+G37) -> 5126.4 | H33: =G33*(1+H37) -> 5433.984 | I33: =H33*(1+I37) -> 5808.9289 | J33: =I33*(1+J37) -> 6209.745 | K33: =J33*(1+K37) -> 6638.2174 | M33: WSP assumption: grow SBC in-line with revenue growth
C34: Adjusted EBITDA | D34: =SUM(D32:D33) -> 74739 | E34: =SUM(E32:E33) -> 76341 | F34: =SUM(F32:F33) -> 87141 | G34: =SUM(G32:G33) -> 77914.451 | H34: =SUM(H32:H33) -> 84442.973 | I34: =SUM(I32:I33) -> 90264.826 | J34: =SUM(J32:J33) -> 96788.549 | K34: =SUM(K32:K33) -> 103782.8 | M34: EBITDA + Stock-based compensation
C36: Growth rates & margins
C37: Revenue growth | E37: =E18/D18-1 -> 0.063045182 | F37: =F18/E18-1 -> 0.15861958 | G37: -0.04 | H37: 0.06 | I37: 0.069 | J37: =I37 -> 0.069 | K37: =J37 -> 0.069 | M37: From scenario analysis below
C38: Gross profit margin | D38: =D20/D18 -> 0.39075956 | E38: =E20/E18 -> 0.3846986 | F38: =F20/F18 -> 0.38343719 | G38: 0.378 | H38: 0.381 | I38: 0.382 | J38: =I38 -> 0.382 | K38: =J38 -> 0.382 | M38: From scenario analysis below
C39: R&D % of sales | D39: =-D21/D18 -> 0.046582483 | E39: =-E21/E18 -> 0.050520429 | F39: =-F21/F18 -> 0.053600407 | G39: 0.062 | H39: 0.063 | I39: 0.063 | J39: =I39 -> 0.063 | K39: =J39 -> 0.063 | M39: From scenario analysis below
C40: SG&A % of sales | D40: =-D22/D18 -> 0.065822973 | E40: =-E22/E18 -> 0.066573894 | F40: =-F22/F18 -> 0.062896515 | G40: 0.074 | H40: 0.069 | I40: 0.069 | J40: =I40 -> 0.069 | K40: =J40 -> 0.069 | M40: From scenario analysis below
C41: Tax rate | D41: =-(D28/D27) -> 0.25557257 | E41: =-(E28/E27) -> 0.24556476 | F41: =-(F28/F27) -> 0.18342181 | G41: 0.167 | H41: 0.17 | I41: 0.169 | J41: =I41 -> 0.169 | K41: =J41 -> 0.169 | M41: JP Morgan estimates through 2021: straight-line margin thereafter
C43: BALANCE SHEET
C44: =C15 -> Fiscal year | E44: =E15 -> 2017 | F44: =F15 -> 2018 | G44: =G15 -> 2019 | H44: =H15 -> 2020 | I44: =I15 -> 2021 | J44: =J15 -> 2022 | K44: =K15 -> 2023
C45: =C16 -> Fiscal year end date | E45: =E16 -> 43008 | F45: =F16 -> 43372 | G45: =G16 -> 43738 | H45: =H16 -> 44104 | I45: =I16 -> 44469 | J45: =J16 -> 44834 | K45: =K16 -> 45199
C46: Cash & equivalents, ST and LT marketable securities | E46: =20289+53892+194714 -> 268895 | F46: =25913+40388+170799 -> 237100 | G46: =G91+F46 -> 202199.73 | H46: =H91+G46 -> 176523.72 | I46: =I91+H46 -> 156076.93 | J46: =J91+I46 -> 140273.78 | K46: =K91+J46 -> 129472.46 | M46: Reference from 'net change in cash' line on the cash flow statement
C47: Accounts receivable | E47: 17874 | F47: 23186 | G47: =F47*(1+G37) -> 22258.56 | H47: =G47*(1+H37) -> 23594.074 | I47: =H47*(1+I37) -> 25222.065 | J47: =I47*(1+J37) -> 26962.387 | K47: =J47*(1+K37) -> 28822.792 | M47: Grow in-line with revenue growth
C48: Inventories | E48: 4855 | F48: 3956 | G48: =F48*G19/F19 -> 3831.2507 | H48: =G48*H19/G19 -> 4041.5383 | I48: =H48*I19/H19 -> 4313.4248 | J48: =I48*J19/I19 -> 4611.0512 | K48: =J48*K19/J19 -> 4929.2137 | M48: Grow in-line with cost of sales growth
C49: Other current assets | E49: =17799+13936 -> 31735 | F49: =25809+12087 -> 37896 | G49: =F49*(1+G37) -> 36380.16 | H49: =G49*(1+H37) -> 38562.97 | I49: =H49*(1+I37) -> 41223.815 | J49: =I49*(1+J37) -> 44068.258 | K49: =J49*(1+K37) -> 47108.967 | M49: Grow in-line with revenue growth
C50: Property, plant & equipment | E50: 33783 | F50: 41304 | G50: =G100 -> 45042.86 | H50: =H100 -> 48611.182 | I50: =I100 -> 51947.568 | J50: =J100 -> 55218.714 | K50: =K100 -> 58399.733 | M50: Reference from PP&E schedule
C51: Other non current assets | E51: 18177 | F51: 22283 | G51: =F51*(1+G37) -> 21391.68 | H51: =G51*(1+H37) -> 22675.181 | I51: =H51*(1+I37) -> 24239.768 | J51: =I51*(1+J37) -> 25912.312 | K51: =J51*(1+K37) -> 27700.262 | M51: Grow in-line with revenue growth
C52: Total assets | E52: =SUM(E46:E51) -> 375319 | F52: =SUM(F46:F51) -> 365725 | G52: =SUM(G46:G51) -> 331104.24 | H52: =SUM(H46:H51) -> 314008.67 | I52: =SUM(I46:I51) -> 303023.57 | J52: =SUM(J46:J51) -> 297046.5 | K52: =SUM(K46:K51) -> 296433.42
C54: Accounts payable | E54: 44242 | F54: 55888 | G54: =F54*G19/F19 -> 54125.617 | H54: =G54*H19/G19 -> 57096.435 | I54: =H54*I19/H19 -> 60937.484 | J54: =I54*J19/I19 -> 65142.171 | K54: =J54*K19/J19 -> 69636.98 | M54: Grow in-line with cost of sales growth
C55: Other current liabilities | E55: 30551 | F55: 32687 | G55: =F55*(1+G37) -> 31379.52 | H55: =G55*(1+H37) -> 33262.291 | I55: =H55*(1+I37) -> 35557.389 | J55: =I55*(1+J37) -> 38010.849 | K55: =J55*(1+K37) -> 40633.598 | M55: Grow in-line with revenue growth
C56: Deferred revenue (current and non current) | E56: =7548+2836 -> 10384 | F56: =7543+2797 -> 10340 | G56: =F56*(1+G37) -> 9926.4 | H56: =G56*(1+H37) -> 10521.984 | I56: =H56*(1+I37) -> 11248.001 | J56: =I56*(1+J37) -> 12024.113 | K56: =J56*(1+K37) -> 12853.777 | M56: Grow in-line with revenue growth
C57: Commercial paper / revolver | E57: 11977 | F57: 11964 | G57: =G136 -> 12000 | H57: =H136 -> 12000 | I57: =I136 -> 12000 | J57: =J136 -> 12000 | K57: =K136 -> 12000 | M57: Reference EOP balance from CP/revolver schedule
C58: Long term debt (includes current portion) | E58: =6496+97207 -> 103703 | F58: =8784+93735 -> 102519 | G58: =F58 -> 102519 | H58: =G58 -> 102519 | I58: =H58 -> 102519 | J58: =I58 -> 102519 | K58: =J58 -> 102519 | M58: WSP assumption: straight-line
C59: Other non current liabilities | E59: 40415 | F59: 45180 | G59: =F59*(1+G37) -> 43372.8 | H59: =G59*(1+H37) -> 45975.168 | I59: =H59*(1+I37) -> 49147.455 | J59: =I59*(1+J37) -> 52538.629 | K59: =J59*(1+K37) -> 56163.794 | M59: Grow in-line with revenue growth
C60: Total liabilities | E60: =SUM(E54:E59) -> 241272 | F60: =SUM(F54:F59) -> 258578 | G60: =SUM(G54:G59) -> 253323.34 | H60: =SUM(H54:H59) -> 261374.88 | I60: =SUM(I54:I59) -> 271409.33 | J60: =SUM(J54:J59) -> 282234.76 | K60: =SUM(K54:K59) -> 293807.15
C62: Common stock | E62: 35867 | F62: 40201 | G62: =F62+G33 -> 45327.4 | H62: =G62+H33 -> 50761.384 | I62: =H62+I33 -> 56570.313 | J62: =I62+J33 -> 62780.058 | K62: =J62+K33 -> 69418.275 | M62: Increase by stock-based compensation forecasted in the I/S section
C63: Retained earnings | E63: =98330 -> 98330 | F63: 70400 | G63: =G120 -> 35907.506 | H63: =H120 -> 5326.4074 | I63: =I120 -> -21502.072 | J63: =J120 -> -44514.32 | K63: =K120 -> -63338.001 | M63: Reference from Retained Earnings schedule
C64: Other comprehensive income | E64: -150 | F64: -3454 | G64: =F64 -> -3454 | H64: =G64 -> -3454 | I64: =H64 -> -3454 | J64: =I64 -> -3454 | K64: =J64 -> -3454 | M64: WSP assumption: straight-line
C65: Total equity | E65: =SUM(E62:E64) -> 134047 | F65: =SUM(F62:F64) -> 107147 | G65: =SUM(G62:G64) -> 77780.906 | H65: =SUM(H62:H64) -> 52633.791 | I65: =SUM(I62:I64) -> 31614.241 | J65: =SUM(J62:J64) -> 14811.738 | K65: =SUM(K62:K64) -> 2626.2747
C67: Balance check | E67: =ROUND(E52-E60-E65,3) -> 0 | F67: =ROUND(F52-F60-F65,3) -> 0 | G67: =ROUND(G52-G60-G65,3) -> 0 | H67: =ROUND(H52-H60-H65,3) -> 0 | I67: =ROUND(I52-I60-I65,3) -> 0 | J67: =ROUND(J52-J60-J65,3) -> 0 | K67: =ROUND(K52-K60-K65,3) -> 0
C69: CASH FLOW STATEMENT
C70: =C15 -> Fiscal year | G70: =G15 -> 2019 | H70: =H15 -> 2020 | I70: =I15 -> 2021 | J70: =J15 -> 2022 | K70: =K15 -> 2023
C71: =C16 -> Fiscal year end date | G71: =G16 -> 43738 | H71: =H16 -> 44104 | I71: =I16 -> 44469 | J71: =J16 -> 44834 | K71: =K16 -> 45199
C73: Net income | G73: =G29 -> 52298.506 | H73: =H29 -> 56209.901 | I73: =I29 -> 59962.52 | J73: =J29 -> 63778.753 | K73: =K29 -> 67967.319
C74: Depreciation and amortization | G74: =G31 -> 11085.02 | H74: =H31 -> 11711.891 | I74: =I31 -> 12226.381 | J74: =J31 -> 13365.451 | K74: =K31 -> 14603.503 | M74: Reference from the I/S
C75: Stock based compensation | G75: =G33 -> 5126.4 | H75: =H33 -> 5433.984 | I75: =I33 -> 5808.9289 | J75: =J33 -> 6209.745 | K75: =K33 -> 6638.2174
C76: Decreases / (Increases) in working capital assets | G76: =-1*(SUM(G47:G49)-SUM(F47:F49)) -> 2568.0293 | H76: =-1*(SUM(H47:H49)-SUM(G47:G49)) -> -3728.6108 | I76: =-1*(SUM(I47:I49)-SUM(H47:H49)) -> -4560.7225 | J76: =-1*(SUM(J47:J49)-SUM(I47:I49)) -> -4882.392 | K76: =-1*(SUM(K47:K49)-SUM(J47:J49)) -> -5219.277
C77: Increases / (Decreases) in working capital liabilities | G77: =SUM(G54:G56)-SUM(F54:F56) -> -3483.4631 | H77: =SUM(H54:H56)-SUM(G54:G56) -> 5449.1728 | I77: =SUM(I54:I56)-SUM(H54:H56) -> 6862.1646 | J77: =SUM(J54:J56)-SUM(I54:I56) -> 7434.2583 | K77: =SUM(K54:K56)-SUM(J54:J56) -> 7947.2222
C78: Other non current assets | G78: =-(G112) -> -647.56 | H78: =-(H112) -> -2914.7136 | I78: =-(I112) -> -3308.354 | J78: =-(J112) -> -3536.6304 | K78: =-(K112) -> -3780.6579 | M78: Reference from schedule NOT the B/S: Only include 'Additions' (as outflow)
C79: Other non current liabilities | G79: =G59-F59 -> -1807.2 | H79: =H59-G59 -> 2602.368 | I79: =I59-H59 -> 3172.2866 | J79: =J59-I59 -> 3391.1744 | K79: =K59-J59 -> 3625.1654
C80: Cash from operating activities | G80: =SUM(G73:G79) -> 65139.732 | H80: =SUM(H73:H79) -> 74763.992 | I80: =SUM(I73:I79) -> 80163.205 | J80: =SUM(J73:J79) -> 85760.359 | K80: =SUM(K73:K79) -> 91781.493
C82: Capital expenditures | G82: =-(G98) -> -13285 | H82: =-(H98) -> -13649 | I82: =-(I98) -> -13819 | J82: =-(J98) -> -14772.511 | K82: =-(K98) -> -15791.814 | M82: Reference from PP&E schedule
C83: Cash from investing activities | G83: =IFERROR(G82,"NA") -> -13285 | H83: =IFERROR(H82,"NA") -> -13649 | I83: =IFERROR(I82,"NA") -> -13819 | J83: =IFERROR(J82,"NA") -> -14772.511 | K83: =IFERROR(K82,"NA") -> -15791.814
C85: Long term debt | G85: =G58-F58 -> 0 | H85: =H58-G58 -> 0 | I85: =I58-H58 -> 0 | J85: =J58-I58 -> 0 | K85: =K58-J58 -> 0
C86: Revolver | G86: =G57-F57 -> 36 | H86: =H57-G57 -> 0 | I86: =I57-H57 -> 0 | J86: =J57-I57 -> 0 | K86: =K57-J57 -> 0 | M86: Reference from B/S
C87: Share repurchases | G87: =G119 -> -73056 | H87: =H119 -> -73056 | I87: =I119 -> -73056 | J87: =J119 -> -73056 | K87: =K119 -> -73056 | M87: Reference from Retained Earnings schedule
C88: Common dividends | G88: =G118 -> -13735 | H88: =H118 -> -13735 | I88: =I118 -> -13735 | J88: =J118 -> -13735 | K88: =K118 -> -13735 | M88: Reference from Retained Earnings schedule
C89: Cash from financing activities | G89: =SUM(G85:G88) -> -86755 | H89: =SUM(H85:H88) -> -86791 | I89: =SUM(I85:I88) -> -86791 | J89: =SUM(J85:J88) -> -86791 | K89: =SUM(K85:K88) -> -86791
C91: Net change in cash during period | G91: =G80+G83+G89 -> -34900.268 | H91: =H80+H83+H89 -> -25676.008 | I91: =I80+I83+I89 -> -20446.795 | J91: =J80+J83+J89 -> -15803.152 | K91: =K80+K83+K89 -> -10801.322
C93: PROPERTY, PLANT & EQUIPMENT
C94: =C15 -> Fiscal year | D94: =D15 -> 2016 | E94: =E15 -> 2017 | F94: =F15 -> 2018 | G94: =G15 -> 2019 | H94: =H15 -> 2020 | I94: =I15 -> 2021 | J94: =J15 -> 2022 | K94: =K15 -> 2023
C95: =C16 -> Fiscal year end date | D95: =D16 -> 42643 | E95: =E16 -> 43008 | F95: =F16 -> 43372 | G95: =G16 -> 43738 | H95: =H16 -> 44104 | I95: =I16 -> 44469 | J95: =J16 -> 44834 | K95: =K16 -> 45199
G96: Forecast
C97: Beginning of period | G97: =F100 -> 41304 | H97: =G100 -> 45042.86 | I97: =H100 -> 48611.182 | J97: =I100 -> 51947.568 | K97: =J100 -> 55218.714 | M97: BOP = Previous year EOP
C98: Plus: Capital expenditures | D98: 12734 | E98: 12451 | F98: 13313 | G98: 13285 | H98: 13649 | I98: 13819 | J98: =I98*(1+J37) -> 14772.511 | K98: =J98*(1+K37) -> 15791.814 | M98: JP Morgan through 2021; WSP assumption thereafter
C99: Less: Depreciation | D99: -8300 | E99: -8200 | F99: -9300 | G99: =-(G102*G98) -> -9546.1402 | H99: =-(H102*H98) -> -10080.678 | I99: =-(I102*I98) -> -10482.614 | J99: =-(J102*J98) -> -11501.365 | K99: =-(K102*K98) -> -12610.795 | M99: Capex x 'D&A related to PP&E as a % of capex' ratio (below)
C100: End of period | E100: =E50 -> 33783 | F100: =F50 -> 41304 | G100: =SUM(G97:G99) -> 45042.86 | H100: =SUM(H97:H99) -> 48611.182 | I100: =SUM(I97:I99) -> 51947.568 | J100: =SUM(J97:J99) -> 55218.714 | K100: =SUM(K97:K99) -> 58399.733 | M100: BOP + Capex - Depreciation
M101: Step
C102: D&A related to PP&E as a % of capex | D102: =-(D99/D98) -> 0.65179834 | E102: =-(E99/E98) -> 0.65858164 | F102: =-(F99/F98) -> 0.69856531 | G102: =F102+$M$102 -> 0.71856531 | H102: =G102+$M$102 -> 0.73856531 | I102: =H102+$M$102 -> 0.75856531 | J102: =I102+$M$102 -> 0.77856531 | K102: =J102+$M$102 -> 0.79856531 | M102: 0.02
C104: IMPUTING TOTAL DEPRECIATION & AMORTIZATION
C105: D&A not related to PP&E | D105: =D107+D99 -> 2205 | E105: =E107+E99 -> 1957 | F105: =F107+F99 -> 1603 | G105: =G106*G18 -> 1538.88 | H105: =H106*H18 -> 1631.2128 | I105: =I106*I18 -> 1743.7665 | J105: =J106*J18 -> 1864.0864 | K105: =K106*K18 -> 1992.7083 | M105: Revenue x 'as % of revenue' assumption
C106: as % of revenue | D106: =D105/D18 -> 0.010225423 | E106: =E105/E18 -> 0.008537128 | F106: =F105/F18 -> 0.0060355052 | G106: =F106 -> 0.0060355052 | H106: =G106 -> 0.0060355052 | I106: =H106 -> 0.0060355052 | J106: =I106 -> 0.0060355052 | K106: =J106 -> 0.0060355052 | M106: Straight line last historical % of revenue - WSP assumption
C107: Depreciation & Amortization - Total | D107: =D31 -> 10505 | E107: =E31 -> 10157 | F107: =F31 -> 10903 | G107: =-G99+G105 -> 11085.02 | H107: =-H99+H105 -> 11711.891 | I107: =-I99+I105 -> 12226.381 | J107: =-J99+J105 -> 13365.451 | K107: =-K99+K105 -> 14603.503 | M107: D&A from PP&E + D&A not from PP&E
C109: OTHER NON-CURRENT ASSETS
C110: Beginning of period | G110: =F113 -> 22283 | H110: =G113 -> 21391.68 | I110: =H113 -> 22675.181 | J110: =I113 -> 24239.768 | K110: =J113 -> 25912.312 | M110: BOP = Previous year EOP
C111: Less: Amortization of intangible assets | G111: =-(G105) -> -1538.88 | H111: =-(H105) -> -1631.2128 | I111: =-(I105) -> -1743.7665 | J111: =-(J105) -> -1864.0864 | K111: =-(K105) -> -1992.7083 | M111: Assume all D&A not from PP&E is in non-current assets
C112: Plus: Additions | G112: =G113-G111-G110 -> 647.56 | H112: =H113-H111-H110 -> 2914.7136 | I112: =I113-I111-I110 -> 3308.354 | J112: =J113-J111-J110 -> 3536.6304 | K112: =K113-K111-K110 -> 3780.6579 | M112: Because we already know the EOP balance, this is a plug: EOP - D&A not from PP&E - BOP
C113: End of period | E113: =E51 -> 18177 | F113: =F51 -> 22283 | G113: =G51 -> 21391.68 | H113: =H51 -> 22675.181 | I113: =I51 -> 24239.768 | J113: =J51 -> 25912.312 | K113: =K51 -> 27700.262 | M113: Referenced from balance sheet
C115: RETAINED EARNINGS
C116: Beginning of period | G116: =F120 -> 70400 | H116: =G120 -> 35907.506 | I116: =H120 -> 5326.4074 | J116: =I120 -> -21502.072 | K116: =J120 -> -44514.32 | M116: BOP = Previous year EOP
C117: Plus: Net income | D117: =D29 -> 45687 | E117: =E29 -> 48351 | F117: =F29 -> 59531 | G117: =G29 -> 52298.506 | H117: =H29 -> 56209.901 | I117: =I29 -> 59962.52 | J117: =J29 -> 63778.753 | K117: =K29 -> 67967.319 | M117: Reference from income statement
C118: Less: Dividends | D118: -12188 | E118: -12803 | F118: -13735 | G118: =F118 -> -13735 | H118: =G118 -> -13735 | I118: =H118 -> -13735 | J118: =I118 -> -13735 | K118: =J118 -> -13735 | M118: WSP assumption: Straight-line last historical year dividends
C119: Less: Repurchases | D119: -29000 | E119: -33001 | F119: -73056 | G119: =F119 -> -73056 | H119: =G119 -> -73056 | I119: =H119 -> -73056 | J119: =I119 -> -73056 | K119: =J119 -> -73056 | M119: WSP assumption: Straight-line last historical year repurchases
...

Sheet Extras Complete
C2: ="Financial Statement Model for "&D5 -> Financial Statement Model for Apple
C3: $ in thousands except per share
C5: Company name | D5: Apple
C6: Ticker | D6: AAPL
C7: Circ break 1=off, 0=on | D7: 1
C8: Latest closing share price | D8: 171.25
C9: Latest closing share price date | D9: 43500
C10: Latest fiscal year end date | D10: 43372
C11: Shares outstanding (millions) | D11: 4745.398
C12: Select an operating scenario: | D12: Base case
C14: INCOME STATEMENT
C15: Fiscal year | D15: =E15-1 -> 2016 | E15: =F15-1 -> 2017 | F15: =YEAR(D10) -> 2018 | G15: =F15+1 -> 2019 | H15: =G15+1 -> 2020 | I15: =H15+1 -> 2021 | J15: =I15+1 -> 2022 | K15: =J15+1 -> 2023
C16: Fiscal year end date | D16: =EOMONTH(E16,-12) -> 42643 | E16: =EOMONTH(F16,-12) -> 43008 | F16: =D10 -> 43372 | G16: =EOMONTH(F16,12) -> 43738 | H16: =EOMONTH(G16,12) -> 44104 | I16: =EOMONTH(H16,12) -> 44469 | J16: =EOMONTH(I16,12) -> 44834 | K16: =EOMONTH(J16,12) -> 45199 | M16: WSP Comments
C18: Revenue | D18: 215639 | E18: 229234 | F18: 265595 | G18: =F18*(1+G37) -> 254971.2 | H18: =G18*(1+H37) -> 270269.47 | I18: =H18*(1+I37) -> 288918.07 | J18: =I18*(1+J37) -> 308853.41 | K18: =J18*(1+K37) -> 330164.3 | M18: Previous year's revenues x (1+revenue growth rate)
C19: Cost of sales (enter as -) | D19: -131376 | E19: -141048 | F19: -163756 | G19: =G20-G18 -> -158592.09 | H19: =H20-H18 -> -167296.8 | I19: =I20-I18 -> -178551.36 | J19: =J20-J18 -> -190871.41 | K19: =K20-K18 -> -204041.54 | M19: Plug = Revenue - Gross Profit
C20: Gross Profit | D20: =SUM(D18:D19) -> 84263 | E20: =SUM(E18:E19) -> 88186 | F20: =SUM(F18:F19) -> 101839 | G20: =G18*G38 -> 96379.114 | H20: =H18*H38 -> 102972.67 | I20: =I18*I38 -> 110366.7 | J20: =J18*J38 -> 117982 | K20: =K18*K38 -> 126122.76 | M20: Revenue x Gross Profit Margin forecast
C21: Research & development (enter as -) | D21: -10045 | E21: -11581 | F21: -14236 | G21: =-G39*G18 -> -15808.214 | H21: =-H39*H18 -> -17026.977 | I21: =-I39*I18 -> -18201.838 | J21: =-J39*J18 -> -19457.765 | K21: =-K39*K18 -> -20800.351 | M21: Revenue x R&D % of sales forecast
C22: Selling, general & administrative (enter as -) | D22: -14194 | E22: -15261 | F22: -16705 | G22: =-G18*G40 -> -18867.869 | H22: =-H18*H40 -> -18648.594 | I22: =-I18*I40 -> -19935.347 | J22: =-J18*J40 -> -21310.885 | K22: =-K18*K40 -> -22781.337 | M22: Revenue x SG&A % of sales forecast
C23: Operating profit (EBIT) | D23: =D20+D21+D22 -> 60024 | E23: =E20+E21+E22 -> 61344 | F23: =F20+F21+F22 -> 70898 | G23: =G20+G21+G22 -> 61703.03 | H23: =H20+H21+H22 -> 67297.099 | I23: =I20+I21+I22 -> 72229.516 | J23: =J20+J21+J22 -> 77213.353 | K23: =K20+K21+K22 -> 82541.074 | M23: Gross Profit - R&D - SG&A
C24: Interest income | D24: 3999 | E24: 5201 | F24: 5686 | G24: =G157 -> 4744.4371 | H24: =H157 -> 4090.2133 | I24: =I157 -> 3592.0871 | J24: =J157 -> 3200.5876 | K24: =K157 -> 2913.2593 | M24: Reference from interest on cash schedule
C25: Interest expense (enter as -) | D25: -1456 | E25: -2323 | F25: -3240 | G25: =-G143 -> -3223.1469 | H25: =-H143 -> -3223.5393 | I25: =-I143 -> -3223.5393 | J25: =-J143 -> -3223.5393 | K25: =-K143 -> -3223.5393 | M25: Reference from interest expense schedule
C26: Other expense, net (enter as -) | D26: -1195 | E26: -133 | F26: -441 | G26: =F26 -> -441 | H26: =G26 -> -441 | I26: =H26 -> -441 | J26: =I26 -> -441 | K26: =J26 -> -441 | M26: Straight-line
C27: Pretax profit | D27: =SUM(D23:D26) -> 61372 | E27: =SUM(E23:E26) -> 64089 | F27: =SUM(F23:F26) -> 72903 | G27: =SUM(G23:G26) -> 62783.321 | H27: =SUM(H23:H26) -> 67722.773 | I27: =SUM(I23:I26) -> 72157.064 | J27: =SUM(J23:J26) -> 76749.401 | K27: =SUM(K23:K26) -> 81789.794 | M27: EBIT + interest income less interest expense less other expense
C28: Taxes (enter expense as -) | D28: -15685 | E28: -15738 | F28: -13372 | G28: =-G41*G27 -> -10484.815 | H28: =-H41*H27 -> -11512.871 | I28: =-I41*I27 -> -12194.544 | J28: =-J41*J27 -> -12970.649 | K28: =-K41*K27 -> -13822.475 | M28: Pre-tax Profit x Tax Rate forecast
C29: Net income | D29: =SUM(D27:D28) -> 45687 | E29: =SUM(E27:E28) -> 48351 | F29: =SUM(F27:F28) -> 59531 | G29: =SUM(G27:G28) -> 52298.506 | H29: =SUM(H27:H28) -> 56209.901 | I29: =SUM(I27:I28) -> 59962.52 | J29: =SUM(J27:J28) -> 63778.753 | K29: =SUM(K27:K28) -> 67967.319 | M29: Pre-tax Profit less taxes
C31: Depreciation & amortization | D31: 10505 | E31: 10157 | F31: 10903 | G31: =G107 -> 11085.02 | H31: =H107 -> 11711.891 | I31: =I107 -> 12226.381 | J31: =J107 -> 13365.451 | K31: =K107 -> 14603.503 | M31: Reference from D&A schedule
C32: EBITDA | D32: =D23+D31 -> 70529 | E32: =E23+E31 -> 71501 | F32: =F23+F31 -> 81801 | G32: =G23+G31 -> 72788.051 | H32: =H23+H31 -> 79008.989 | I32: =I23+I31 -> 84455.897 | J32: =J23+J31 -> 90578.804 | K32: =K23+K31 -> 97144.578 | M32: EBIT + D&A
C33: Stock based compensation | D33: 4210 | E33: 4840 | F33: 5340 | G33: =F33*(1+G37) -> 5126.4 | H33: =G33*(1+H37) -> 5433.984 | I33: =H33*(1+I37) -> 5808.9289 | J33: =I33*(1+J37) -> 6209.745 | K33: =J33*(1+K37) -> 6638.2174 | M33: WSP assumption: grow SBC in-line with revenue growth
C34: Adjusted EBITDA | D34: =SUM(D32:D33) -> 74739 | E34: =SUM(E32:E33) -> 76341 | F34: =SUM(F32:F33) -> 87141 | G34: =SUM(G32:G33) -> 77914.451 | H34: =SUM(H32:H33) -> 84442.973 | I34: =SUM(I32:I33) -> 90264.826 | J34: =SUM(J32:J33) -> 96788.549 | K34: =SUM(K32:K33) -> 103782.8 | M34: EBITDA + Stock-based compensation
C36: Growth rates & margins
C37: Revenue growth | E37: =E18/D18-1 -> 0.063045182 | F37: =F18/E18-1 -> 0.15861958 | G37: =G175 -> -0.04 | H37: =H175 -> 0.06 | I37: =I175 -> 0.069 | J37: =J175 -> 0.069 | K37: =K175 -> 0.069 | M37: From scenario analysis below
C38: Gross profit margin | D38: =D20/D18 -> 0.39075956 | E38: =E20/E18 -> 0.3846986 | F38: =F20/F18 -> 0.38343719 | G38: =G176 -> 0.378 | H38: =H176 -> 0.381 | I38: =I176 -> 0.382 | J38: =J176 -> 0.382 | K38: =K176 -> 0.382 | M38: From scenario analysis below
C39: R&D % of sales | D39: =-D21/D18 -> 0.046582483 | E39: =-E21/E18 -> 0.050520429 | F39: =-F21/F18 -> 0.053600407 | G39: =G177 -> 0.062 | H39: =H177 -> 0.063 | I39: =I177 -> 0.063 | J39: =J177 -> 0.063 | K39: =K177 -> 0.063 | M39: From scenario analysis below
C40: SG&A % of sales | D40: =-D22/D18 -> 0.065822973 | E40: =-E22/E18 -> 0.066573894 | F40: =-F22/F18 -> 0.062896515 | G40: =G178 -> 0.074 | H40: =H178 -> 0.069 | I40: =I178 -> 0.069 | J40: =J178 -> 0.069 | K40: =K178 -> 0.069 | M40: From scenario analysis below
C41: Tax rate | D41: =-(D28/D27) -> 0.25557257 | E41: =-(E28/E27) -> 0.24556476 | F41: =-(F28/F27) -> 0.18342181 | G41: 0.167 | H41: 0.17 | I41: 0.169 | J41: =I41 -> 0.169 | K41: =J41 -> 0.169 | M41: JP Morgan estimates through 2021: straight-line margin thereafter
C43: BALANCE SHEET
C44: =C15 -> Fiscal year | E44: =E15 -> 2017 | F44: =F15 -> 2018 | G44: =G15 -> 2019 | H44: =H15 -> 2020 | I44: =I15 -> 2021 | J44: =J15 -> 2022 | K44: =K15 -> 2023
C45: =C16 -> Fiscal year end date | E45: =E16 -> 43008 | F45: =F16 -> 43372 | G45: =G16 -> 43738 | H45: =H16 -> 44104 | I45: =I16 -> 44469 | J45: =J16 -> 44834 | K45: =K16 -> 45199
C46: Cash & equivalents, ST and LT marketable securities | E46: =20289+53892+194714 -> 268895 | F46: =25913+40388+170799 -> 237100 | G46: =G91+F46 -> 202199.73 | H46: =H91+G46 -> 176523.72 | I46: =I91+H46 -> 156076.93 | J46: =J91+I46 -> 140273.78 | K46: =K91+J46 -> 129472.46 | M46: Reference from 'net change in cash' line on the cash flow statement
C47: Accounts receivable | E47: 17874 | F47: 23186 | G47: =F47*(1+G37) -> 22258.56 | H47: =G47*(1+H37) -> 23594.074 | I47: =H47*(1+I37) -> 25222.065 | J47: =I47*(1+J37) -> 26962.387 | K47: =J47*(1+K37) -> 28822.792 | M47: Grow in-line with revenue growth
C48: Inventories | E48: 4855 | F48: 3956 | G48: =F48*G19/F19 -> 3831.2507 | H48: =G48*H19/G19 -> 4041.5383 | I48: =H48*I19/H19 -> 4313.4248 | J48: =I48*J19/I19 -> 4611.0512 | K48: =J48*K19/J19 -> 4929.2137 | M48: Grow in-line with cost of sales growth
C49: Other current assets | E49: =17799+13936 -> 31735 | F49: =25809+12087 -> 37896 | G49: =F49*(1+G37) -> 36380.16 | H49: =G49*(1+H37) -> 38562.97 | I49: =H49*(1+I37) -> 41223.815 | J49: =I49*(1+J37) -> 44068.258 | K49: =J49*(1+K37) -> 47108.967 | M49: Grow in-line with revenue growth
C50: Property, plant & equipment | E50: 33783 | F50: 41304 | G50: =G100 -> 45042.86 | H50: =H100 -> 48611.182 | I50: =I100 -> 51947.568 | J50: =J100 -> 55218.714 | K50: =K100 -> 58399.733 | M50: Reference from PP&E schedule
C51: Other non current assets | E51: 18177 | F51: 22283 | G51: =F51*(1+G37) -> 21391.68 | H51: =G51*(1+H37) -> 22675.181 | I51: =H51*(1+I37) -> 24239.768 | J51: =I51*(1+J37) -> 25912.312 | K51: =J51*(1+K37) -> 27700.262 | M51: Grow in-line with revenue growth
C52: Total assets | E52: =SUM(E46:E51) -> 375319 | F52: =SUM(F46:F51) -> 365725 | G52: =SUM(G46:G51) -> 331104.24 | H52: =SUM(H46:H51) -> 314008.67 | I52: =SUM(I46:I51) -> 303023.57 | J52: =SUM(J46:J51) -> 297046.5 | K52: =SUM(K46:K51) -> 296433.42
C54: Accounts payable | E54: 44242 | F54: 55888 | G54: =F54*G19/F19 -> 54125.617 | H54: =G54*H19/G19 -> 57096.435 | I54: =H54*I19/H19 -> 60937.484 | J54: =I54*J19/I19 -> 65142.171 | K54: =J54*K19/J19 -> 69636.98 | M54: Grow in-line with cost of sales growth
C55: Other current liabilities | E55: 30551 | F55: 32687 | G55: =F55*(1+G37) -> 31379.52 | H55: =G55*(1+H37) -> 33262.291 | I55: =H55*(1+I37) -> 35557.389 | J55: =I55*(1+J37) -> 38010.849 | K55: =J55*(1+K37) -> 40633.598 | M55: Grow in-line with revenue growth
C56: Deferred revenue (current and non current) | E56: =7548+2836 -> 10384 | F56: =7543+2797 -> 10340 | G56: =F56*(1+G37) -> 9926.4 | H56: =G56*(1+H37) -> 10521.984 | I56: =H56*(1+I37) -> 11248.001 | J56: =I56*(1+J37) -> 12024.113 | K56: =J56*(1+K37) -> 12853.777 | M56: Grow in-line with revenue growth
C57: Commercial paper / revolver | E57: 11977 | F57: 11964 | G57: =G136 -> 12000 | H57: =H136 -> 12000 | I57: =I136 -> 12000 | J57: =J136 -> 12000 | K57: =K136 -> 12000 | M57: Reference EOP balance from CP/revolver schedule
C58: Long term debt (includes current portion) | E58: =6496+97207 -> 103703 | F58: =8784+93735 -> 102519 | G58: =F58 -> 102519 | H58: =G58 -> 102519 | I58: =H58 -> 102519 | J58: =I58 -> 102519 | K58: =J58 -> 102519 | M58: WSP assumption: straight-line
C59: Other non current liabilities | E59: 40415 | F59: 45180 | G59: =F59*(1+G37) -> 43372.8 | H59: =G59*(1+H37) -> 45975.168 | I59: =H59*(1+I37) -> 49147.455 | J59: =I59*(1+J37) -> 52538.629 | K59: =J59*(1+K37) -> 56163.794 | M59: Grow in-line with revenue growth
C60: Total liabilities | E60: =SUM(E54:E59) -> 241272 | F60: =SUM(F54:F59) -> 258578 | G60: =SUM(G54:G59) -> 253323.34 | H60: =SUM(H54:H59) -> 261374.88 | I60: =SUM(I54:I59) -> 271409.33 | J60: =SUM(J54:J59) -> 282234.76 | K60: =SUM(K54:K59) -> 293807.15
C62: Common stock | E62: 35867 | F62: 40201 | G62: =F62+G33 -> 45327.4 | H62: =G62+H33 -> 50761.384 | I62: =H62+I33 -> 56570.313 | J62: =I62+J33 -> 62780.058 | K62: =J62+K33 -> 69418.275 | M62: Increase by stock-based compensation forecasted in the I/S section
C63: Retained earnings | E63: =98330 -> 98330 | F63: 70400 | G63: =G120 -> 35907.506 | H63: =H120 -> 5326.4074 | I63: =I120 -> -21502.072 | J63: =J120 -> -44514.32 | K63: =K120 -> -63338.001 | M63: Reference from Retained Earnings schedule
C64: Other comprehensive income | E64: -150 | F64: -3454 | G64: =F64 -> -3454 | H64: =G64 -> -3454 | I64: =H64 -> -3454 | J64: =I64 -> -3454 | K64: =J64 -> -3454 | M64: WSP assumption: straight-line
C65: Total equity | E65: =SUM(E62:E64) -> 134047 | F65: =SUM(F62:F64) -> 107147 | G65: =SUM(G62:G64) -> 77780.906 | H65: =SUM(H62:H64) -> 52633.791 | I65: =SUM(I62:I64) -> 31614.241 | J65: =SUM(J62:J64) -> 14811.738 | K65: =SUM(K62:K64) -> 2626.2747
C67: Balance check | E67: =ROUND(E52-E60-E65,3) -> 0 | F67: =ROUND(F52-F60-F65,3) -> 0 | G67: =ROUND(G52-G60-G65,3) -> 0 | H67: =ROUND(H52-H60-H65,3) -> 0 | I67: =ROUND(I52-I60-I65,3) -> 0 | J67: =ROUND(J52-J60-J65,3) -> 0 | K67: =ROUND(K52-K60-K65,3) -> 0
C69: CASH FLOW STATEMENT
C70: =C15 -> Fiscal year | G70: =G15 -> 2019 | H70: =H15 -> 2020 | I70: =I15 -> 2021 | J70: =J15 -> 2022 | K70: =K15 -> 2023
C71: =C16 -> Fiscal year end date | G71: =G16 -> 43738 | H71: =H16 -> 44104 | I71: =I16 -> 44469 | J71: =J16 -> 44834 | K71: =K16 -> 45199
C73: Net income | G73: =G29 -> 52298.506 | H73: =H29 -> 56209.901 | I73: =I29 -> 59962.52 | J73: =J29 -> 63778.753 | K73: =K29 -> 67967.319
C74: Depreciation and amortization | G74: =G31 -> 11085.02 | H74: =H31 -> 11711.891 | I74: =I31 -> 12226.381 | J74: =J31 -> 13365.451 | K74: =K31 -> 14603.503 | M74: Reference from the I/S
C75: Stock based compensation | G75: =G33 -> 5126.4 | H75: =H33 -> 5433.984 | I75: =I33 -> 5808.9289 | J75: =J33 -> 6209.745 | K75: =K33 -> 6638.2174
C76: Decreases / (Increases) in working capital assets | G76: =-1*(SUM(G47:G49)-SUM(F47:F49)) -> 2568.0293 | H76: =-1*(SUM(H47:H49)-SUM(G47:G49)) -> -3728.6108 | I76: =-1*(SUM(I47:I49)-SUM(H47:H49)) -> -4560.7225 | J76: =-1*(SUM(J47:J49)-SUM(I47:I49)) -> -4882.392 | K76: =-1*(SUM(K47:K49)-SUM(J47:J49)) -> -5219.277
C77: Increases / (Decreases) in working capital liabilities | G77: =SUM(G54:G56)-SUM(F54:F56) -> -3483.4631 | H77: =SUM(H54:H56)-SUM(G54:G56) -> 5449.1728 | I77: =SUM(I54:I56)-SUM(H54:H56) -> 6862.1646 | J77: =SUM(J54:J56)-SUM(I54:I56) -> 7434.2583 | K77: =SUM(K54:K56)-SUM(J54:J56) -> 7947.2222
C78: Other non current assets | G78: =-(G112) -> -647.56 | H78: =-(H112) -> -2914.7136 | I78: =-(I112) -> -3308.354 | J78: =-(J112) -> -3536.6304 | K78: =-(K112) -> -3780.6579 | M78: Reference from schedule NOT the B/S: Only include 'Additions' (as outflow)
C79: Other non current liabilities | G79: =G59-F59 -> -1807.2 | H79: =H59-G59 -> 2602.368 | I79: =I59-H59 -> 3172.2866 | J79: =J59-I59 -> 3391.1744 | K79: =K59-J59 -> 3625.1654
C80: Cash from operating activities | G80: =SUM(G73:G79) -> 65139.732 | H80: =SUM(H73:H79) -> 74763.992 | I80: =SUM(I73:I79) -> 80163.205 | J80: =SUM(J73:J79) -> 85760.359 | K80: =SUM(K73:K79) -> 91781.493
C82: Capital expenditures | G82: =-(G98) -> -13285 | H82: =-(H98) -> -13649 | I82: =-(I98) -> -13819 | J82: =-(J98) -> -14772.511 | K82: =-(K98) -> -15791.814 | M82: Reference from PP&E schedule
C83: Cash from investing activities | G83: =IFERROR(G82,"NA") -> -13285 | H83: =IFERROR(H82,"NA") -> -13649 | I83: =IFERROR(I82,"NA") -> -13819 | J83: =IFERROR(J82,"NA") -> -14772.511 | K83: =IFERROR(K82,"NA") -> -15791.814
C85: Long term debt | G85: =G58-F58 -> 0 | H85: =H58-G58 -> 0 | I85: =I58-H58 -> 0 | J85: =J58-I58 -> 0 | K85: =K58-J58 -> 0
C86: Revolver | G86: =G57-F57 -> 36 | H86: =H57-G57 -> 0 | I86: =I57-H57 -> 0 | J86: =J57-I57 -> 0 | K86: =K57-J57 -> 0 | M86: Reference from B/S
C87: Share repurchases | G87: =G119 -> -73056 | H87: =H119 -> -73056 | I87: =I119 -> -73056 | J87: =J119 -> -73056 | K87: =K119 -> -73056 | M87: Reference from Retained Earnings schedule
C88: Common dividends | G88: =G118 -> -13735 | H88: =H118 -> -13735 | I88: =I118 -> -13735 | J88: =J118 -> -13735 | K88: =K118 -> -13735 | M88: Reference from Retained Earnings schedule
C89: Cash from financing activities | G89: =SUM(G85:G88) -> -86755 | H89: =SUM(H85:H88) -> -86791 | I89: =SUM(I85:I88) -> -86791 | J89: =SUM(J85:J88) -> -86791 | K89: =SUM(K85:K88) -> -86791
C91: Net change in cash during period | G91: =G80+G83+G89 -> -34900.268 | H91: =H80+H83+H89 -> -25676.008 | I91: =I80+I83+I89 -> -20446.795 | J91: =J80+J83+J89 -> -15803.152 | K91: =K80+K83+K89 -> -10801.322
C93: PROPERTY, PLANT & EQUIPMENT
C94: =C15 -> Fiscal year | D94: =D15 -> 2016 | E94: =E15 -> 2017 | F94: =F15 -> 2018 | G94: =G15 -> 2019 | H94: =H15 -> 2020 | I94: =I15 -> 2021 | J94: =J15 -> 2022 | K94: =K15 -> 2023
C95: =C16 -> Fiscal year end date | D95: =D16 -> 42643 | E95: =E16 -> 43008 | F95: =F16 -> 43372 | G95: =G16 -> 43738 | H95: =H16 -> 44104 | I95: =I16 -> 44469 | J95: =J16 -> 44834 | K95: =K16 -> 45199
G96: Forecast
C97: Beginning of period | G97: =F100 -> 41304 | H97: =G100 -> 45042.86 | I97: =H100 -> 48611.182 | J97: =I100 -> 51947.568 | K97: =J100 -> 55218.714 | M97: BOP = Previous year EOP
C98: Plus: Capital expenditures | D98: 12734 | E98: 12451 | F98: 13313 | G98: 13285 | H98: 13649 | I98: 13819 | J98: =I98*(1+J37) -> 14772.511 | K98: =J98*(1+K37) -> 15791.814 | M98: JP Morgan through 2021; WSP assumption thereafter
C99: Less: Depreciation | D99: -8300 | E99: -8200 | F99: -9300 | G99: =-(G102*G98) -> -9546.1402 | H99: =-(H102*H98) -> -10080.678 | I99: =-(I102*I98) -> -10482.614 | J99: =-(J102*J98) -> -11501.365 | K99: =-(K102*K98) -> -12610.795 | M99: Capex x 'D&A related to PP&E as a % of capex' ratio (below)
C100: End of period | E100: =E50 -> 33783 | F100: =F50 -> 41304 | G100: =SUM(G97:G99) -> 45042.86 | H100: =SUM(H97:H99) -> 48611.182 | I100: =SUM(I97:I99) -> 51947.568 | J100: =SUM(J97:J99) -> 55218.714 | K100: =SUM(K97:K99) -> 58399.733 | M100: BOP + Capex - Depreciation
M101: Step
C102: D&A related to PP&E as a % of capex | D102: =-(D99/D98) -> 0.65179834 | E102: =-(E99/E98) -> 0.65858164 | F102: =-(F99/F98) -> 0.69856531 | G102: =F102+$M$102 -> 0.71856531 | H102: =G102+$M$102 -> 0.73856531 | I102: =H102+$M$102 -> 0.75856531 | J102: =I102+$M$102 -> 0.77856531 | K102: =J102+$M$102 -> 0.79856531 | M102: 0.02
C104: IMPUTING TOTAL DEPRECIATION & AMORTIZATION
C105: D&A not related to PP&E | D105: =D107+D99 -> 2205 | E105: =E107+E99 -> 1957 | F105: =F107+F99 -> 1603 | G105: =G106*G18 -> 1538.88 | H105: =H106*H18 -> 1631.2128 | I105: =I106*I18 -> 1743.7665 | J105: =J106*J18 -> 1864.0864 | K105: =K106*K18 -> 1992.7083 | M105: Revenue x 'as % of revenue' assumption
